Workbook
Name ETRI_off: #REF!
Name ETRI_on: #REF!
Name markups: #REF!

Sheet READ_ME
A2: Notes on commodity prices in IESA-Opt
A4: Units: | B4: Prices are given in constant EUR2022 except where otherwise specified
A5: Scope: | B5: Exogenous prices are applied to commodities that come from outside the boundary of the optimization. This applies mainly to fuels/energy carriers imported from outside the geographical boundary (NL), but can also apply to commodities purchased from outside the energy system, such as agricultural byproducts, municipal waste, or primary energy carriers with extraction costs not modelled explicitly (like domestic oil or natural gas). In some cases, multiple "commodities" can be defined in IESA-Opt for a single energy carrier. This can be used to approximate a cost curve, or differing transport costs for purchases of the same commodity from different regions.

Sheet Commodity_prices_MEUR2022
A1: Name | B1: Unit | C1: 2022 | D1: 2025 | E1: 2030 | F1: 2035 | G1: 2040 | H1: 2045 | I1: 2050 | J1: Updated | K1: Source | L1: Notes
A2: Imported LPG - Refineries | B2: M€2022/PJ | C2: =AVERAGE('Prices wo taxes'!$FO$98:$FO$148)*1.915/45.2 -> 25.331964 | D2: =(D20*($C$2/$C$20)) -> 23.51929 | E2: =(E20*($C$2/$C$20)) -> 21.713112 | F2: =(F20*($C$2/$C$20)) -> 21.713112 | G2: =(G20*($C$2/$C$20)) -> 16.284834 | H2: =(H20*($C$2/$C$20)) -> 15.645066 | I2: =(I20*($C$2/$C$20)) -> 14.992387 | J2: 45582 | K2: EC Weekly Oil Bulletin | L2: Average of weekly 2022 fuel oil prices for NL reported in oil bulletin. Assumed 45.2 MJ/kg per RVO NCV for LPG, and 1915 l/t as per IEA statistics manual. Future years assume constant ratio for refined products to crude oil.
A3: Imported Naphtha - Refineries | B3: M€2022/PJ | C3: =other_sources!B93 -> 16.619183 | D3: =(D20*($C$3/$C$20)) -> 15.429968 | E3: =(E20*($C$3/$C$20)) -> 14.245014 | F3: =(F20*($C$3/$C$20)) -> 14.245014 | G3: =(G20*($C$3/$C$20)) -> 10.683761 | H3: =(H20*($C$3/$C$20)) -> 10.264037 | I3: =(I20*($C$3/$C$20)) -> 9.8358432 | J3: 45582 | K3: BASF key prices | L3: Base year prices reported by BASF (annual average price for 2022). Projections are based on ratio of naphtha to crude oil price.
A4: Imported Road Fuel - Refineries | B4: M€2022/PJ | C4: =AVERAGE('Prices wo taxes'!$FJ$98:$FJ$148)*1.35/43.3 -> 31.52515 | D4: =(D20*($C$4/$C$20)) -> 29.269311 | E4: =(E20*($C$4/$C$20)) -> 27.021557 | F4: =(F20*($C$4/$C$20)) -> 27.021557 | G4: =(G20*($C$4/$C$20)) -> 20.266168 | H4: =(H20*($C$4/$C$20)) -> 19.469989 | I4: =(I20*($C$4/$C$20)) -> 18.657742 | J4: 45582 | K4: EC Weekly Oil Bulletin | L4: Average of weekly 2022 fuel oil prices for NL reported in oil bulletin. Assumed 43.3 MJ/kg per RVO NCV for gasoline, and 1350 l/t as per IEA statistics manual. Future years assume constant ratio for refined products to crude oil.
A5: Imported Kerosene - Refineries | B5: M€2022/PJ | C5: =AVERAGE('Prices wo taxes'!$FL$98:$FL$148)*1.246/43.92 -> 30.374081 | D5: =(D20*($C$5/$C$20)) -> 28.200609 | E5: =(E20*($C$5/$C$20)) -> 26.034927 | F5: =(F20*($C$5/$C$20)) -> 26.034927 | G5: =(G20*($C$5/$C$20)) -> 19.526195 | H5: =(H20*($C$5/$C$20)) -> 18.759086 | I5: =(I20*($C$5/$C$20)) -> 17.976497 | J5: 45582 | K5: EC Weekly Oil Bulletin; IEA 2024 | L5: Used gas/diesel oil as a proxy. Average of weekly 2022 fuel oil prices for NL reported in oil bulletin. Assumed 43.2 MJ/kg per RVO NCV for gasoline, and 1185 l/t as per IEA statistics manual. Future years assume constant ratio for refined products to crude oil. Well aligned with prices for BE in IEA 2024 (End Use price explorer) - there NL data is only available for 2010.
A6: Imported Fuel Oil - Refineries | B6: M€2022/PJ | C6: =AVERAGE('Prices wo taxes'!$FM$98:$FM$148)/41 -> 17.62704 | D6: =(D20*($C$6/$C$20)) -> 16.365705 | E6: =(E20*($C$6/$C$20)) -> 15.108891 | F6: =(F20*($C$6/$C$20)) -> 15.108891 | G6: =(G20*($C$6/$C$20)) -> 11.331668 | H6: =(H20*($C$6/$C$20)) -> 10.886491 | I6: =(I20*($C$6/$C$20)) -> 10.43233 | J6: 45582 | K6: EC Weekly Oil Bulletin | L6: Average of weekly 2022 fuel oil prices for NL reported in oil bulletin. Assumed 41 MJ/kg per RVO NCV for residual fuel oil. Future years assume constant ratio for refined products to crude oil.
A7: Imported Other Oil Products - Refineries | B7: M€2022/PJ | C7: =C6 -> 17.62704 | D7: =D6 -> 16.365705 | E7: =E6 -> 15.108891 | F7: =F6 -> 15.108891 | G7: =G6 -> 11.331668 | H7: =H6 -> 10.886491 | I7: =I6 -> 10.43233 | J7: 45579 | K7: - | L7: Assumed equal to fuel oil.
A8: Imported Bionaphtha - Refineries | B8: M€2022/PJ | C8: =C3*2 -> 33.238367 | D8: =(($I8-$C8)/($I$1-$C$1))*(D$1-C$1)+C8 -> 31.813865 | E8: =(($I8-$C8)/($I$1-$C$1))*(E$1-D$1)+D8 -> 29.439696 | F8: =(($I8-$C8)/($I$1-$C$1))*(F$1-E$1)+E8 -> 27.065527 | G8: =(($I8-$C8)/($I$1-$C$1))*(G$1-F$1)+F8 -> 24.691358 | H8: =(($I8-$C8)/($I$1-$C$1))*(H$1-G$1)+G8 -> 22.317189 | I8: =C8*0.6 -> 19.94302 | J8: 45629 | K8: TNO 2020; IEA Bioenergy 2020 | L8: Assumed 2x price of fossil equivalent in base year, then 40% decline by 2050.
A9: Imported Bioethanol - Refineries | B9: M€2022/PJ | C9: =1.3/0.789*26.7/Conversions!AC4 -> 41.778153 | D9: =ROUND((C9+E9)/2,2) -> 38.04 | E9: =other_sources!C182 -> 34.3 | F9: =E9 -> 34.3 | G9: =F9 -> 34.3 | H9: =G9 -> 34.3 | I9: =H9 -> 34.3 | J9: 45625 | K9: TNO 2024; IEA 2021 | L9: 2022 price from IEA Renewables Market Report. European ethanol price of $1.3/liter. Ethanol market currently at a high point (see market report) due to supply shocks i.e. high price of key feedstocks like corn. We take TNO 2030 value as the longer term stable value, as price shock effects dissipate. Demand pressures are mixed (US & Europe loosening or keeping stable their blending requirements, while new requirements are implemented elsewhere i.e. India). Assumed equal to 2030/2050 price for bioethanol. Note TNO assumes significant price increase to 2050 (~4x).
A10: Imported Biodiesel - Refineries | B10: M€2022/PJ | C10: =C4*2 -> 63.0503 | D10: =(($I10-$C10)/($I$1-$C$1))*(D$1-C$1)+C10 -> 60.348145 | E10: =(($I10-$C10)/($I$1-$C$1))*(E$1-D$1)+D10 -> 55.844552 | F10: =(($I10-$C10)/($I$1-$C$1))*(F$1-E$1)+E10 -> 51.340959 | G10: =(($I10-$C10)/($I$1-$C$1))*(G$1-F$1)+F10 -> 46.837366 | H10: =(($I10-$C10)/($I$1-$C$1))*(H$1-G$1)+G10 -> 42.333773 | I10: =C10*0.6 -> 37.83018 | J10: 45629 | K10: TNO 2020; IEA Bioenergy 2020 | L10: Assumed 2x price of fossil equivalent in base year, then 40% decline by 2050.
A11: Imported Biokerosene - Refineries | B11: M€2022/PJ | C11: =C5*2 -> 60.748163 | D11: =(($I11-$C11)/($I$1-$C$1))*(D$1-C$1)+C11 -> 58.14467 | E11: =(($I11-$C11)/($I$1-$C$1))*(E$1-D$1)+D11 -> 53.805516 | F11: =(($I11-$C11)/($I$1-$C$1))*(F$1-E$1)+E11 -> 49.466361 | G11: =(($I11-$C11)/($I$1-$C$1))*(G$1-F$1)+F11 -> 45.127207 | H11: =(($I11-$C11)/($I$1-$C$1))*(H$1-G$1)+G11 -> 40.788052 | I11: =C11*0.6 -> 36.448898 | J11: 45629 | K11: TNO 2020; IEA Bioenergy 2020 | L11: Assumed 2x price of fossil equivalent in base year, then 40% decline by 2050.
A12: Imported Bio-LPG - Refineries | B12: M€2022/PJ | C12: =C2*2 -> 50.663929 | D12: =(($I12-$C12)/($I$1-$C$1))*(D$1-C$1)+C12 -> 48.492617 | E12: =(($I12-$C12)/($I$1-$C$1))*(E$1-D$1)+D12 -> 44.873765 | F12: =(($I12-$C12)/($I$1-$C$1))*(F$1-E$1)+E12 -> 41.254913 | G12: =(($I12-$C12)/($I$1-$C$1))*(G$1-F$1)+F12 -> 37.636061 | H12: =(($I12-$C12)/($I$1-$C$1))*(H$1-G$1)+G12 -> 34.017209 | I12: =C12*0.6 -> 30.398357 | J12: 45839 | K12: TNO 2020; IEA Bioenergy 2020 | L12: Assumed 2x price of fossil equivalent in base year, then 40% decline by 2050.
A13: Imported Natural Gas - Final Gas | B13: M€2022/PJ | C13: ='KEV2024'!$F$50 -> 26.878361 | D13: ='KEV2024'!$G$50 -> 15.52972 | E13: ='KEV2024'!$H$50 -> 6.8689145 | F13: =ROUND((E13+G13)/2,2) -> 5.95 | G13: =other_sources!L267 -> 5.028918 | H13: =ROUND((G13+I13)/2,2) -> 5.03 | I13: =other_sources!M267 -> 5.028918 | J13: 45853 | K13: KEV 2024; IEA 2024 | L13: KEV2024 prices used for 2022, 2025, 2030. Note that 2023 prices are used for 2025. IEA APS prices used for 2035-2050. No differentiation of prices for national & imported natural gas. Note that IEA's NZE includes declining global gas prices.
A14: Imported LNG - Final Gas | B14: M€2022/PJ | C14: =C13 -> 26.878361 | D14: =D13 -> 15.52972 | E14: =E13 -> 6.8689145 | F14: =F13 -> 5.95 | G14: =G13 -> 5.028918 | H14: =H13 -> 5.03 | I14: =I13 -> 5.028918 | J14: 45625 | K14: - | L14: Assumed equal to natural gas prices (import & domestic). Highly correlated and close together. (https://globallnghub.com/report-presentation/lng-markets-understanding-the-jkm-ttf-relationship) Average LNG NW Europe price reported by ACER from 1 January 2023-16 October 2024, not used because of volatility of LNG/TTF during the period 2020-2024.
A15: Imported Hydrogen (liquid) - Hydrogen Production | B15: M€2022/PJ | C15: =other_sources!I407 -> 41.250694 | D15: =ROUND((C15+E15)/2,2) -> 40.1 | E15: =other_sources!I403 -> 38.958989 | F15: =ROUND((E15+G15)/2,2) -> 38.58 | G15: =other_sources!I408 -> 38.195087 | H15: =ROUND((G15+I15)/2,2) -> 37.62 | I15: =other_sources!I405 -> 37.049235 | J15: 45628 | K15: IEA 2023 | L15: Assumed expensive liquid H2 import for 2022, less expensive liquid H2 import for 2030, high cost LOHC in 2040, low cost LOHC in 2050. These are based on 2030 costs for NW Europe in IEA NZE scenario, with imports from North Africa and Latin America.
A16: Imported Hydrogen (pipeline) - Hydrogen Production | B16: M€2022/PJ | C16: =other_sources!I410 -> 23.680954 | D16: =ROUND((C16+E16)/2,2) -> 22.34 | E16: =other_sources!I402 -> 21.007298 | F16: =ROUND((E16+G16)/2,2) -> 21.01 | G16: =other_sources!I402 -> 21.007298 | H16: =ROUND((G16+I16)/2,2) -> 21.01 | I16: =other_sources!I402 -> 21.007298 | J16: 45628 | K16: IEA 2023 | L16: 2022 value based on "domestic production" in NW Europe. 2030 to 2050 based on 2030 costs for NW Europe in IEA NZE scenario, with pipeline from North Africa. Assumes pipeline would be in place by 2030, volumes should be limited to reflect available pipeline infrastructure within Europe and from N Africa.
A17: Exported Hydrogen - Hydrogen Production | B17: M€2022/PJ | J17: 45582 | K17: - | L17: Should be set to zero, no assumed hydrogen exports as a baseline. No price needed.
A18: Imported Ammonia - Ammonia Production | B18: M€2022/PJ | C18: =other_sources!I369 -> 34.275681 | D18: =ROUND((C18+E18)/2,2) -> 30.38 | E18: =other_sources!I399 -> 26.481927 | F18: =ROUND((E18+G18)/2,2) -> 25.97 | G18: =ROUND((E18+I18)/2,2) -> 25.46 | H18: =ROUND((G18+I18)/2,2) -> 24.95 | I18: =other_sources!I400 -> 24.444856 | J18: 45628 | K18: Platts 2024; IEA 2023 | L18: Platts Ammonia price data for base year. Used current (2024) values, average of all ammonia types, for 2022. For 2030, IEA source used - import from NA. For 2050, import from Latin America. Based on 2030 costs for NW Europe in IEA NZE scenario.
A19: Imported Coal | B19: M€2022/PJ | C19: ='KEV2024'!F52 -> 11.963684 | D19: ='KEV2024'!G52 -> 8.0823362 | E19: ='KEV2024'!H52 -> 3.0137525 | F19: ='KEV2024'!I52 -> 3.0594154 | G19: =other_sources!L271 -> 2.2584921 | H19: =(G19+I19)/2 -> 2.1920659 | I19: =other_sources!M271 -> 2.1256396 | J19: 45853 | K19: KEV 2024; IEA 2024 | L19: KEV2024 prices used for 2022, 2025, 2030. Note that 2023 prices are used for 2025. Note that KEV draws on CPB & CBS data and EC research. IEA APS prices used for 2035-2050. Steenkool & bruinkool NCV used to calculate price.
A20: Imported Crude Oil | B20: M€2022/PJ | C20: ='KEV2024'!F48 -> 14.70203 | D20: =ROUND((C20+E20)/2,2) -> 13.65 | E20: ='KEV2024'!H48 -> 12.60174 | F20: ='KEV2024'!I48 -> 12.60174 | G20: =other_sources!L263 -> 9.4513053 | H20: =ROUND((G20+I20)/2,2) -> 9.08 | I20: =other_sources!M263 -> 8.7012017 | J20: 45853 | K20: KEV 2024; IEA 2024 | L20: KEV2024 prices used for 2022. Note that KEV draws on CPB & CBS data and EC research. IEA APS prices used for 2030-2050.
A21: National Natural Gas | B21: M€2022/PJ | C21: ='KEV2024'!$F$50 -> 26.878361 | D21: ='KEV2024'!$G$50 -> 15.52972 | E21: ='KEV2024'!$H$50 -> 6.8689145 | F21: =ROUND((E21+G21)/2,2) -> 5.95 | G21: =other_sources!L267 -> 5.028918 | H21: =ROUND((G21+I21)/2,2) -> 5.03 | I21: =other_sources!M267 -> 5.028918 | J21: 45853 | K21: KEV 2024; IEA 2024 | L21: KEV2024 prices used for 2022, 2025, 2030. Note that 2023 prices are used for 2025. IEA APS used for 2035-2050. No differentiation of prices for national & imported natural gas.
A22: Municipal Waste NL | B22: M€2022/PJ | C22: =33.58/9.5 -> 3.5347368 | D22: =39.23/9.5 -> 4.1294737 | E22: =D22 -> 4.1294737 | F22: =E22 -> 4.1294737 | G22: =F22 -> 4.1294737 | H22: =G22 -> 4.1294737 | I22: =H22 -> 4.1294737 | J22: 45582 | K22: CE Delft 2024 | L22: Updated based on 2022 tariff per tonne of municipal waste for 2022, and 2024 used for 2025-2050. Assumed 9.5 MJ/kg municipal waste.
A23: Imported plastic waste | B23: M€2022/Mt | C23: ='average_yearly price of plastic'!$A$15 -> 466.69121 | D23: =C23 -> 466.69121 | E23: =D23 -> 466.69121 | F23: =E23 -> 466.69121 | G23: =F23 -> 466.69121 | H23: =G23 -> 466.69121 | I23: =H23 -> 466.69121 | J23: 45582 | K23: EEA 2024 | L23: Assumed 2022 price will remain constant until 2050. Note increasing trend in recent years. Price given in mass terms (not energy).
A24: Wood (crops, and others) | B24: M€2022/PJ | C24: 10.6 | D24: =C24 -> 10.6 | E24: =D24 -> 10.6 | F24: =E24 -> 10.6 | G24: =F24 -> 10.6 | H24: =G24 -> 10.6 | I24: =H24 -> 10.6 | J24: 45625 | K24: SDE++ 2022 | L24: Assumed equal to Houtpellets, ketels price for woody biomass in 2022.
A25: Imported Wood EU | B25: M€2022/PJ | C25: =other_sources!F178 -> 11.167017 | D25: =C25 -> 11.167017 | E25: =D25 -> 11.167017 | F25: =E25 -> 11.167017 | G25: =F25 -> 11.167017 | H25: =G25 -> 11.167017 | I25: =H25 -> 11.167017 | J25: 45582 | K25: TNO 2024 | L25: Assumed equal to 2030/2050 price for cheap imported woody biomass
A26: Imported Wood America | B26: M€2022/PJ | C26: =other_sources!F179 -> 14.620734 | D26: =C26 -> 14.620734 | E26: =D26 -> 14.620734 | F26: =E26 -> 14.620734 | G26: =F26 -> 14.620734 | H26: =G26 -> 14.620734 | I26: =H26 -> 14.620734 | J26: 45582 | K26: TNO 2024 | L26: Assumed equal to 2030/2050 price for expensive imported woody biomass
A27: Grasscrops | B27: M€2022/PJ | C27: ='[1]COST - NUTS0 EnergyCom'!$E$3303*Conversions!$AA$2/Conversions!$Q$2 -> 9.5931288 | D27: =ROUND((C27+E27)/2,2) -> 9.17 | E27: ='Enspreso_COST - NUTS0 EnergyCom'!E6111*Conversions!$AA$2/Conversions!$Q$2 -> 8.7472214 | F27: =ROUND((E27+G27)/2,2) -> 8.62 | G27: ='Enspreso_COST - NUTS0 EnergyCom'!E8383*Conversions!$AA$2/Conversions!$Q$2 -> 8.4831259 | H27: =ROUND((G27+I27)/2,2) -> 8.36 | I27: ='Enspreso_COST - NUTS0 EnergyCom'!E10655*Conversions!$AA$2/Conversions!$Q$2 -> 8.2424305 | J27: 45834 | K27: JRC 2019 | L27: Based on ENSPRESO costs (ENS Med scenario) for NL. Original source in EUR2010. MINBIOCRP31
A28: Dry organic matter | B28: M€2022/PJ | C28: ='Enspreso_COST - NUTS0 EnergyCom'!$E$3708*Conversions!$AA$2/Conversions!$Q$2 -> 26.799359 | D28: =ROUND((C28+E28)/2,2) -> 32.61 | E28: ='Enspreso_COST - NUTS0 EnergyCom'!$E$5947*Conversions!$AA$2/Conversions!$Q$2 -> 38.426321 | F28: =ROUND((E28+G28)/2,2) -> 38.4 | G28: ='Enspreso_COST - NUTS0 EnergyCom'!$E$8219*Conversions!$AA$2/Conversions!$Q$2 -> 38.376558 | H28: =ROUND((G28+I28)/2,2) -> 38.35 | I28: ='Enspreso_COST - NUTS0 EnergyCom'!$E$10491*Conversions!$AA$2/Conversions!$Q$2 -> 38.325672 | J28: 45834 | K28: JRC 2019 | L28: Based on ENSPRESO costs (ENS Med scenario) for NL. Original source in EUR2010. MINBIORPS1
A29: Wet organic matter | B29: M€2022/PJ | C29: ='Enspreso_COST - NUTS0 EnergyCom'!$E$3709*Conversions!$AA$2/Conversions!$Q$2 -> 8.5386322 | D29: =ROUND((C29+E29)/2,2) -> 8.11 | E29: ='Enspreso_COST - NUTS0 EnergyCom'!$E$5948*Conversions!$AA$2/Conversions!$Q$2 -> 7.684769 | F29: =ROUND((E29+G29)/2,2) -> 7.3 | G29: ='Enspreso_COST - NUTS0 EnergyCom'!$E$8220*Conversions!$AA$2/Conversions!$Q$2 -> 6.9162921 | H29: =ROUND((G29+I29)/2,2) -> 6.57 | I29: ='Enspreso_COST - NUTS0 EnergyCom'!$E$10492*Conversions!$AA$2/Conversions!$Q$2 -> 6.2246629 | J29: 45834 | K29: JRC 2019 | L29: Based on ENSPRESO costs (ENS Med scenario) for NL. Original source in EUR2010. MINBIOSLU1
A30: Manure | B30: M€2022/PJ | C30: ='Enspreso_COST - NUTS0 EnergyCom'!$E$3706*Conversions!$AA$2/Conversions!$Q$2 -> 6.977354 | D30: =ROUND((C30+E30)/2,2) -> 7 | E30: ='Enspreso_COST - NUTS0 EnergyCom'!$E$5945*Conversions!$AA$2/Conversions!$Q$2 -> 7.0240302 | F30: =ROUND((E30+G30)/2,2) -> 7.04 | G30: ='Enspreso_COST - NUTS0 EnergyCom'!$E$8217*Conversions!$AA$2/Conversions!$Q$2 -> 7.0605801 | H30: =ROUND((G30+I30)/2,2) -> 7.07 | I30: ='Enspreso_COST - NUTS0 EnergyCom'!$E$10489*Conversions!$AA$2/Conversions!$Q$2 -> 7.0787377 | J30: 45834 | K30: JRC 2019 | L30: Based on ENSPRESO costs (ENS Med scenario) for NL. Original source in EUR2010. MINBIOGAS1
A31: Sugars | B31: M€2022/PJ | C31: ='Enspreso_COST - NUTS0 EnergyCom'!$E$3701*Conversions!$AA$2/Conversions!$Q$2 -> 4.3284907 | D31: =ROUND((C31+E31)/2,2) -> 4.47 | E31: ='Enspreso_COST - NUTS0 EnergyCom'!$E$5940*Conversions!$AA$2/Conversions!$Q$2 -> 4.6157889 | F31: =ROUND((E31+G31)/2,2) -> 4.63 | G31: ='Enspreso_COST - NUTS0 EnergyCom'!$E$8212*Conversions!$AA$2/Conversions!$Q$2 -> 4.6444136 | H31: =ROUND((G31+I31)/2,2) -> 4.66 | I31: ='Enspreso_COST - NUTS0 EnergyCom'!$E$10484*Conversions!$AA$2/Conversions!$Q$2 -> 4.6730383 | J31: 45834 | K31: JRC 2019 | L31: Based on ENSPRESO costs (ENS Med scenario) for NL. Original source in EUR2010. MINBIOCRP21
A32: Starch | B32: M€2022/PJ | C32: 16 | D32: =ROUND((C32+E32)/2,2) -> 18.5 | E32: 21 | F32: =ROUND((E32+G32)/2,2) -> 21.25 | G32: =ROUND((E32+I32)/2,2) -> 21.5 | H32: =ROUND((G32+I32)/2,2) -> 21.75 | I32: 22 | K32: EU 2017 | L32: Not updated, no updated source available. Uptake mainly driven by (small) potentials. Currently based on Heat Roadmap Europe prices.
A33: Vegetable Oil | B33: M€2022/PJ | C33: ='Enspreso_COST - NUTS0 EnergyCom'!$E$3708*Conversions!$AA$2/Conversions!$Q$2 -> 26.799359 | D33: =ROUND((C33+E33)/2,2) -> 32.61 | E33: ='Enspreso_COST - NUTS0 EnergyCom'!$E$5947*Conversions!$AA$2/Conversions!$Q$2 -> 38.426321 | F33: =ROUND((E33+G33)/2,2) -> 38.4 | G33: ='Enspreso_COST - NUTS0 EnergyCom'!$E$8219*Conversions!$AA$2/Conversions!$Q$2 -> 38.376558 | H33: =ROUND((G33+I33)/2,2) -> 38.35 | I33: ='Enspreso_COST - NUTS0 EnergyCom'!$E$10491*Conversions!$AA$2/Conversions!$Q$2 -> 38.325672 | J33: 45834 | K33: JRC 2019 | L33: Based on ENSPRESO costs (ENS Med scenario) for NL. Original source in EUR2010. MINBIORPS1
A34: Imported Vegetable Oil | B34: M€2022/PJ | C34: =C33*1.1 -> 29.479295 | D34: =D33*1.1 -> 35.871 | E34: =E33*1.1 -> 42.268953 | F34: =F33*1.1 -> 42.24 | G34: =G33*1.1 -> 42.214214 | H34: =H33*1.1 -> 42.185 | I34: =I33*1.1 -> 42.158239 | J34: 45834 | K34: TNO 2024 | L34: Assumed 10% markup for imported vegetable oil from rest of Europe
A35: Imported DRI briquettes | B35: M€2022/Mt | C35: =441/Conversions!AC4 -> 418.80342 | D35: =C35 -> 418.80342 | E35: =D35 -> 418.80342 | F35: =E35 -> 418.80342 | G35: =F35 -> 418.80342 | H35: =G35 -> 418.80342 | I35: =H35 -> 418.80342 | J35: 45748 | K35: Steel on the net.com 2025 | L35: Average of 2022 values. Future prices could be constructed from some relation to iron ore, gas, and coal prices (right now much of global DRI exports come from coal) https://www.steelonthenet.com/files/dri.html
A36: Imported or purchased steel scrap | B36: M€2022/Mt | C36: =Steel_scrap!F36 -> 422.17711 | D36: =C36 -> 422.17711 | E36: =D36 -> 422.17711 | F36: =E36 -> 422.17711 | G36: =F36 -> 422.17711 | H36: =G36 -> 422.17711 | I36: =H36 -> 422.17711 | J36: 45748 | K36: Investing.com (in range of news articles) | L36: https://www.investing.com/commodities/steel-scrap-historical-data
A37: Ethylene imports - Petrochemical industry | B37: M€2022/Mt | C37: =AVERAGE(olefins!T20:T21) -> 1146.9706 | D37: =C37 -> 1146.9706 | E37: =D37 -> 1146.9706 | F37: =E37 -> 1146.9706 | G37: =F37 -> 1146.9706 | H37: =G37 -> 1146.9706 | I37: =H37 -> 1146.9706 | J37: 45748 | K37: CBS 2025 | L37: invoerwaarde & hoeveelheid, normal portland cement, total of EU & non-EU countries, https://opendata.cbs.nl/#/CBS/nl/dataset/81261ned/table?searchKeywords=cement
A38: Propylene imports - Petrochemical industry | B38: M€2022/Mt | C38: =AVERAGE(olefins!T35:T36) -> 1138.7412 | D38: =C38 -> 1138.7412 | E38: =D38 -> 1138.7412 | F38: =E38 -> 1138.7412 | G38: =F38 -> 1138.7412 | H38: =G38 -> 1138.7412 | I38: =H38 -> 1138.7412 | J38: 45748 | K38: CBS 2025 | L38: invoerwaarde & hoeveelheid, normal portland cement, total of EU & non-EU countries, https://opendata.cbs.nl/#/CBS/nl/dataset/81261ned/table?searchKeywords=cement
A39: Butadiene imports - Petrochemical industry | B39: M€2022/Mt | C39: =AVERAGE(olefins!T50:T51) -> 1025.3758 | D39: =C39 -> 1025.3758 | E39: =D39 -> 1025.3758 | F39: =E39 -> 1025.3758 | G39: =F39 -> 1025.3758 | H39: =G39 -> 1025.3758 | I39: =H39 -> 1025.3758 | J39: 45748 | K39: CBS 2025 | L39: invoerwaarde & hoeveelheid, normal portland cement, total of EU & non-EU countries, https://opendata.cbs.nl/#/CBS/nl/dataset/81261ned/table?searchKeywords=cement
A40: Imported aromatics | B40: M€2022/Mt | C40: =C7*40 -> 705.08159 | D40: =D7*40 -> 654.6282 | E40: =E7*40 -> 604.35565 | F40: =F7*40 -> 604.35565 | G40: =G7*40 -> 453.26673 | H40: =H7*40 -> 435.45964 | I40: =I7*40 -> 417.29318 | J40: 45582 | L40: Assumed equal to "other oil product imports." Converted to mass terms with NCV 40 MJ/kg.
A41: Imported or purchased iron ore | B41: M€2022/Mt | C41: =AVERAGE(Sand_ironore!T36,Sand_ironore!T51) -> 119.14917 | D41: =C41 -> 119.14917 | E41: =D41 -> 119.14917 | F41: =E41 -> 119.14917 | G41: =F41 -> 119.14917 | H41: =G41 -> 119.14917 | I41: =H41 -> 119.14917 | J41: 45747 | K41: CBS 2025 | L41: Used jan-august 2022 invoerwaarde & hoeveelheid, normal portland cement, total of EU & non-EU countries, https://opendata.cbs.nl/#/CBS/nl/dataset/81261ned/table?searchKeywords=cement
A42: Stock of end-of-life concrete | B42: M€2022/Mt | C42: 10.5 | D42: 10.5 | E42: 10.5 | F42: 10.5 | G42: 10.5 | H42: 10.5 | I42: 10.5 | J42: 45747 | K42: Zhang et al. 2020 | L42: Table 1, price for secondary material, recycling for concrete industry
A43: Stock of end-of-life ceramic (CTW) | B43: M€2022/Mt | C43: 0 | D43: 0 | E43: 0 | F43: 0 | G43: 0 | H43: 0 | I43: 0 | J43: 45747 | K43: Samadi et al 2020 | L43: Assumed to be available at 0 cost because it is a waste material. This should be increased to consider some transport/logistical cost at least - but no source for that yet
A44: Imported/purchased sand | B44: M€2022/Mt | C44: =AVERAGE(Sand_ironore!T20:T21) -> 17.808764 | D44: =C44 -> 17.808764 | E44: =D44 -> 17.808764 | F44: =E44 -> 17.808764 | G44: =F44 -> 17.808764 | H44: =G44 -> 17.808764 | I44: =H44 -> 17.808764 | J44: 45747 | K44: CBS 2025 | L44: invoerwaarde & hoeveelheid, normal portland cement, total of EU & non-EU countries, https://opendata.cbs.nl/#/CBS/nl/dataset/81261ned/table?searchKeywords=cement
A45: Imported/purchased gravel/aggregate | B45: M€2022/Mt | C45: 10.2 | D45: 10.2 | E45: 10.2 | F45: 10.2 | G45: 10.2 | H45: 10.2 | I45: 10.2 | J45: 45747 | K45: Zhang et al. 2019 | L45: Table 4 cost data (virgin material cost)
A46: Imported/purchased cement | B46: M€2022/Mt | C46: 84.2 | D46: 84.2 | E46: 84.2 | F46: 84.2 | G46: 84.2 | H46: 84.2 | I46: 84.2 | J46: 45747 | K46: CBS 2025 | L46: invoerwaarde & hoeveelheid, normal portland cement, total of EU & non-EU countries, https://opendata.cbs.nl/#/CBS/nl/dataset/81261ned/table?searchKeywords=cement
A47: Stock of recovered cement | B47: M€2022/Mt | C47: 200 | D47: 200 | E47: 200 | F47: 200 | G47: 200 | H47: 200 | I47: 200 | J47: 45747
A48: Limestone | B48: M€2022/Mt | C48: =Limestone!D38 -> 28.299989 | D48: =C48 -> 28.299989 | E48: =D48 -> 28.299989 | F48: =E48 -> 28.299989 | G48: =F48 -> 28.299989 | H48: =G48 -> 28.299989 | I48: =H48 -> 28.299989 | J48: 45747 | K48: CBS 2025 | L48: Used jan-august 2022 invoerwaarde & hoeveelheid, normal portland cement, total of EU & non-EU countries, https://opendata.cbs.nl/#/CBS/nl/dataset/81261ned/table?searchKeywords=cement
A49: Imported salt | B49: M€2022/Mt | C49: =60*Conversions!AC2/Conversions!U2 -> 70.043507 | D49: =C49 -> 70.043507 | E49: =D49 -> 70.043507 | F49: =E49 -> 70.043507 | G49: =F49 -> 70.043507 | H49: =G49 -> 70.043507 | I49: =H49 -> 70.043507 | J49: 45749 | K49: Scherpbier & Eerens 2021 | L49: PBL MIDDEN report Table 4, in range for two main salt types. Converted from 2014 EUR to 2022. https://www.pbl.nl/uploads/default/downloads/pbl-2021-decarbonisation-options-for-the-dutch-salt-industry-3477.pdf
A50: Recycled glass | B50: M€2022/Mt | C50: 68.3 | D50: 68.3 | E50: 68.3 | F50: 68.3 | G50: 68.3 | H50: 68.3 | I50: 68.3 | J50: 45869 | K50: Eurostat 2025 | L50: https://ec.europa.eu/eurostat/statistics-explained/index.php?title=Recycling_%E2%80%93_secondary_material_price_indicator
A51: Imported biomethane | B51: M€2022/PJ | C51: =22*(Conversions!$AB$2/Conversions!$AA$2) -> 22.4752 | D51: =22*(Conversions!$AB$2/Conversions!$AA$2) -> 22.4752 | E51: =22*(Conversions!$AB$2/Conversions!$AA$2) -> 22.4752 | F51: =22*(Conversions!$AB$2/Conversions!$AA$2) -> 22.4752 | G51: =22*(Conversions!$AB$2/Conversions!$AA$2) -> 22.4752 | H51: =22*(Conversions!$AB$2/Conversions!$AA$2) -> 22.4752 | I51: =22*(Conversions!$AB$2/Conversions!$AA$2) -> 22.4752 | J51: 45959 | K51: Cluster model | L51: See email from Julia (1 september)

Sheet Commodity_prices_MEUR2019
A1: Name | B1: Unit | C1: 2022 | D1: 2025 | E1: 2030 | F1: 2035 | G1: 2040 | H1: 2045 | I1: 2050 | J1: Updated | K1: Source | L1: Notes
A2: Imported LPG - Refineries | B2: M€2019/PJ | C2: =Commodity_prices_MEUR2022!C2*(Conversions!$Z$2/Conversions!$AC$2) -> 23.181827 | D2: =Commodity_prices_MEUR2022!D2*(Conversions!$Z$2/Conversions!$AC$2) -> 21.52301 | E2: =Commodity_prices_MEUR2022!E2*(Conversions!$Z$2/Conversions!$AC$2) -> 19.870138 | F2: =Commodity_prices_MEUR2022!F2*(Conversions!$Z$2/Conversions!$AC$2) -> 19.870138 | G2: =Commodity_prices_MEUR2022!G2*(Conversions!$Z$2/Conversions!$AC$2) -> 14.902603 | H2: =Commodity_prices_MEUR2022!H2*(Conversions!$Z$2/Conversions!$AC$2) -> 14.317138 | I2: =Commodity_prices_MEUR2022!I2*(Conversions!$Z$2/Conversions!$AC$2) -> 13.719857 | J2: 45582 | K2: EC Weekly Oil Bulletin | L2: Average of weekly 2022 fuel oil prices for NL reported in oil bulletin. Assumed 45.2 MJ/kg per RVO NCV for LPG, and 1915 l/t as per IEA statistics manual. Future years assume constant ratio for refined products to crude oil.
A3: Imported Naphtha - Refineries | B3: M€2019/PJ | C3: =Commodity_prices_MEUR2022!C3*(Conversions!$Z$2/Conversions!$AC$2) -> 15.208573 | D3: =Commodity_prices_MEUR2022!D3*(Conversions!$Z$2/Conversions!$AC$2) -> 14.120296 | E3: =Commodity_prices_MEUR2022!E3*(Conversions!$Z$2/Conversions!$AC$2) -> 13.03592 | F3: =Commodity_prices_MEUR2022!F3*(Conversions!$Z$2/Conversions!$AC$2) -> 13.03592 | G3: =Commodity_prices_MEUR2022!G3*(Conversions!$Z$2/Conversions!$AC$2) -> 9.77694 | H3: =Commodity_prices_MEUR2022!H3*(Conversions!$Z$2/Conversions!$AC$2) -> 9.3928418 | I3: =Commodity_prices_MEUR2022!I3*(Conversions!$Z$2/Conversions!$AC$2) -> 9.0009924 | J3: 45582 | K3: BASF key prices | L3: Base year prices reported by BASF (annual average price for 2022). Projections are based on ratio of naphtha to crude oil price.
A4: Imported Road Fuel - Refineries | B4: M€2019/PJ | C4: =Commodity_prices_MEUR2022!C4*(Conversions!$Z$2/Conversions!$AC$2) -> 28.849345 | D4: =Commodity_prices_MEUR2022!D4*(Conversions!$Z$2/Conversions!$AC$2) -> 26.784978 | E4: =Commodity_prices_MEUR2022!E4*(Conversions!$Z$2/Conversions!$AC$2) -> 24.72801 | F4: =Commodity_prices_MEUR2022!F4*(Conversions!$Z$2/Conversions!$AC$2) -> 24.72801 | G4: =Commodity_prices_MEUR2022!G4*(Conversions!$Z$2/Conversions!$AC$2) -> 18.546008 | H4: =Commodity_prices_MEUR2022!H4*(Conversions!$Z$2/Conversions!$AC$2) -> 17.817407 | I4: =Commodity_prices_MEUR2022!I4*(Conversions!$Z$2/Conversions!$AC$2) -> 17.074102 | J4: 45582 | K4: EC Weekly Oil Bulletin | L4: Average of weekly 2022 fuel oil prices for NL reported in oil bulletin. Assumed 43.3 MJ/kg per RVO NCV for gasoline, and 1350 l/t as per IEA statistics manual. Future years assume constant ratio for refined products to crude oil.
A5: Imported Kerosene - Refineries | B5: M€2019/PJ | C5: =Commodity_prices_MEUR2022!C5*(Conversions!$Z$2/Conversions!$AC$2) -> 27.795978 | D5: =Commodity_prices_MEUR2022!D5*(Conversions!$Z$2/Conversions!$AC$2) -> 25.806986 | E5: =Commodity_prices_MEUR2022!E5*(Conversions!$Z$2/Conversions!$AC$2) -> 23.825124 | F5: =Commodity_prices_MEUR2022!F5*(Conversions!$Z$2/Conversions!$AC$2) -> 23.825124 | G5: =Commodity_prices_MEUR2022!G5*(Conversions!$Z$2/Conversions!$AC$2) -> 17.868843 | H5: =Commodity_prices_MEUR2022!H5*(Conversions!$Z$2/Conversions!$AC$2) -> 17.166845 | I5: =Commodity_prices_MEUR2022!I5*(Conversions!$Z$2/Conversions!$AC$2) -> 16.450681 | J5: 45582 | K5: EC Weekly Oil Bulletin; IEA 2024 | L5: Used gas/diesel oil as a proxy. Average of weekly 2022 fuel oil prices for NL reported in oil bulletin. Assumed 43.2 MJ/kg per RVO NCV for gasoline, and 1185 l/t as per IEA statistics manual. Future years assume constant ratio for refined products to crude oil. Well aligned with prices for BE in IEA 2024 (End Use price explorer) - there NL data is only available for 2010.
A6: Imported Fuel Oil - Refineries | B6: M€2019/PJ | C6: =Commodity_prices_MEUR2022!C6*(Conversions!$Z$2/Conversions!$AC$2) -> 16.130885 | D6: =Commodity_prices_MEUR2022!D6*(Conversions!$Z$2/Conversions!$AC$2) -> 14.97661 | E6: =Commodity_prices_MEUR2022!E6*(Conversions!$Z$2/Conversions!$AC$2) -> 13.826472 | F6: =Commodity_prices_MEUR2022!F6*(Conversions!$Z$2/Conversions!$AC$2) -> 13.826472 | G6: =Commodity_prices_MEUR2022!G6*(Conversions!$Z$2/Conversions!$AC$2) -> 10.369854 | H6: =Commodity_prices_MEUR2022!H6*(Conversions!$Z$2/Conversions!$AC$2) -> 9.9624628 | I6: =Commodity_prices_MEUR2022!I6*(Conversions!$Z$2/Conversions!$AC$2) -> 9.54685 | J6: 45582 | K6: EC Weekly Oil Bulletin | L6: Average of weekly 2022 fuel oil prices for NL reported in oil bulletin. Assumed 41 MJ/kg per RVO NCV for residual fuel oil. Future years assume constant ratio for refined products to crude oil.
A7: Imported Other Oil Products - Refineries | B7: M€2019/PJ | C7: =Commodity_prices_MEUR2022!C7*(Conversions!$Z$2/Conversions!$AC$2) -> 16.130885 | D7: =Commodity_prices_MEUR2022!D7*(Conversions!$Z$2/Conversions!$AC$2) -> 14.97661 | E7: =Commodity_prices_MEUR2022!E7*(Conversions!$Z$2/Conversions!$AC$2) -> 13.826472 | F7: =Commodity_prices_MEUR2022!F7*(Conversions!$Z$2/Conversions!$AC$2) -> 13.826472 | G7: =Commodity_prices_MEUR2022!G7*(Conversions!$Z$2/Conversions!$AC$2) -> 10.369854 | H7: =Commodity_prices_MEUR2022!H7*(Conversions!$Z$2/Conversions!$AC$2) -> 9.9624628 | I7: =Commodity_prices_MEUR2022!I7*(Conversions!$Z$2/Conversions!$AC$2) -> 9.54685 | J7: 45579 | K7: - | L7: Assumed equal to fuel oil.
A8: Imported Bionaphtha - Refineries | B8: M€2019/PJ | C8: =Commodity_prices_MEUR2022!C8*(Conversions!$Z$2/Conversions!$AC$2) -> 30.417147 | D8: =Commodity_prices_MEUR2022!D8*(Conversions!$Z$2/Conversions!$AC$2) -> 29.113555 | E8: =Commodity_prices_MEUR2022!E8*(Conversions!$Z$2/Conversions!$AC$2) -> 26.940901 | F8: =Commodity_prices_MEUR2022!F8*(Conversions!$Z$2/Conversions!$AC$2) -> 24.768248 | G8: =Commodity_prices_MEUR2022!G8*(Conversions!$Z$2/Conversions!$AC$2) -> 22.595595 | H8: =Commodity_prices_MEUR2022!H8*(Conversions!$Z$2/Conversions!$AC$2) -> 20.422941 | I8: =Commodity_prices_MEUR2022!I8*(Conversions!$Z$2/Conversions!$AC$2) -> 18.250288 | J8: 45629 | K8: TNO 2020; IEA Bioenergy 2020 | L8: Assumed 2x price of fossil equivalent in base year, then 40% decline by 2050.
A9: Imported Bioethanol - Refineries | B9: M€2019/PJ | C9: =Commodity_prices_MEUR2022!C9*(Conversions!$Z$2/Conversions!$AC$2) -> 38.23209 | D9: =Commodity_prices_MEUR2022!D9*(Conversions!$Z$2/Conversions!$AC$2) -> 34.811225 | E9: =Commodity_prices_MEUR2022!E9*(Conversions!$Z$2/Conversions!$AC$2) -> 31.38867 | F9: =Commodity_prices_MEUR2022!F9*(Conversions!$Z$2/Conversions!$AC$2) -> 31.38867 | G9: =Commodity_prices_MEUR2022!G9*(Conversions!$Z$2/Conversions!$AC$2) -> 31.38867 | H9: =Commodity_prices_MEUR2022!H9*(Conversions!$Z$2/Conversions!$AC$2) -> 31.38867 | I9: =Commodity_prices_MEUR2022!I9*(Conversions!$Z$2/Conversions!$AC$2) -> 31.38867 | J9: 45625 | K9: TNO 2024; IEA 2021 | L9: 2022 price from IEA Renewables Market Report. European ethanol price of $1.3/liter. Ethanol market currently at a high point (see market report) due to supply shocks i.e. high price of key feedstocks like corn. We take TNO 2030 value as the longer term stable value, as price shock effects dissipate. Demand pressures are mixed (US & Europe loosening or keeping stable their blending requirements, while new requirements are implemented elsewhere i.e. India). Assumed equal to 2030/2050 price for bioethanol. Note TNO assumes significant price increase to 2050 (~4x).
A10: Imported Biodiesel - Refineries | B10: M€2019/PJ | C10: =Commodity_prices_MEUR2022!C10*(Conversions!$Z$2/Conversions!$AC$2) -> 57.698691 | D10: =Commodity_prices_MEUR2022!D10*(Conversions!$Z$2/Conversions!$AC$2) -> 55.22589 | E10: =Commodity_prices_MEUR2022!E10*(Conversions!$Z$2/Conversions!$AC$2) -> 51.104555 | F10: =Commodity_prices_MEUR2022!F10*(Conversions!$Z$2/Conversions!$AC$2) -> 46.98322 | G10: =Commodity_prices_MEUR2022!G10*(Conversions!$Z$2/Conversions!$AC$2) -> 42.861885 | H10: =Commodity_prices_MEUR2022!H10*(Conversions!$Z$2/Conversions!$AC$2) -> 38.74055 | I10: =Commodity_prices_MEUR2022!I10*(Conversions!$Z$2/Conversions!$AC$2) -> 34.619215 | J10: 45629 | K10: TNO 2020; IEA Bioenergy 2020 | L10: Assumed 2x price of fossil equivalent in base year, then 40% decline by 2050.
A11: Imported Biokerosene - Refineries | B11: M€2019/PJ | C11: =Commodity_prices_MEUR2022!C11*(Conversions!$Z$2/Conversions!$AC$2) -> 55.591955 | D11: =Commodity_prices_MEUR2022!D11*(Conversions!$Z$2/Conversions!$AC$2) -> 53.209443 | E11: =Commodity_prices_MEUR2022!E11*(Conversions!$Z$2/Conversions!$AC$2) -> 49.238589 | F11: =Commodity_prices_MEUR2022!F11*(Conversions!$Z$2/Conversions!$AC$2) -> 45.267735 | G11: =Commodity_prices_MEUR2022!G11*(Conversions!$Z$2/Conversions!$AC$2) -> 41.296881 | H11: =Commodity_prices_MEUR2022!H11*(Conversions!$Z$2/Conversions!$AC$2) -> 37.326027 | I11: =Commodity_prices_MEUR2022!I11*(Conversions!$Z$2/Conversions!$AC$2) -> 33.355173 | J11: 45629 | K11: TNO 2020; IEA Bioenergy 2020 | L11: Assumed 2x price of fossil equivalent in base year, then 40% decline by 2050.
A12: Imported Bio-LPG - Refineries | B12: M€2019/PJ | C12: =Commodity_prices_MEUR2022!C12*(Conversions!$Z$2/Conversions!$AC$2) -> 46.363655 | D12: =Commodity_prices_MEUR2022!D12*(Conversions!$Z$2/Conversions!$AC$2) -> 44.376641 | E12: =Commodity_prices_MEUR2022!E12*(Conversions!$Z$2/Conversions!$AC$2) -> 41.064951 | F12: =Commodity_prices_MEUR2022!F12*(Conversions!$Z$2/Conversions!$AC$2) -> 37.753262 | G12: =Commodity_prices_MEUR2022!G12*(Conversions!$Z$2/Conversions!$AC$2) -> 34.441572 | H12: =Commodity_prices_MEUR2022!H12*(Conversions!$Z$2/Conversions!$AC$2) -> 31.129882 | I12: =Commodity_prices_MEUR2022!I12*(Conversions!$Z$2/Conversions!$AC$2) -> 27.818193 | J12: 45839 | K12: TNO 2020; IEA Bioenergy 2020 | L12: Assumed 2x price of fossil equivalent in base year, then 40% decline by 2050.
A13: Imported Natural Gas - Final Gas | B13: M€2019/PJ | C13: =Commodity_prices_MEUR2022!C13*(Conversions!$Z$2/Conversions!$AC$2) -> 24.596969 | D13: =Commodity_prices_MEUR2022!D13*(Conversions!$Z$2/Conversions!$AC$2) -> 14.211582 | E13: =Commodity_prices_MEUR2022!E13*(Conversions!$Z$2/Conversions!$AC$2) -> 6.285892 | F13: =Commodity_prices_MEUR2022!F13*(Conversions!$Z$2/Conversions!$AC$2) -> 5.4449734 | G13: =Commodity_prices_MEUR2022!G13*(Conversions!$Z$2/Conversions!$AC$2) -> 4.6020714 | H13: =Commodity_prices_MEUR2022!H13*(Conversions!$Z$2/Conversions!$AC$2) -> 4.6030616 | I13: =Commodity_prices_MEUR2022!I13*(Conversions!$Z$2/Conversions!$AC$2) -> 4.6020714 | J13: 45853 | K13: KEV 2024; IEA 2024 | L13: KEV2024 prices used for 2022, 2025, 2030. Note that 2023 prices are used for 2025. IEA APS prices used for 2035-2050. No differentiation of prices for national & imported natural gas. Note that IEA's NZE includes declining global gas prices.
... A31: Sugars | B31: M€2019/PJ | C31: =Commodity_prices_MEUR2022!C31*(Conversions!$Z$2/Conversions!$AC$2) -> 3.9610952 | D31: =Commodity_prices_MEUR2022!D31*(Conversions!$Z$2/Conversions!$AC$2) -> 4.0905935 | E31: =Commodity_prices_MEUR2022!E31*(Conversions!$Z$2/Conversions!$AC$2) -> 4.224008 | F31: =Commodity_prices_MEUR2022!F31*(Conversions!$Z$2/Conversions!$AC$2) -> 4.237013 | G31: =Commodity_prices_MEUR2022!G31*(Conversions!$Z$2/Conversions!$AC$2) -> 4.2502031 | H31: =Commodity_prices_MEUR2022!H31*(Conversions!$Z$2/Conversions!$AC$2) -> 4.2644666 | I31: =Commodity_prices_MEUR2022!I31*(Conversions!$Z$2/Conversions!$AC$2) -> 4.2763983 | J31: 45834 | K31: JRC 2019 | L31: Based on ENSPRESO costs (ENS Med scenario) for NL. Original source in EUR2010. MINBIOCRP21
A32: Starch | B32: M€2019/PJ | C32: =Commodity_prices_MEUR2022!C32*(Conversions!$Z$2/Conversions!$AC$2) -> 14.641945 | D32: =Commodity_prices_MEUR2022!D32*(Conversions!$Z$2/Conversions!$AC$2) -> 16.929749 | E32: =Commodity_prices_MEUR2022!E32*(Conversions!$Z$2/Conversions!$AC$2) -> 19.217553 | F32: =Commodity_prices_MEUR2022!F32*(Conversions!$Z$2/Conversions!$AC$2) -> 19.446334 | G32: =Commodity_prices_MEUR2022!G32*(Conversions!$Z$2/Conversions!$AC$2) -> 19.675114 | H32: =Commodity_prices_MEUR2022!H32*(Conversions!$Z$2/Conversions!$AC$2) -> 19.903895 | I32: =Commodity_prices_MEUR2022!I32*(Conversions!$Z$2/Conversions!$AC$2) -> 20.132675 | K32: EU 2017 | L32: Not updated, no updated source available. Uptake mainly driven by (small) potentials. Currently based on Heat Roadmap Europe prices.
A33: Vegetable Oil | B33: M€2019/PJ | C33: =Commodity_prices_MEUR2022!C33*(Conversions!$Z$2/Conversions!$AC$2) -> 24.524672 | D33: =Commodity_prices_MEUR2022!D33*(Conversions!$Z$2/Conversions!$AC$2) -> 29.842115 | E33: =Commodity_prices_MEUR2022!E33*(Conversions!$Z$2/Conversions!$AC$2) -> 35.164756 | F33: =Commodity_prices_MEUR2022!F33*(Conversions!$Z$2/Conversions!$AC$2) -> 35.140669 | G33: =Commodity_prices_MEUR2022!G33*(Conversions!$Z$2/Conversions!$AC$2) -> 35.119217 | H33: =Commodity_prices_MEUR2022!H33*(Conversions!$Z$2/Conversions!$AC$2) -> 35.094913 | I33: =Commodity_prices_MEUR2022!I33*(Conversions!$Z$2/Conversions!$AC$2) -> 35.07265 | J33: 45582 | K33: TNO 2024 | L33: Based on ENSPRESO costs (ENS Med scenario) for NL. Original source in EUR2010. MINBIORPS1
A34: Imported Vegetable Oil | B34: M€2019/PJ | C34: =Commodity_prices_MEUR2022!C34*(Conversions!$Z$2/Conversions!$AC$2) -> 26.97714 | D34: =Commodity_prices_MEUR2022!D34*(Conversions!$Z$2/Conversions!$AC$2) -> 32.826326 | E34: =Commodity_prices_MEUR2022!E34*(Conversions!$Z$2/Conversions!$AC$2) -> 38.681231 | F34: =Commodity_prices_MEUR2022!F34*(Conversions!$Z$2/Conversions!$AC$2) -> 38.654736 | G34: =Commodity_prices_MEUR2022!G34*(Conversions!$Z$2/Conversions!$AC$2) -> 38.631139 | H34: =Commodity_prices_MEUR2022!H34*(Conversions!$Z$2/Conversions!$AC$2) -> 38.604404 | I34: =Commodity_prices_MEUR2022!I34*(Conversions!$Z$2/Conversions!$AC$2) -> 38.579915 | J34: 45582 | K34: TNO 2024 | L34: Assumed 10% markup for imported vegetable oil from rest of Europe
A35: Imported DRI briquettes | B35: M€2019/Mt | C35: =Commodity_prices_MEUR2022!C35*(Conversions!$Z$2/Conversions!$AC$2) -> 383.25605 | D35: =Commodity_prices_MEUR2022!D35*(Conversions!$Z$2/Conversions!$AC$2) -> 383.25605 | E35: =Commodity_prices_MEUR2022!E35*(Conversions!$Z$2/Conversions!$AC$2) -> 383.25605 | F35: =Commodity_prices_MEUR2022!F35*(Conversions!$Z$2/Conversions!$AC$2) -> 383.25605 | G35: =Commodity_prices_MEUR2022!G35*(Conversions!$Z$2/Conversions!$AC$2) -> 383.25605 | H35: =Commodity_prices_MEUR2022!H35*(Conversions!$Z$2/Conversions!$AC$2) -> 383.25605 | I35: =Commodity_prices_MEUR2022!I35*(Conversions!$Z$2/Conversions!$AC$2) -> 383.25605 | J35: 45748 | K35: Steel on the net.com 2025 | L35: Average of 2022 values. Future prices could be constructed from some relation to iron ore, gas, and coal prices (right now much of global DRI exports come from coal) https://www.steelonthenet.com/files/dri.html
A36: Imported or purchased steel scrap | B36: M€2019/Mt | C36: =Commodity_prices_MEUR2022!C36*(Conversions!$Z$2/Conversions!$AC$2) -> 386.34339 | D36: =Commodity_prices_MEUR2022!D36*(Conversions!$Z$2/Conversions!$AC$2) -> 386.34339 | E36: =Commodity_prices_MEUR2022!E36*(Conversions!$Z$2/Conversions!$AC$2) -> 386.34339 | F36: =Commodity_prices_MEUR2022!F36*(Conversions!$Z$2/Conversions!$AC$2) -> 386.34339 | G36: =Commodity_prices_MEUR2022!G36*(Conversions!$Z$2/Conversions!$AC$2) -> 386.34339 | H36: =Commodity_prices_MEUR2022!H36*(Conversions!$Z$2/Conversions!$AC$2) -> 386.34339 | I36: =Commodity_prices_MEUR2022!I36*(Conversions!$Z$2/Conversions!$AC$2) -> 386.34339 | J36: 45748 | K36: Investing.com (in range of news articles) | L36: https://www.investing.com/commodities/steel-scrap-historical-data
A37: Ethylene imports - Petrochemical industry | B37: M€2019/Mt | C37: =Commodity_prices_MEUR2022!C37*(Conversions!$Z$2/Conversions!$AC$2) -> 1049.6176 | D37: =Commodity_prices_MEUR2022!D37*(Conversions!$Z$2/Conversions!$AC$2) -> 1049.6176 | E37: =Commodity_prices_MEUR2022!E37*(Conversions!$Z$2/Conversions!$AC$2) -> 1049.6176 | F37: =Commodity_prices_MEUR2022!F37*(Conversions!$Z$2/Conversions!$AC$2) -> 1049.6176 | G37: =Commodity_prices_MEUR2022!G37*(Conversions!$Z$2/Conversions!$AC$2) -> 1049.6176 | H37: =Commodity_prices_MEUR2022!H37*(Conversions!$Z$2/Conversions!$AC$2) -> 1049.6176 | I37: =Commodity_prices_MEUR2022!I37*(Conversions!$Z$2/Conversions!$AC$2) -> 1049.6176 | J37: 45748 | K37: CBS 2025 | L37: invoerwaarde & hoeveelheid, normal portland cement, total of EU & non-EU countries, https://opendata.cbs.nl/#/CBS/nl/dataset/81261ned/table?searchKeywords=cement
A38: Propylene imports - Petrochemical industry | B38: M€2019/Mt | C38: =Commodity_prices_MEUR2022!C38*(Conversions!$Z$2/Conversions!$AC$2) -> 1042.0867 | D38: =Commodity_prices_MEUR2022!D38*(Conversions!$Z$2/Conversions!$AC$2) -> 1042.0867 | E38: =Commodity_prices_MEUR2022!E38*(Conversions!$Z$2/Conversions!$AC$2) -> 1042.0867 | F38: =Commodity_prices_MEUR2022!F38*(Conversions!$Z$2/Conversions!$AC$2) -> 1042.0867 | G38: =Commodity_prices_MEUR2022!G38*(Conversions!$Z$2/Conversions!$AC$2) -> 1042.0867 | H38: =Commodity_prices_MEUR2022!H38*(Conversions!$Z$2/Conversions!$AC$2) -> 1042.0867 | I38: =Commodity_prices_MEUR2022!I38*(Conversions!$Z$2/Conversions!$AC$2) -> 1042.0867 | J38: 45748 | K38: CBS 2025 | L38: invoerwaarde & hoeveelheid, normal portland cement, total of EU & non-EU countries, https://opendata.cbs.nl/#/CBS/nl/dataset/81261ned/table?searchKeywords=cement
A39: Butadiene imports - Petrochemical industry | B39: M€2019/Mt | C39: =Commodity_prices_MEUR2022!C39*(Conversions!$Z$2/Conversions!$AC$2) -> 938.34354 | D39: =Commodity_prices_MEUR2022!D39*(Conversions!$Z$2/Conversions!$AC$2) -> 938.34354 | E39: =Commodity_prices_MEUR2022!E39*(Conversions!$Z$2/Conversions!$AC$2) -> 938.34354 | F39: =Commodity_prices_MEUR2022!F39*(Conversions!$Z$2/Conversions!$AC$2) -> 938.34354 | G39: =Commodity_prices_MEUR2022!G39*(Conversions!$Z$2/Conversions!$AC$2) -> 938.34354 | H39: =Commodity_prices_MEUR2022!H39*(Conversions!$Z$2/Conversions!$AC$2) -> 938.34354 | I39: =Commodity_prices_MEUR2022!I39*(Conversions!$Z$2/Conversions!$AC$2) -> 938.34354 | J39: 45748 | K39: CBS 2025 | L39: invoerwaarde & hoeveelheid, normal portland cement, total of EU & non-EU countries, https://opendata.cbs.nl/#/CBS/nl/dataset/81261ned/table?searchKeywords=cement
A40: Imported aromatics | B40: M€2019/Mt | C40: =Commodity_prices_MEUR2022!C40*(Conversions!$Z$2/Conversions!$AC$2) -> 645.23538 | D40: =Commodity_prices_MEUR2022!D40*(Conversions!$Z$2/Conversions!$AC$2) -> 599.0644 | E40: =Commodity_prices_MEUR2022!E40*(Conversions!$Z$2/Conversions!$AC$2) -> 553.0589 | F40: =Commodity_prices_MEUR2022!F40*(Conversions!$Z$2/Conversions!$AC$2) -> 553.0589 | G40: =Commodity_prices_MEUR2022!G40*(Conversions!$Z$2/Conversions!$AC$2) -> 414.79417 | H40: =Commodity_prices_MEUR2022!H40*(Conversions!$Z$2/Conversions!$AC$2) -> 398.49851 | I40: =Commodity_prices_MEUR2022!I40*(Conversions!$Z$2/Conversions!$AC$2) -> 381.874 | J40: 45582 | L40: Assumed equal to "other oil product imports." Converted to mass terms with NCV 40 MJ/kg.
A41: Imported or purchased iron ore | B41: M€2019/Mt | C41: =Commodity_prices_MEUR2022!C41*(Conversions!$Z$2/Conversions!$AC$2) -> 109.03598 | D41: =Commodity_prices_MEUR2022!D41*(Conversions!$Z$2/Conversions!$AC$2) -> 109.03598 | E41: =Commodity_prices_MEUR2022!E41*(Conversions!$Z$2/Conversions!$AC$2) -> 109.03598 | F41: =Commodity_prices_MEUR2022!F41*(Conversions!$Z$2/Conversions!$AC$2) -> 109.03598 | G41: =Commodity_prices_MEUR2022!G41*(Conversions!$Z$2/Conversions!$AC$2) -> 109.03598 | H41: =Commodity_prices_MEUR2022!H41*(Conversions!$Z$2/Conversions!$AC$2) -> 109.03598 | I41: =Commodity_prices_MEUR2022!I41*(Conversions!$Z$2/Conversions!$AC$2) -> 109.03598 | J41: 45747 | K41: CBS 2025 | L41: Used jan-august 2022 invoerwaarde & hoeveelheid, normal portland cement, total of EU & non-EU countries, https://opendata.cbs.nl/#/CBS/nl/dataset/81261ned/table?searchKeywords=cement
A42: Stock of end-of-life concrete | B42: M€2019/Mt | C42: =Commodity_prices_MEUR2022!C42*(Conversions!$Z$2/Conversions!$AC$2) -> 9.6087767 | D42: =Commodity_prices_MEUR2022!D42*(Conversions!$Z$2/Conversions!$AC$2) -> 9.6087767 | E42: =Commodity_prices_MEUR2022!E42*(Conversions!$Z$2/Conversions!$AC$2) -> 9.6087767 | F42: =Commodity_prices_MEUR2022!F42*(Conversions!$Z$2/Conversions!$AC$2) -> 9.6087767 | G42: =Commodity_prices_MEUR2022!G42*(Conversions!$Z$2/Conversions!$AC$2) -> 9.6087767 | H42: =Commodity_prices_MEUR2022!H42*(Conversions!$Z$2/Conversions!$AC$2) -> 9.6087767 | I42: =Commodity_prices_MEUR2022!I42*(Conversions!$Z$2/Conversions!$AC$2) -> 9.6087767 | J42: 45747 | K42: Zhang et al. 2020 | L42: Table 1, price for secondary material, recycling for concrete industry
A43: Stock of end-of-life ceramic (CTW) | B43: M€2019/Mt | C43: =Commodity_prices_MEUR2022!C43*(Conversions!$Z$2/Conversions!$AC$2) -> 0 | D43: =Commodity_prices_MEUR2022!D43*(Conversions!$Z$2/Conversions!$AC$2) -> 0 | E43: =Commodity_prices_MEUR2022!E43*(Conversions!$Z$2/Conversions!$AC$2) -> 0 | F43: =Commodity_prices_MEUR2022!F43*(Conversions!$Z$2/Conversions!$AC$2) -> 0 | G43: =Commodity_prices_MEUR2022!G43*(Conversions!$Z$2/Conversions!$AC$2) -> 0 | H43: =Commodity_prices_MEUR2022!H43*(Conversions!$Z$2/Conversions!$AC$2) -> 0 | I43: =Commodity_prices_MEUR2022!I43*(Conversions!$Z$2/Conversions!$AC$2) -> 0 | J43: 45747 | K43: Samadi et al 2020 | L43: Assumed to be available at 0 cost because it is a waste material. This should be increased to consider some transport/logistical cost at least - but no source for that yet
A44: Imported/purchased sand | B44: M€2019/Mt | C44: =Commodity_prices_MEUR2022!C44*(Conversions!$Z$2/Conversions!$AC$2) -> 16.297184 | D44: =Commodity_prices_MEUR2022!D44*(Conversions!$Z$2/Conversions!$AC$2) -> 16.297184 | E44: =Commodity_prices_MEUR2022!E44*(Conversions!$Z$2/Conversions!$AC$2) -> 16.297184 | F44: =Commodity_prices_MEUR2022!F44*(Conversions!$Z$2/Conversions!$AC$2) -> 16.297184 | G44: =Commodity_prices_MEUR2022!G44*(Conversions!$Z$2/Conversions!$AC$2) -> 16.297184 | H44: =Commodity_prices_MEUR2022!H44*(Conversions!$Z$2/Conversions!$AC$2) -> 16.297184 | I44: =Commodity_prices_MEUR2022!I44*(Conversions!$Z$2/Conversions!$AC$2) -> 16.297184 | J44: 45747 | K44: CBS 2025 | L44: invoerwaarde & hoeveelheid, normal portland cement, total of EU & non-EU countries, https://opendata.cbs.nl/#/CBS/nl/dataset/81261ned/table?searchKeywords=cement
A45: Imported/purchased gravel/aggregate | B45: M€2019/Mt | C45: =Commodity_prices_MEUR2022!C45*(Conversions!$Z$2/Conversions!$AC$2) -> 9.3342402 | D45: =Commodity_prices_MEUR2022!D45*(Conversions!$Z$2/Conversions!$AC$2) -> 9.3342402 | E45: =Commodity_prices_MEUR2022!E45*(Conversions!$Z$2/Conversions!$AC$2) -> 9.3342402 | F45: =Commodity_prices_MEUR2022!F45*(Conversions!$Z$2/Conversions!$AC$2) -> 9.3342402 | G45: =Commodity_prices_MEUR2022!G45*(Conversions!$Z$2/Conversions!$AC$2) -> 9.3342402 | H45: =Commodity_prices_MEUR2022!H45*(Conversions!$Z$2/Conversions!$AC$2) -> 9.3342402 | I45: =Commodity_prices_MEUR2022!I45*(Conversions!$Z$2/Conversions!$AC$2) -> 9.3342402 | J45: 45747 | K45: Zhang et al. 2019 | L45: Table 4 cost data (virgin material cost)
A46: Imported/purchased cement | B46: M€2019/Mt | C46: =Commodity_prices_MEUR2022!C46*(Conversions!$Z$2/Conversions!$AC$2) -> 77.053238 | D46: =Commodity_prices_MEUR2022!D46*(Conversions!$Z$2/Conversions!$AC$2) -> 77.053238 | E46: =Commodity_prices_MEUR2022!E46*(Conversions!$Z$2/Conversions!$AC$2) -> 77.053238 | F46: =Commodity_prices_MEUR2022!F46*(Conversions!$Z$2/Conversions!$AC$2) -> 77.053238 | G46: =Commodity_prices_MEUR2022!G46*(Conversions!$Z$2/Conversions!$AC$2) -> 77.053238 | H46: =Commodity_prices_MEUR2022!H46*(Conversions!$Z$2/Conversions!$AC$2) -> 77.053238 | I46: =Commodity_prices_MEUR2022!I46*(Conversions!$Z$2/Conversions!$AC$2) -> 77.053238 | J46: 45747 | K46: CBS 2025 | L46: invoerwaarde & hoeveelheid, normal portland cement, total of EU & non-EU countries, https://opendata.cbs.nl/#/CBS/nl/dataset/81261ned/table?searchKeywords=cement
A47: Stock of recovered cement | B47: M€2019/Mt | C47: =Commodity_prices_MEUR2022!C47*(Conversions!$Z$2/Conversions!$AC$2) -> 183.02432 | D47: =Commodity_prices_MEUR2022!D47*(Conversions!$Z$2/Conversions!$AC$2) -> 183.02432 | E47: =Commodity_prices_MEUR2022!E47*(Conversions!$Z$2/Conversions!$AC$2) -> 183.02432 | F47: =Commodity_prices_MEUR2022!F47*(Conversions!$Z$2/Conversions!$AC$2) -> 183.02432 | G47: =Commodity_prices_MEUR2022!G47*(Conversions!$Z$2/Conversions!$AC$2) -> 183.02432 | H47: =Commodity_prices_MEUR2022!H47*(Conversions!$Z$2/Conversions!$AC$2) -> 183.02432 | I47: =Commodity_prices_MEUR2022!I47*(Conversions!$Z$2/Conversions!$AC$2) -> 183.02432 | J47: 45747
A48: Limestone | B48: M€2019/Mt | C48: =Commodity_prices_MEUR2022!C48*(Conversions!$Z$2/Conversions!$AC$2) -> 25.897931 | D48: =Commodity_prices_MEUR2022!D48*(Conversions!$Z$2/Conversions!$AC$2) -> 25.897931 | E48: =Commodity_prices_MEUR2022!E48*(Conversions!$Z$2/Conversions!$AC$2) -> 25.897931 | F48: =Commodity_prices_MEUR2022!F48*(Conversions!$Z$2/Conversions!$AC$2) -> 25.897931 | G48: =Commodity_prices_MEUR2022!G48*(Conversions!$Z$2/Conversions!$AC$2) -> 25.897931 | H48: =Commodity_prices_MEUR2022!H48*(Conversions!$Z$2/Conversions!$AC$2) -> 25.897931 | I48: =Commodity_prices_MEUR2022!I48*(Conversions!$Z$2/Conversions!$AC$2) -> 25.897931 | J48: 45747 | K48: CBS 2025 | L48: Used jan-august 2022 invoerwaarde & hoeveelheid, normal portland cement, total of EU & non-EU countries, https://opendata.cbs.nl/#/CBS/nl/dataset/81261ned/table?searchKeywords=cement
A49: Imported salt | B49: M€2019/Mt | C49: =Commodity_prices_MEUR2022!C49*(Conversions!$Z$2/Conversions!$AC$2) -> 64.098325 | D49: =Commodity_prices_MEUR2022!D49*(Conversions!$Z$2/Conversions!$AC$2) -> 64.098325 | E49: =Commodity_prices_MEUR2022!E49*(Conversions!$Z$2/Conversions!$AC$2) -> 64.098325 | F49: =Commodity_prices_MEUR2022!F49*(Conversions!$Z$2/Conversions!$AC$2) -> 64.098325 | G49: =Commodity_prices_MEUR2022!G49*(Conversions!$Z$2/Conversions!$AC$2) -> 64.098325 | H49: =Commodity_prices_MEUR2022!H49*(Conversions!$Z$2/Conversions!$AC$2) -> 64.098325 | I49: =Commodity_prices_MEUR2022!I49*(Conversions!$Z$2/Conversions!$AC$2) -> 64.098325 | J49: 45749 | K49: Scherpbier & Eerens 2021 | L49: PBL MIDDEN report Table 4, in range for two main salt types. Converted from 2014 EUR to 2022. https://www.pbl.nl/uploads/default/downloads/pbl-2021-decarbonisation-options-for-the-dutch-salt-industry-3477.pdf
A50: Recycled glass | B50: M€2019/Mt | C50: =Commodity_prices_MEUR2022!C50*(Conversions!$Z$2/Conversions!$AC$2) -> 62.502804 | D50: =Commodity_prices_MEUR2022!D50*(Conversions!$Z$2/Conversions!$AC$2) -> 62.502804 | E50: =Commodity_prices_MEUR2022!E50*(Conversions!$Z$2/Conversions!$AC$2) -> 62.502804 | F50: =Commodity_prices_MEUR2022!F50*(Conversions!$Z$2/Conversions!$AC$2) -> 62.502804 | G50: =Commodity_prices_MEUR2022!G50*(Conversions!$Z$2/Conversions!$AC$2) -> 62.502804 | H50: =Commodity_prices_MEUR2022!H50*(Conversions!$Z$2/Conversions!$AC$2) -> 62.502804 | I50: =Commodity_prices_MEUR2022!I50*(Conversions!$Z$2/Conversions!$AC$2) -> 62.502804 | J50: 45869 | K50: Eurostat 2025 | L50: https://ec.europa.eu/eurostat/statistics-explained/index.php?title=Recycling_%E2%80%93_secondary_material_price_indicator
A51: Imported biomethane | B51: M€2019/PJ | C51: =22*(Conversions!$Z$2/Conversions!$AA$2) -> 21.6084 | D51: =22*(Conversions!$Z$2/Conversions!$AA$2) -> 21.6084 | E51: =22*(Conversions!$Z$2/Conversions!$AA$2) -> 21.6084 | F51: =22*(Conversions!$Z$2/Conversions!$AA$2) -> 21.6084 | G51: =22*(Conversions!$Z$2/Conversions!$AA$2) -> 21.6084 | H51: =22*(Conversions!$Z$2/Conversions!$AA$2) -> 21.6084 | I51: =22*(Conversions!$Z$2/Conversions!$AA$2) -> 21.6084 | J51: 45959 | K51: Cluster model | L51: See email from Julia (1 september)

Sheet Commodity_prices_index
A1: Name | B1: 2022 | C1: 2025 | D1: 2030 | E1: 2035 | F1: 2040 | G1: 2045 | H1: 2050 | I1: Updated | J1: Source | K1: Notes
A2: Imported LPG - Refineries | B2: 100 | C2: =B2*Commodity_prices_MEUR2022!D2/Commodity_prices_MEUR2022!C2 -> 92.844319 | D2: =C2*Commodity_prices_MEUR2022!E2/Commodity_prices_MEUR2022!D2 -> 85.714286 | E2: =D2*Commodity_prices_MEUR2022!F2/Commodity_prices_MEUR2022!E2 -> 85.714286 | F2: =E2*Commodity_prices_MEUR2022!G2/Commodity_prices_MEUR2022!F2 -> 64.285714 | G2: =F2*Commodity_prices_MEUR2022!H2/Commodity_prices_MEUR2022!G2 -> 61.760177 | H2: =G2*Commodity_prices_MEUR2022!I2/Commodity_prices_MEUR2022!H2 -> 59.183673 | I2: 45582 | J2: EC Weekly Oil Bulletin | K2: Average of weekly 2022 fuel oil prices for NL reported in oil bulletin. Assumed 45.2 MJ/kg per RVO NCV for LPG, and 1915 l/t as per IEA statistics manual. Future years assume constant ratio for refined products to crude oil.
A3: Imported Naphtha - Refineries | B3: 100 | C3: =B3*Commodity_prices_MEUR2022!D3/Commodity_prices_MEUR2022!C3 -> 92.844319 | D3: =C3*Commodity_prices_MEUR2022!E3/Commodity_prices_MEUR2022!D3 -> 85.714286 | E3: =D3*Commodity_prices_MEUR2022!F3/Commodity_prices_MEUR2022!E3 -> 85.714286 | F3: =E3*Commodity_prices_MEUR2022!G3/Commodity_prices_MEUR2022!F3 -> 64.285714 | G3: =F3*Commodity_prices_MEUR2022!H3/Commodity_prices_MEUR2022!G3 -> 61.760177 | H3: =G3*Commodity_prices_MEUR2022!I3/Commodity_prices_MEUR2022!H3 -> 59.183673 | I3: 45582 | J3: BASF key prices | K3: Base year prices reported by BASF (annual average price for 2022). Projections are based on ratio of naphtha to crude oil price.
A4: Imported Road Fuel - Refineries | B4: 100 | C4: =B4*Commodity_prices_MEUR2022!D4/Commodity_prices_MEUR2022!C4 -> 92.844319 | D4: =C4*Commodity_prices_MEUR2022!E4/Commodity_prices_MEUR2022!D4 -> 85.714286 | E4: =D4*Commodity_prices_MEUR2022!F4/Commodity_prices_MEUR2022!E4 -> 85.714286 | F4: =E4*Commodity_prices_MEUR2022!G4/Commodity_prices_MEUR2022!F4 -> 64.285714 | G4: =F4*Commodity_prices_MEUR2022!H4/Commodity_prices_MEUR2022!G4 -> 61.760177 | H4: =G4*Commodity_prices_MEUR2022!I4/Commodity_prices_MEUR2022!H4 -> 59.183673 | I4: 45582 | J4: EC Weekly Oil Bulletin | K4: Average of weekly 2022 fuel oil prices for NL reported in oil bulletin. Assumed 43.3 MJ/kg per RVO NCV for gasoline, and 1350 l/t as per IEA statistics manual. Future years assume constant ratio for refined products to crude oil.
A5: Imported Kerosene - Refineries | B5: 100 | C5: =B5*Commodity_prices_MEUR2022!D5/Commodity_prices_MEUR2022!C5 -> 92.844319 | D5: =C5*Commodity_prices_MEUR2022!E5/Commodity_prices_MEUR2022!D5 -> 85.714286 | E5: =D5*Commodity_prices_MEUR2022!F5/Commodity_prices_MEUR2022!E5 -> 85.714286 | F5: =E5*Commodity_prices_MEUR2022!G5/Commodity_prices_MEUR2022!F5 -> 64.285714 | G5: =F5*Commodity_prices_MEUR2022!H5/Commodity_prices_MEUR2022!G5 -> 61.760177 | H5: =G5*Commodity_prices_MEUR2022!I5/Commodity_prices_MEUR2022!H5 -> 59.183673 | I5: 45582 | J5: EC Weekly Oil Bulletin; IEA 2024 | K5: Used gas/diesel oil as a proxy. Average of weekly 2022 fuel oil prices for NL reported in oil bulletin. Assumed 43.2 MJ/kg per RVO NCV for gasoline, and 1185 l/t as per IEA statistics manual. Future years assume constant ratio for refined products to crude oil. Well aligned with prices for BE in IEA 2024 (End Use price explorer) - there NL data is only available for 2010.
A6: Imported Fuel Oil - Refineries | B6: 100 | C6: =B6*Commodity_prices_MEUR2022!D6/Commodity_prices_MEUR2022!C6 -> 92.844319 | D6: =C6*Commodity_prices_MEUR2022!E6/Commodity_prices_MEUR2022!D6 -> 85.714286 | E6: =D6*Commodity_prices_MEUR2022!F6/Commodity_prices_MEUR2022!E6 -> 85.714286 | F6: =E6*Commodity_prices_MEUR2022!G6/Commodity_prices_MEUR2022!F6 -> 64.285714 | G6: =F6*Commodity_prices_MEUR2022!H6/Commodity_prices_MEUR2022!G6 -> 61.760177 | H6: =G6*Commodity_prices_MEUR2022!I6/Commodity_prices_MEUR2022!H6 -> 59.183673 | I6: 45582 | J6: EC Weekly Oil Bulletin | K6: Average of weekly 2022 fuel oil prices for NL reported in oil bulletin. Assumed 41 MJ/kg per RVO NCV for residual fuel oil. Future years assume constant ratio for refined products to crude oil.
A7: Imported Other Oil Products - Refineries | B7: 100 | C7: =B7*Commodity_prices_MEUR2022!D7/Commodity_prices_MEUR2022!C7 -> 92.844319 | D7: =C7*Commodity_prices_MEUR2022!E7/Commodity_prices_MEUR2022!D7 -> 85.714286 | E7: =D7*Commodity_prices_MEUR2022!F7/Commodity_prices_MEUR2022!E7 -> 85.714286 | F7: =E7*Commodity_prices_MEUR2022!G7/Commodity_prices_MEUR2022!F7 -> 64.285714 | G7: =F7*Commodity_prices_MEUR2022!H7/Commodity_prices_MEUR2022!G7 -> 61.760177 | H7: =G7*Commodity_prices_MEUR2022!I7/Commodity_prices_MEUR2022!H7 -> 59.183673 | I7: 45579 | J7: - | K7: Assumed equal to fuel oil.
A8: Imported Bionaphtha - Refineries | B8: 100 | C8: =B8*Commodity_prices_MEUR2022!D8/Commodity_prices_MEUR2022!C8 -> 95.714286 | D8: =C8*Commodity_prices_MEUR2022!E8/Commodity_prices_MEUR2022!D8 -> 88.571429 | E8: =D8*Commodity_prices_MEUR2022!F8/Commodity_prices_MEUR2022!E8 -> 81.428571 | F8: =E8*Commodity_prices_MEUR2022!G8/Commodity_prices_MEUR2022!F8 -> 74.285714 | G8: =F8*Commodity_prices_MEUR2022!H8/Commodity_prices_MEUR2022!G8 -> 67.142857 | H8: =G8*Commodity_prices_MEUR2022!I8/Commodity_prices_MEUR2022!H8 -> 60 | I8: 45629 | J8: TNO 2020; IEA Bioenergy 2020 | K8: Assumed 2x price of fossil equivalent in base year, then 40% decline by 2050.
A9: Imported Bioethanol - Refineries | B9: 100 | C9: =B9*Commodity_prices_MEUR2022!D9/Commodity_prices_MEUR2022!C9 -> 91.052373 | D9: =C9*Commodity_prices_MEUR2022!E9/Commodity_prices_MEUR2022!D9 -> 82.100326 | E9: =D9*Commodity_prices_MEUR2022!F9/Commodity_prices_MEUR2022!E9 -> 82.100326 | F9: =E9*Commodity_prices_MEUR2022!G9/Commodity_prices_MEUR2022!F9 -> 82.100326 | G9: =F9*Commodity_prices_MEUR2022!H9/Commodity_prices_MEUR2022!G9 -> 82.100326 | H9: =G9*Commodity_prices_MEUR2022!I9/Commodity_prices_MEUR2022!H9 -> 82.100326 | I9: 45625 | J9: TNO 2024; IEA 2021 | K9: 2022 price from IEA Renewables Market Report. European ethanol price of $1.3/liter. Ethanol market currently at a high point (see market report) due to supply shocks i.e. high price of key feedstocks like corn. We take TNO 2030 value as the longer term stable value, as price shock effects dissipate. Demand pressures are mixed (US & Europe loosening or keeping stable their blending requirements, while new requirements are implemented elsewhere i.e. India). Assumed equal to 2030/2050 price for bioethanol. Note TNO assumes significant price increase to 2050 (~4x).
A10: Imported Biodiesel - Refineries | B10: 100 | C10: =B10*Commodity_prices_MEUR2022!D10/Commodity_prices_MEUR2022!C10 -> 95.714286 | D10: =C10*Commodity_prices_MEUR2022!E10/Commodity_prices_MEUR2022!D10 -> 88.571429 | E10: =D10*Commodity_prices_MEUR2022!F10/Commodity_prices_MEUR2022!E10 -> 81.428571 | F10: =E10*Commodity_prices_MEUR2022!G10/Commodity_prices_MEUR2022!F10 -> 74.285714 | G10: =F10*Commodity_prices_MEUR2022!H10/Commodity_prices_MEUR2022!G10 -> 67.142857 | H10: =G10*Commodity_prices_MEUR2022!I10/Commodity_prices_MEUR2022!H10 -> 60 | I10: 45629 | J10: TNO 2020; IEA Bioenergy 2020 | K10: Assumed 2x price of fossil equivalent in base year, then following trend for biomass import prices.
A11: Imported Biokerosene - Refineries | B11: 100 | C11: =B11*Commodity_prices_MEUR2022!D11/Commodity_prices_MEUR2022!C11 -> 95.714286 | D11: =C11*Commodity_prices_MEUR2022!E11/Commodity_prices_MEUR2022!D11 -> 88.571429 | E11: =D11*Commodity_prices_MEUR2022!F11/Commodity_prices_MEUR2022!E11 -> 81.428571 | F11: =E11*Commodity_prices_MEUR2022!G11/Commodity_prices_MEUR2022!F11 -> 74.285714 | G11: =F11*Commodity_prices_MEUR2022!H11/Commodity_prices_MEUR2022!G11 -> 67.142857 | H11: =G11*Commodity_prices_MEUR2022!I11/Commodity_prices_MEUR2022!H11 -> 60 | I11: 45629 | J11: TNO 2020; IEA Bioenergy 2020 | K11: Assumed 2x price of fossil kerosene in base year, then following trend for biomass import prices
A12: Imported Natural Gas - Final Gas | B12: 100 | C12: =B12*Commodity_prices_MEUR2022!D13/Commodity_prices_MEUR2022!C13 -> 57.777778 | D12: =C12*Commodity_prices_MEUR2022!E13/Commodity_prices_MEUR2022!D13 -> 25.555556 | E12: =D12*Commodity_prices_MEUR2022!F13/Commodity_prices_MEUR2022!E13 -> 22.136766 | F12: =E12*Commodity_prices_MEUR2022!G13/Commodity_prices_MEUR2022!F13 -> 18.709913 | G12: =F12*Commodity_prices_MEUR2022!H13/Commodity_prices_MEUR2022!G13 -> 18.713939 | H12: =G12*Commodity_prices_MEUR2022!I13/Commodity_prices_MEUR2022!H13 -> 18.709913 | I12: 45625 | J12: TNO 2024; IEA 2021 | K12: KEV2024 prices used for 2022, 2025, 2030. Note that 2023 prices are used for 2025. IEA NZE prices used for 2035-2050. No differentiation of prices for national & imported natural gas. Note that IEA's NZE includes declining global gas prices.
A13: Imported LNG - Final Gas | B13: 100 | C13: =B13*Commodity_prices_MEUR2022!D14/Commodity_prices_MEUR2022!C14 -> 57.777778 | D13: =C13*Commodity_prices_MEUR2022!E14/Commodity_prices_MEUR2022!D14 -> 25.555556 | E13: =D13*Commodity_prices_MEUR2022!F14/Commodity_prices_MEUR2022!E14 -> 22.136766 | F13: =E13*Commodity_prices_MEUR2022!G14/Commodity_prices_MEUR2022!F14 -> 18.709913 | G13: =F13*Commodity_prices_MEUR2022!H14/Commodity_prices_MEUR2022!G14 -> 18.713939 | H13: =G13*Commodity_prices_MEUR2022!I14/Commodity_prices_MEUR2022!H14 -> 18.709913 | I13: 45625 | J13: - | K13: Assumed equal to natural gas prices (import & domestic). Highly correlated and close together. (https://globallnghub.com/report-presentation/lng-markets-understanding-the-jkm-ttf-relationship) Average LNG NW Europe price reported by ACER from 1 January 2023-16 October 2024, not used because of volatility of LNG/TTF during the period 2020-2024.
A14: Imported Hydrogen (liquid) - Hydrogen Production | B14: 100 | C14: =B14*Commodity_prices_MEUR2022!D15/Commodity_prices_MEUR2022!C15 -> 97.210485 | D14: =C14*Commodity_prices_MEUR2022!E15/Commodity_prices_MEUR2022!D15 -> 94.444444 | E14: =D14*Commodity_prices_MEUR2022!F15/Commodity_prices_MEUR2022!E15 -> 93.525698 | F14: =E14*Commodity_prices_MEUR2022!G15/Commodity_prices_MEUR2022!F15 -> 92.592593 | G14: =F14*Commodity_prices_MEUR2022!H15/Commodity_prices_MEUR2022!G15 -> 91.198465 | H14: =G14*Commodity_prices_MEUR2022!I15/Commodity_prices_MEUR2022!H15 -> 89.814815 | I14: 45628 | J14: IEA 2023 | K14: Assumed expensive liquid H2 import for 2022, less expensive liquid H2 import for 2030, high cost LOHC in 2040, low cost LOHC in 2050. These are based on 2030 costs for NW Europe in IEA NZE scenario, with imports from North Africa and Latin America.
A15: Imported Hydrogen (pipeline) - Hydrogen Production | I15: 45628 | J15: IEA 2023 | K15: 2022 value based on "domestic production" in NW Europe. 2030 to 2050 based on 2030 costs for NW Europe in IEA NZE scenario, with pipeline from North Africa. Assumes pipeline would be in place by 2030, volumes should be limited to reflect available pipeline infrastructure within Europe and from N Africa.
A16: Exported Hydrogen - Hydrogen Production | I16: 45582 | J16: - | K16: Should be set to zero, no assumed hydrogen exports as a baseline. No price needed.
A17: Imported Ammonia - Ammonia Production | B17: 100 | C17: =B17*Commodity_prices_MEUR2022!D18/Commodity_prices_MEUR2022!C18 -> 88.634272 | D17: =C17*Commodity_prices_MEUR2022!E18/Commodity_prices_MEUR2022!D18 -> 77.261565 | E17: =D17*Commodity_prices_MEUR2022!F18/Commodity_prices_MEUR2022!E18 -> 75.768007 | F17: =E17*Commodity_prices_MEUR2022!G18/Commodity_prices_MEUR2022!F18 -> 74.280071 | G17: =F17*Commodity_prices_MEUR2022!H18/Commodity_prices_MEUR2022!G18 -> 72.792136 | H17: =G17*Commodity_prices_MEUR2022!I18/Commodity_prices_MEUR2022!H18 -> 71.318368 | I17: 45628 | J17: Platts 2024; IEA 2023 | K17: Platts Ammonia price data for base year. Used current (2024) values, average of all ammonia types, for 2022. For 2030, IEA source used - import from NA. For 2050, import from Latin America. Based on 2030 costs for NW Europe in IEA NZE scenario.
A18: Imported Coal | B18: 100 | C18: =B18*Commodity_prices_MEUR2022!D19/Commodity_prices_MEUR2022!C19 -> 67.557252 | D18: =C18*Commodity_prices_MEUR2022!E19/Commodity_prices_MEUR2022!D19 -> 25.19084 | E18: =D18*Commodity_prices_MEUR2022!F19/Commodity_prices_MEUR2022!E19 -> 25.572519 | F18: =E18*Commodity_prices_MEUR2022!G19/Commodity_prices_MEUR2022!F19 -> 18.877898 | G18: =F18*Commodity_prices_MEUR2022!H19/Commodity_prices_MEUR2022!G19 -> 18.322666 | H18: =G18*Commodity_prices_MEUR2022!I19/Commodity_prices_MEUR2022!H19 -> 17.767434 | I18: 45625 | J18: TNO 2024; IEA 2021 | K18: KEV2024 prices used for 2022, 2025, 2030. Note that 2023 prices are used for 2025. Note that KEV draws on CPB & CBS data and EC research. IEA NZE prices used for 2035-2050. Steenkool & bruinkool NCV used to calculate price.
A19: Imported Crude Oil | B19: 100 | C19: =B19*Commodity_prices_MEUR2022!D20/Commodity_prices_MEUR2022!C20 -> 92.844319 | D19: =C19*Commodity_prices_MEUR2022!E20/Commodity_prices_MEUR2022!D20 -> 85.714286 | E19: =D19*Commodity_prices_MEUR2022!F20/Commodity_prices_MEUR2022!E20 -> 85.714286 | F19: =E19*Commodity_prices_MEUR2022!G20/Commodity_prices_MEUR2022!F20 -> 64.285714 | G19: =F19*Commodity_prices_MEUR2022!H20/Commodity_prices_MEUR2022!G20 -> 61.760177 | H19: =G19*Commodity_prices_MEUR2022!I20/Commodity_prices_MEUR2022!H20 -> 59.183673 | I19: 45625 | J19: KEV2024; IEA2021 | K19: KEV2024 prices used for 2022. Note that KEV draws on CPB & CBS data and EC research. IEA NZE prices used for 2030-2050.
A20: National Natural Gas | B20: 100 | C20: =B20*Commodity_prices_MEUR2022!D21/Commodity_prices_MEUR2022!C21 -> 57.777778 | D20: =C20*Commodity_prices_MEUR2022!E21/Commodity_prices_MEUR2022!D21 -> 25.555556 | E20: =D20*Commodity_prices_MEUR2022!F21/Commodity_prices_MEUR2022!E21 -> 22.136766 | F20: =E20*Commodity_prices_MEUR2022!G21/Commodity_prices_MEUR2022!F21 -> 18.709913 | G20: =F20*Commodity_prices_MEUR2022!H21/Commodity_prices_MEUR2022!G21 -> 18.713939 | H20: =G20*Commodity_prices_MEUR2022!I21/Commodity_prices_MEUR2022!H21 -> 18.709913 | I20: 45625 | J20: TNO 2024; IEA 2021 | K20: KEV2024 prices used for 2022, 2025, 2030. Note that 2023 prices are used for 2025. IEA NZE used for 2035-2050. No differentiation of prices for national & imported natural gas.
A21: Municipal Waste NL | B21: 100 | C21: =B21*Commodity_prices_MEUR2022!D22/Commodity_prices_MEUR2022!C22 -> 116.82549 | D21: =C21*Commodity_prices_MEUR2022!E22/Commodity_prices_MEUR2022!D22 -> 116.82549 | E21: =D21*Commodity_prices_MEUR2022!F22/Commodity_prices_MEUR2022!E22 -> 116.82549 | F21: =E21*Commodity_prices_MEUR2022!G22/Commodity_prices_MEUR2022!F22 -> 116.82549 | G21: =F21*Commodity_prices_MEUR2022!H22/Commodity_prices_MEUR2022!G22 -> 116.82549 | H21: =G21*Commodity_prices_MEUR2022!I22/Commodity_prices_MEUR2022!H22 -> 116.82549 | I21: 45582 | J21: CE Delft 2024 | K21: Updated based on 2022 tariff per tonne of municipal waste for 2022, and 2024 used for 2025-2050. Assumed 9.5 MJ/kg municipal waste.
A22: Imported plastic waste | B22: 100 | C22: =B22*Commodity_prices_MEUR2022!D23/Commodity_prices_MEUR2022!C23 -> 100 | D22: =C22*Commodity_prices_MEUR2022!E23/Commodity_prices_MEUR2022!D23 -> 100 | E22: =D22*Commodity_prices_MEUR2022!F23/Commodity_prices_MEUR2022!E23 -> 100 | F22: =E22*Commodity_prices_MEUR2022!G23/Commodity_prices_MEUR2022!F23 -> 100 | G22: =F22*Commodity_prices_MEUR2022!H23/Commodity_prices_MEUR2022!G23 -> 100 | H22: =G22*Commodity_prices_MEUR2022!I23/Commodity_prices_MEUR2022!H23 -> 100 | I22: 45582 | J22: EEA 2024 | K22: Assumed 2022 price will remain constant until 2050. Note increasing trend in recent years. Price given in mass terms (not energy).
A23: Wood (crops, and others) | B23: 100 | C23: =B23*Commodity_prices_MEUR2022!D24/Commodity_prices_MEUR2022!C24 -> 100 | D23: =C23*Commodity_prices_MEUR2022!E24/Commodity_prices_MEUR2022!D24 -> 100 | E23: =D23*Commodity_prices_MEUR2022!F24/Commodity_prices_MEUR2022!E24 -> 100 | F23: =E23*Commodity_prices_MEUR2022!G24/Commodity_prices_MEUR2022!F24 -> 100 | G23: =F23*Commodity_prices_MEUR2022!H24/Commodity_prices_MEUR2022!G24 -> 100 | H23: =G23*Commodity_prices_MEUR2022!I24/Commodity_prices_MEUR2022!H24 -> 100 | I23: 45625 | J23: SDE++ 2022 | K23: Assumed equal to Houtpellets, ketels price for woody biomass in 2022.
A24: Imported Wood EU | B24: 100 | C24: =B24*Commodity_prices_MEUR2022!D25/Commodity_prices_MEUR2022!C25 -> 100 | D24: =C24*Commodity_prices_MEUR2022!E25/Commodity_prices_MEUR2022!D25 -> 100 | E24: =D24*Commodity_prices_MEUR2022!F25/Commodity_prices_MEUR2022!E25 -> 100 | F24: =E24*Commodity_prices_MEUR2022!G25/Commodity_prices_MEUR2022!F25 -> 100 | G24: =F24*Commodity_prices_MEUR2022!H25/Commodity_prices_MEUR2022!G25 -> 100 | H24: =G24*Commodity_prices_MEUR2022!I25/Commodity_prices_MEUR2022!H25 -> 100 | I24: 45582 | J24: TNO 2024 | K24: Assumed equal to 2030/2050 price for cheap imported woody biomass
A25: Imported Wood America | B25: 100 | C25: =B25*Commodity_prices_MEUR2022!D26/Commodity_prices_MEUR2022!C26 -> 100 | D25: =C25*Commodity_prices_MEUR2022!E26/Commodity_prices_MEUR2022!D26 -> 100 | E25: =D25*Commodity_prices_MEUR2022!F26/Commodity_prices_MEUR2022!E26 -> 100 | F25: =E25*Commodity_prices_MEUR2022!G26/Commodity_prices_MEUR2022!F26 -> 100 | G25: =F25*Commodity_prices_MEUR2022!H26/Commodity_prices_MEUR2022!G26 -> 100 | H25: =G25*Commodity_prices_MEUR2022!I26/Commodity_prices_MEUR2022!H26 -> 100 | I25: 45582 | J25: TNO 2024 | K25: Assumed equal to 2030/2050 price for expensive imported woody biomass
A26: Grasscrops | B26: 100 | C26: =B26*Commodity_prices_MEUR2022!D27/Commodity_prices_MEUR2022!C27 -> 95.589252 | D26: =C26*Commodity_prices_MEUR2022!E27/Commodity_prices_MEUR2022!D27 -> 91.182153 | E26: =D26*Commodity_prices_MEUR2022!F27/Commodity_prices_MEUR2022!E27 -> 89.855981 | F26: =E26*Commodity_prices_MEUR2022!G27/Commodity_prices_MEUR2022!F27 -> 88.429188 | G26: =F26*Commodity_prices_MEUR2022!H27/Commodity_prices_MEUR2022!G27 -> 87.145708 | H26: =G26*Commodity_prices_MEUR2022!I27/Commodity_prices_MEUR2022!H27 -> 85.920148 | J26: EU 2017 | K26: Not updated, no updated source available. Uptake mainly driven by (small) potentials. Currently based on Heat Roadmap Europe prices.
A27: Dry organic matter | B27: 100 | C27: =B27*Commodity_prices_MEUR2022!D28/Commodity_prices_MEUR2022!C28 -> 121.68201 | D27: =C27*Commodity_prices_MEUR2022!E28/Commodity_prices_MEUR2022!D28 -> 143.38522 | E27: =D27*Commodity_prices_MEUR2022!F28/Commodity_prices_MEUR2022!E28 -> 143.28701 | F27: =E27*Commodity_prices_MEUR2022!G28/Commodity_prices_MEUR2022!F28 -> 143.19954 | G27: =F27*Commodity_prices_MEUR2022!H28/Commodity_prices_MEUR2022!G28 -> 143.10044 | H27: =G27*Commodity_prices_MEUR2022!I28/Commodity_prices_MEUR2022!H28 -> 143.00966 | J27: EU 2017 | K27: Not updated, no updated source available. Uptake mainly driven by (small) potentials. Currently based on Heat Roadmap Europe prices.
A28: Wet organic matter | B28: 100 | C28: =B28*Commodity_prices_MEUR2022!D29/Commodity_prices_MEUR2022!C29 -> 94.980083 | D28: =C28*Commodity_prices_MEUR2022!E29/Commodity_prices_MEUR2022!D29 -> 90 | E28: =D28*Commodity_prices_MEUR2022!F29/Commodity_prices_MEUR2022!E29 -> 85.493786 | F28: =E28*Commodity_prices_MEUR2022!G29/Commodity_prices_MEUR2022!F29 -> 81 | G28: =F28*Commodity_prices_MEUR2022!H29/Commodity_prices_MEUR2022!G29 -> 76.944408 | H28: =G28*Commodity_prices_MEUR2022!I29/Commodity_prices_MEUR2022!H29 -> 72.9 | J28: EU 2017 | K28: Not updated, no updated source available. Uptake mainly driven by (small) potentials. Currently based on Heat Roadmap Europe prices.
A29: Manure | B29: 100 | C29: =B29*Commodity_prices_MEUR2022!D30/Commodity_prices_MEUR2022!C30 -> 100.32456 | D29: =C29*Commodity_prices_MEUR2022!E30/Commodity_prices_MEUR2022!D30 -> 100.66897 | E29: =D29*Commodity_prices_MEUR2022!F30/Commodity_prices_MEUR2022!E30 -> 100.89785 | F29: =E29*Commodity_prices_MEUR2022!G30/Commodity_prices_MEUR2022!F30 -> 101.1928 | G29: =F29*Commodity_prices_MEUR2022!H30/Commodity_prices_MEUR2022!G30 -> 101.32781 | H29: =G29*Commodity_prices_MEUR2022!I30/Commodity_prices_MEUR2022!H30 -> 101.45304 | J29: EU 2017 | K29: Not updated, no updated source available. Uptake mainly driven by (small) potentials. Currently based on Heat Roadmap Europe prices.
A30: Sugars | B30: 100 | C30: =B30*Commodity_prices_MEUR2022!D31/Commodity_prices_MEUR2022!C31 -> 103.26925 | D30: =C30*Commodity_prices_MEUR2022!E31/Commodity_prices_MEUR2022!D31 -> 106.63738 | E30: =D30*Commodity_prices_MEUR2022!F31/Commodity_prices_MEUR2022!E31 -> 106.96569 | F30: =E30*Commodity_prices_MEUR2022!G31/Commodity_prices_MEUR2022!F31 -> 107.29869 | G30: =F30*Commodity_prices_MEUR2022!H31/Commodity_prices_MEUR2022!G31 -> 107.65877 | H30: =G30*Commodity_prices_MEUR2022!I31/Commodity_prices_MEUR2022!H31 -> 107.96 | J30: EU 2017 | K30: Not updated, no updated source available. Uptake mainly driven by (small) potentials. Currently based on Heat Roadmap Europe prices.
A31: Starch | B31: 100 | C31: =B31*Commodity_prices_MEUR2022!D32/Commodity_prices_MEUR2022!C32 -> 115.625 | D31: =C31*Commodity_prices_MEUR2022!E32/Commodity_prices_MEUR2022!D32 -> 131.25 | E31: =D31*Commodity_prices_MEUR2022!F32/Commodity_prices_MEUR2022!E32 -> 132.8125 | F31: =E31*Commodity_prices_MEUR2022!G32/Commodity_prices_MEUR2022!F32 -> 134.375 | G31: =F31*Commodity_prices_MEUR2022!H32/Commodity_prices_MEUR2022!G32 -> 135.9375 | H31: =G31*Commodity_prices_MEUR2022!I32/Commodity_prices_MEUR2022!H32 -> 137.5 | J31: EU 2017 | K31: Not updated, no updated source available. Uptake mainly driven by (small) potentials. Currently based on Heat Roadmap Europe prices.
A32: Vegetable Oil | B32: 100 | C32: =B32*Commodity_prices_MEUR2022!D33/Commodity_prices_MEUR2022!C33 -> 121.68201 | D32: =C32*Commodity_prices_MEUR2022!E33/Commodity_prices_MEUR2022!D33 -> 143.38522 | E32: =D32*Commodity_prices_MEUR2022!F33/Commodity_prices_MEUR2022!E33 -> 143.28701 | F32: =E32*Commodity_prices_MEUR2022!G33/Commodity_prices_MEUR2022!F33 -> 143.19954 | G32: =F32*Commodity_prices_MEUR2022!H33/Commodity_prices_MEUR2022!G33 -> 143.10044 | H32: =G32*Commodity_prices_MEUR2022!I33/Commodity_prices_MEUR2022!H33 -> 143.00966 | I32: 45582 | J32: TNO 2024 | K32: Assumed equal to 2030/2050 price for used cooking oil
A33: Imported Vegetable Oil | B33: 100 | C33: =B33*Commodity_prices_MEUR2022!D34/Commodity_prices_MEUR2022!C34 -> 121.68201 | D33: =C33*Commodity_prices_MEUR2022!E34/Commodity_prices_MEUR2022!D34 -> 143.38522 | E33: =D33*Commodity_prices_MEUR2022!F34/Commodity_prices_MEUR2022!E34 -> 143.28701 | F33: =E33*Commodity_prices_MEUR2022!G34/Commodity_prices_MEUR2022!F34 -> 143.19954 | G33: =F33*Commodity_prices_MEUR2022!H34/Commodity_prices_MEUR2022!G34 -> 143.10044 | H33: =G33*Commodity_prices_MEUR2022!I34/Commodity_prices_MEUR2022!H34 -> 143.00966 | I33: 45582 | J33: TNO 2024 | K33: Assumed equal to 2030/2050 price for used cooking oil
A34: Imported DRI briquettes | B34: 100 | C34: =B34*Commodity_prices_MEUR2022!D35/Commodity_prices_MEUR2022!C35 -> 100 | D34: =C34*Commodity_prices_MEUR2022!E35/Commodity_prices_MEUR2022!D35 -> 100 | E34: =D34*Commodity_prices_MEUR2022!F35/Commodity_prices_MEUR2022!E35 -> 100 | F34: =E34*Commodity_prices_MEUR2022!G35/Commodity_prices_MEUR2022!F35 -> 100 | G34: =F34*Commodity_prices_MEUR2022!H35/Commodity_prices_MEUR2022!G35 -> 100 | H34: =G34*Commodity_prices_MEUR2022!I35/Commodity_prices_MEUR2022!H35 -> 100 | J34: NOT UPDATED
A35: Imported or purchased steel scrap | B35: 100 | C35: =B35*Commodity_prices_MEUR2022!D36/Commodity_prices_MEUR2022!C36 -> 100 | D35: =C35*Commodity_prices_MEUR2022!E36/Commodity_prices_MEUR2022!D36 -> 100 | E35: =D35*Commodity_prices_MEUR2022!F36/Commodity_prices_MEUR2022!E36 -> 100 | F35: =E35*Commodity_prices_MEUR2022!G36/Commodity_prices_MEUR2022!F36 -> 100 | G35: =F35*Commodity_prices_MEUR2022!H36/Commodity_prices_MEUR2022!G36 -> 100 | H35: =G35*Commodity_prices_MEUR2022!I36/Commodity_prices_MEUR2022!H36 -> 100 | J35: NOT UPDATED
A36: Ethylene imports - Petrochemical industry | B36: 100 | C36: =B36*Commodity_prices_MEUR2022!D37/Commodity_prices_MEUR2022!C37 -> 100 | D36: =C36*Commodity_prices_MEUR2022!E37/Commodity_prices_MEUR2022!D37 -> 100 | E36: =D36*Commodity_prices_MEUR2022!F37/Commodity_prices_MEUR2022!E37 -> 100 | F36: =E36*Commodity_prices_MEUR2022!G37/Commodity_prices_MEUR2022!F37 -> 100 | G36: =F36*Commodity_prices_MEUR2022!H37/Commodity_prices_MEUR2022!G37 -> 100 | H36: =G36*Commodity_prices_MEUR2022!I37/Commodity_prices_MEUR2022!H37 -> 100 | J36: NOT UPDATED
A37: Propylene imports - Petrochemical industry | B37: 100 | C37: =B37*Commodity_prices_MEUR2022!D38/Commodity_prices_MEUR2022!C38 -> 100 | D37: =C37*Commodity_prices_MEUR2022!E38/Commodity_prices_MEUR2022!D38 -> 100 | E37: =D37*Commodity_prices_MEUR2022!F38/Commodity_prices_MEUR2022!E38 -> 100 | F37: =E37*Commodity_prices_MEUR2022!G38/Commodity_prices_MEUR2022!F38 -> 100 | G37: =F37*Commodity_prices_MEUR2022!H38/Commodity_prices_MEUR2022!G38 -> 100 | H37: =G37*Commodity_prices_MEUR2022!I38/Commodity_prices_MEUR2022!H38 -> 100 | J37: NOT UPDATED
A38: Butadiene imports - Petrochemical industry | B38: 100 | C38: =B38*Commodity_prices_MEUR2022!D39/Commodity_prices_MEUR2022!C39 -> 100 | D38: =C38*Commodity_prices_MEUR2022!E39/Commodity_prices_MEUR2022!D39 -> 100 | E38: =D38*Commodity_prices_MEUR2022!F39/Commodity_prices_MEUR2022!E39 -> 100 | F38: =E38*Commodity_prices_MEUR2022!G39/Commodity_prices_MEUR2022!F39 -> 100 | G38: =F38*Commodity_prices_MEUR2022!H39/Commodity_prices_MEUR2022!G39 -> 100 | H38: =G38*Commodity_prices_MEUR2022!I39/Commodity_prices_MEUR2022!H39 -> 100 | J38: NOT UPDATED
A39: Imported aromatics | B39: 100 | C39: =B39*Commodity_prices_MEUR2022!D40/Commodity_prices_MEUR2022!C40 -> 92.844319 | D39: =C39*Commodity_prices_MEUR2022!E40/Commodity_prices_MEUR2022!D40 -> 85.714286 | E39: =D39*Commodity_prices_MEUR2022!F40/Commodity_prices_MEUR2022!E40 -> 85.714286 | F39: =E39*Commodity_prices_MEUR2022!G40/Commodity_prices_MEUR2022!F40 -> 64.285714 | G39: =F39*Commodity_prices_MEUR2022!H40/Commodity_prices_MEUR2022!G40 -> 61.760177 | H39: =G39*Commodity_prices_MEUR2022!I40/Commodity_prices_MEUR2022!H40 -> 59.183673 | I39: 45582 | K39: Assumed equal to "other oil product imports." Converted to mass terms with NCV 40 MJ/kg.
A40: Imported or purchased iron ore | B40: 100 | C40: =B40*Commodity_prices_MEUR2022!D41/Commodity_prices_MEUR2022!C41 -> 100 | D40: =C40*Commodity_prices_MEUR2022!E41/Commodity_prices_MEUR2022!D41 -> 100 | E40: =D40*Commodity_prices_MEUR2022!F41/Commodity_prices_MEUR2022!E41 -> 100 | F40: =E40*Commodity_prices_MEUR2022!G41/Commodity_prices_MEUR2022!F41 -> 100 | G40: =F40*Commodity_prices_MEUR2022!H41/Commodity_prices_MEUR2022!G41 -> 100 | H40: =G40*Commodity_prices_MEUR2022!I41/Commodity_prices_MEUR2022!H41 -> 100 | I40: 45583 | J40: IMF 2024 | K40: Assumed constant from 2022 spot price.
A41: Stock of end-of-life concrete | B41: 100 | C41: =B41*Commodity_prices_MEUR2022!D42/Commodity_prices_MEUR2022!C42 -> 100 | D41: =C41*Commodity_prices_MEUR2022!E42/Commodity_prices_MEUR2022!D42 -> 100 | E41: =D41*Commodity_prices_MEUR2022!F42/Commodity_prices_MEUR2022!E42 -> 100 | F41: =E41*Commodity_prices_MEUR2022!G42/Commodity_prices_MEUR2022!F42 -> 100 | G41: =F41*Commodity_prices_MEUR2022!H42/Commodity_prices_MEUR2022!G42 -> 100 | H41: =G41*Commodity_prices_MEUR2022!I42/Commodity_prices_MEUR2022!H42 -> 100 | I41: 45747 | J41: Zhang et al. 2020 | K41: Table 1, price for secondary material, recycling for concrete industry
A42: Stock of end-of-life ceramic (CTW) | I42: 45747 | J42: Samadi et al 2020 | K42: Assumed to be available at 0 cost because it is a waste material. This should be increased to consider some transport/logistical cost at least - but no source for that yet
A43: Imported/purchased sand | B43: 100 | C43: =B43*Commodity_prices_MEUR2022!D44/Commodity_prices_MEUR2022!C44 -> 100 | D43: =C43*Commodity_prices_MEUR2022!E44/Commodity_prices_MEUR2022!D44 -> 100 | E43: =D43*Commodity_prices_MEUR2022!F44/Commodity_prices_MEUR2022!E44 -> 100 | F43: =E43*Commodity_prices_MEUR2022!G44/Commodity_prices_MEUR2022!F44 -> 100 | G43: =F43*Commodity_prices_MEUR2022!H44/Commodity_prices_MEUR2022!G44 -> 100 | H43: =G43*Commodity_prices_MEUR2022!I44/Commodity_prices_MEUR2022!H44 -> 100 | I43: 45747 | J43: Zhang et al. 2019 | K43: Table 4 cost data (virgin material cost)
A44: Imported/purchased gravel/aggregate | B44: 100 | C44: =B44*Commodity_prices_MEUR2022!D45/Commodity_prices_MEUR2022!C45 -> 100 | D44: =C44*Commodity_prices_MEUR2022!E45/Commodity_prices_MEUR2022!D45 -> 100 | E44: =D44*Commodity_prices_MEUR2022!F45/Commodity_prices_MEUR2022!E45 -> 100 | F44: =E44*Commodity_prices_MEUR2022!G45/Commodity_prices_MEUR2022!F45 -> 100 | G44: =F44*Commodity_prices_MEUR2022!H45/Commodity_prices_MEUR2022!G45 -> 100 | H44: =G44*Commodity_prices_MEUR2022!I45/Commodity_prices_MEUR2022!H45 -> 100 | I44: 45747 | J44: Zhang et al. 2019 | K44: Table 4 cost data (virgin material cost)
A45: Imported/purchased cement | B45: 100 | C45: =B45*Commodity_prices_MEUR2022!D46/Commodity_prices_MEUR2022!C46 -> 100 | D45: =C45*Commodity_prices_MEUR2022!E46/Commodity_prices_MEUR2022!D46 -> 100 | E45: =D45*Commodity_prices_MEUR2022!F46/Commodity_prices_MEUR2022!E46 -> 100 | F45: =E45*Commodity_prices_MEUR2022!G46/Commodity_prices_MEUR2022!F46 -> 100 | G45: =F45*Commodity_prices_MEUR2022!H46/Commodity_prices_MEUR2022!G46 -> 100 | H45: =G45*Commodity_prices_MEUR2022!I46/Commodity_prices_MEUR2022!H46 -> 100 | I45: 45747 | J45: CBS 2025 | K45: invoerwaarde & hoeveelheid, normal portland cement, total of EU & non-EU countries, https://opendata.cbs.nl/#/CBS/nl/dataset/81261ned/table?searchKeywords=cement
A46: Stock of recovered cement | B46: 100 | C46: =B46*Commodity_prices_MEUR2022!D47/Commodity_prices_MEUR2022!C47 -> 100 | D46: =C46*Commodity_prices_MEUR2022!E47/Commodity_prices_MEUR2022!D47 -> 100 | E46: =D46*Commodity_prices_MEUR2022!F47/Commodity_prices_MEUR2022!E47 -> 100 | F46: =E46*Commodity_prices_MEUR2022!G47/Commodity_prices_MEUR2022!F47 -> 100 | G46: =F46*Commodity_prices_MEUR2022!H47/Commodity_prices_MEUR2022!G47 -> 100 | H46: =G46*Commodity_prices_MEUR2022!I47/Commodity_prices_MEUR2022!H47 -> 100 | I46: 45747

Sheet Technologies_2023pricesfromIESA
A2: Tech. Specifics | H2: Cost data | AH2: Operation data | AL2: CHP flexibility data | AR2: Asymetric flexibility | AU2: Hydro Reservoirs | AX2: Flexibility data | BG2: Network buffers | BK2: Technology Potentials | BO2: Planned decommissioning | BU2: Minimum stock in a year | CB2: Maximum stock in a year | CI2: Data source | CJ2: Reference Volume of the main activity | CQ2: No new investments | CX2: No economic/early decommissioning
A3: Tech_ID | B3: Category | C3: Sector | D3: Sub-sector | E3: Main Activity | F3: Name | G3: UoC | H3: Investment | I3: Investment | J3: Investment | K3: Investment | L3: Investment | M3: Investment | N3: Investment | O3: Salvage value | P3: Fixed O&M | Q3: Fixed O&M | R3: Fixed O&M | S3: Fixed O&M | T3: Fixed O&M | U3: Fixed O&M | V3: Fixed O&M | W3: Variable O&M | X3: Variable O&M | Y3: Variable O&M | Z3: Variable O&M | AA3: Variable O&M | AB3: Variable O&M | AC3: Variable O&M | AD3: WACC | AE3: Const. Time | AF3: Ec. Lifetime | AG3: Tech. Lifetime | AH3: Cap2Act | AI3: Type of process | AJ3: Type of profile | AK3: Ramping constraint | AL3: CHP product | AM3: CHP fuel | AN3: CHP η | AO3: CHP heat balance range | AP3: CHP deviation in USE tolerance | AQ3: CHP deviation in P/H RATIO tolerance | AR3: Shedding capacity | AS3: Shedding volume | AT3: Range for demand curtailing | AU3: Pump to head ratio | AV3: Reservoir capacity | AW3: Pumping losses | AX3: Form of Flexibility | AY3: Benefited activity | AZ3: Flexible installed capacity | BA3: Storage capacity | BB3: Shifting range | BC3: Losses | BD3: Non-negotiable load | BE3: Average journey duration | BF3: Average speed | BG3: Benefited activity | BH3: Upward capacity | BI3: Downward capacity | BJ3: Buffer capacity | BK3: Apply max constraint | BL3: Current installed capacity needed | BM3: Maximum technology deployment | BN3: Current Installed Capacity | CB3: 0 | CC3: 0 | CD3: 0.1 | CE3: 0.2 | CF3: 0.5 | CG3: 1 | CH3: 1 | CJ3: (also works as an auxiliary) | CQ3: 1 = no new investments allowed in this year | CX3: 1 = no early decommissioning allowed in this year
H4: 2020 | I4: 2025 | J4: 2030 | K4: 2035 | L4: 2040 | M4: 2045 | N4: 2050 | O4: % of CAPEX | P4: 2020 | Q4: 2025 | R4: 2030 | S4: 2035 | T4: 2040 | U4: 2045 | V4: 2050 | W4: 2020 | X4: 2025 | Y4: 2030 | Z4: 2035 | AA4: 2040 | AB4: 2045 | AC4: 2050 | AL4: (only for CHP) | AM4: (only for CHP) | AN4: (only for CHP) | AO4: (only for CHP) | AP4: (only for CHP) | AQ4: (only for CHP) | AU4: (zero if not PS) | AV4: (hours of discharge) | BA4: (hours of charge) | BJ4: (in relation to discharge) | BL4: (not in the model) | BO4: 1 | BP4: 2 | BQ4: 3 | BR4: 4 | BS4: 5 | BT4: 6 | CB4: 0 | CC4: 0.5 | CD4: 1 | CE4: 1 | CF4: 1 | CG4: 1 | CH4: 1 | CM4: (no AIMMS) | CT4: [y/n] | DA4: [y/n]
AI5: (mandatory) | AJ5: (mandatory) | AK5: (only for Hourly dispatch) | BA5: (only if storage is present) | BE5: (only for flexible electric transport) | BF5: (only for flexible electric transport) | BN5: 2020 | BO5: 2025 | BP5: 2030 | BQ5: 2035 | BR5: 2040 | BS5: 2045 | BT5: 2050 | BU5: 2020 | BV5: 2025 | BW5: 2030 | BX5: 2035 | BY5: 2040 | BZ5: 2045 | CA5: 2050 | CB5: 2020 | CC5: 2025 | CD5: 2030 | CE5: 2035 | CF5: 2040 | CG5: 2045 | CH5: 2050 | CQ5: 2020 | CR5: 2025 | CS5: 2030 | CT5: 2035 | CU5: 2040 | CV5: 2045 | CW5: 2050 | CX5: 2020 | CY5: 2025 | CZ5: 2030 | DA5: 2035 | DB5: 2040 | DC5: 2045 | DD5: 2050
H6: [M€/UoC] | I6: [M€/UoC] | J6: [M€/UoC] | K6: [M€/UoC] | L6: [M€/UoC] | M6: [M€/UoC] | N6: [M€/UoC] | O6: [%] | P6: [M€/UoC-y] | Q6: [M€/UoC-y] | R6: [M€/UoC-y] | S6: [M€/UoC-y] | T6: [M€/UoC-y] | U6: [M€/UoC-y] | V6: [M€/UoC-y] | W6: [M€/UoA] | X6: [M€/UoA] | Y6: [M€/UoA] | Z6: [M€/UoA] | AA6: [M€/UoA] | AB6: [M€/UoA] | AC6: [M€/UoA] | AD6: [1/y] | AE6: [y] | AF6: [y] | AG6: [y] | AH6: [UoA/UoC-y] | AI6: [type] | AJ6: [type] | AK6: [%] | AL6: [activity] | AM6: [activity] | AN6: [%] | AO6: [UoR] | AP6: [%] | AQ6: [%] | AR6: [PJ/UoC-h] | AS6: [%] | AT6: [UoR] | AU6: [%] | AV6: [h] | AW6: [%] | AX6: [type] | AY6: [activity] | AZ6: [PJ/UoC-h] | BA6: [h] | BB6: [UoR] | BC6: [%] | BD6: [%] | BE6: [h] | BF6: [UoA/UoC-h] | BG6: [activity] | BH6: [PJ/UoC-d] | BI6: [PJ/UoC-d] | BJ6: [d] | BK6: [y/n] | BL6: [y/n] | BM6: [UoC/5y] | BN6: [UoC] | BO6: [UoC] | BP6: [UoC] | BQ6: [UoC] | BR6: [UoC] | BS6: [UoC] | BT6: [UoC] | BU6: [UoC] | BV6: [UoC] | BW6: [UoC] | BX6: [UoC] | BY6: [UoC] | BZ6: [UoC] | CA6: [UoC] | CB6: [UoC] | CC6: [UoC] | CD6: [UoC] | CE6: [UoC] | CF6: [UoC] | CG6: [UoC] | CH6: [UoC] | CI6: [ref No.] | CJ6: 2020 | CK6: 2025 | CL6: 2030 | CM6: 2035 | CN6: 2040 | CO6: 2045 | CP6: 2050 | CQ6: [y/n] | CR6: [y/n] | CS6: [y/n] | CT6: [y/n] | CU6: [y/n] | CV6: [y/n] | CW6: [y/n] | CX6: [y/n] | CY6: [y/n] | CZ6: [y/n] | DA6: [y/n] | DB6: [y/n] | DC6: [y/n] | DD6: [y/n]
A7: Res01_01 | B7: Final | C7: Residential | D7: Appliances | E7: Electricity demand - Residential | F7: Dummy standard electricity consumption - Residential | G7: [PJ/y] | H7: 0 | I7: 0 | J7: 0 | K7: 0 | L7: 0 | M7: 0 | N7: 0 | O7: 0 | P7: 0 | Q7: 0 | R7: 0 | S7: 0 | T7: 0 | U7: 0 | V7: 0 | W7: 0 | X7: 0 | Y7: 0 | Z7: 0 | AA7: 0 | AB7: 0 | AC7: 0 | AD7: 0.05 | AE7: 0 | AF7: 1 | AG7: 1 | AH7: 1 | AI7: Operation | AJ7: Standard Load | AX7: none | BK7: 0 | BL7: =IF(AG7=1,0,1) -> 0 | BO7: 0 | BP7: 0 | BQ7: 0 | BR7: 0 | BS7: 0 | BT7: 0 | BU7: =IF(BL7=1,BN7,0) -> 0 | CB7: =CJ7 -> 84 | CC7: =CK7 -> 86 | CD7: =CL7 -> 88 | CE7: =CM7 -> 90 | CF7: =CN7 -> 92 | CG7: =CO7 -> 94 | CH7: =CP7 -> 96 | CI7: [1],[12] | CJ7: =VLOOKUP($E7,[2]Activities!$A$9:$I$162,3,FALSE)/$AH7 -> 84 | CK7: =VLOOKUP($E7,[2]Activities!$A$9:$I$162,4,FALSE)/$AH7 -> 86 | CL7: =VLOOKUP($E7,[2]Activities!$A$9:$I$162,5,FALSE)/$AH7 -> 88 | CM7: =VLOOKUP($E7,[2]Activities!$A$9:$I$162,6,FALSE)/$AH7 -> 90 | CN7: =VLOOKUP($E7,[2]Activities!$A$9:$I$162,7,FALSE)/$AH7 -> 92 | CO7: =VLOOKUP($E7,[2]Activities!$A$9:$I$162,8,FALSE)/$AH7 -> 94 | CP7: =VLOOKUP($E7,[2]Activities!$A$9:$I$162,9,FALSE)/$AH7 -> 96
A8: Res01_02 | B8: Final | C8: Residential | D8: Appliances | E8: Electricity demand - Residential | F8: Flexible standard electricity consumption - Residential | G8: [PJ/y] | H8: 0.5 | I8: 0.5 | J8: 0.5 | K8: 0.3 | L8: 0.1 | M8: 0 | N8: 0 | O8: 0.9 | P8: 0 | Q8: 0 | R8: 0 | S8: 0 | T8: 0 | U8: 0 | V8: 0 | W8: 0 | X8: 0 | Y8: 0 | Z8: 0 | AA8: 0 | AB8: 0 | AC8: 0 | AD8: 0.05 | AE8: 0 | AF8: 15 | AG8: 15 | AH8: 1 | AI8: Operation | AJ8: Standard Load | AX8: DR shifting | AY8: Electricity NL - LV | AZ8: 0.0002 | BB8: 1 day [d] | BC8: 0.01 | BD8: 0.7 | BK8: 1 | BL8: =IF(AG8=1,0,1) -> 1 | BN8: 0.5 | BQ8: 0.5 | BU8: =IF(BL8=1,BN8,0) -> 0.5 | CB8: 0.5 | CC8: 1 | CD8: 2 | CE8: 4 | CF8: 8 | CG8: 20 | CH8: 32 | CI8: [1],[12] | CJ8: =VLOOKUP($E8,[2]Activities!$A$9:$I$162,3,FALSE)/$AH8 -> 84 | CK8: =VLOOKUP($E8,[2]Activities!$A$9:$I$162,4,FALSE)/$AH8 -> 86 | CL8: =VLOOKUP($E8,[2]Activities!$A$9:$I$162,5,FALSE)/$AH8 -> 88 | CM8: =VLOOKUP($E8,[2]Activities!$A$9:$I$162,6,FALSE)/$AH8 -> 90 | CN8: =VLOOKUP($E8,[2]Activities!$A$9:$I$162,7,FALSE)/$AH8 -> 92 | CO8: =VLOOKUP($E8,[2]Activities!$A$9:$I$162,8,FALSE)/$AH8 -> 94 | CP8: =VLOOKUP($E8,[2]Activities!$A$9:$I$162,9,FALSE)/$AH8 -> 96
A9: Res02_01 | B9: Final | C9: Residential | D9: Flats | E9: Houses - Residential Flats | F9: House with insulation GFE - Residential Flats | G9: [khouses/y] | H9: 0 | I9: 0 | J9: 0 | K9: 0 | L9: 0 | M9: 0 | N9: 0 | O9: 0.9 | P9: 0 | Q9: 0 | R9: 0 | S9: 0 | T9: 0 | U9: 0 | V9: 0 | W9: 0 | X9: 0 | Y9: 0 | Z9: 0 | AA9: 0 | AB9: 0 | AC9: 0 | AD9: 0.05 | AE9: 0 | AF9: 40 | AG9: 40 | AH9: 1 | AI9: Operation | AJ9: Built Environment | AX9: none | BK9: 0 | BL9: =IF(AG9=1,0,1) -> 1 | BN9: =CB9 -> 900 | BO9: =$BN$9/5 -> 180 | BP9: =$BN$9/5 -> 180 | BQ9: =$BN$9/5 -> 180 | BR9: =$BN$9/5 -> 180 | BS9: =$BN$9/5 -> 180 | BT9: 0 | BU9: =IF(BL9=1,BN9,0) -> 900 | CB9: 900 | CC9: =CK9 -> 3120 | CD9: =CL9 -> 3220 | CE9: =CM9 -> 3300 | CF9: =CN9 -> 3390 | CG9: =CO9 -> 3460 | CH9: =CP9 -> 3540 | CI9: [1],[12] | CJ9: =VLOOKUP($E9,[2]Activities!$A$9:$I$162,3,FALSE)/$AH9 -> 3000 | CK9: =VLOOKUP($E9,[2]Activities!$A$9:$I$162,4,FALSE)/$AH9 -> 3120 | CL9: =VLOOKUP($E9,[2]Activities!$A$9:$I$162,5,FALSE)/$AH9 -> 3220 | CM9: =VLOOKUP($E9,[2]Activities!$A$9:$I$162,6,FALSE)/$AH9 -> 3300 | CN9: =VLOOKUP($E9,[2]Activities!$A$9:$I$162,7,FALSE)/$AH9 -> 3390 | CO9: =VLOOKUP($E9,[2]Activities!$A$9:$I$162,8,FALSE)/$AH9 -> 3460 | CP9: =VLOOKUP($E9,[2]Activities!$A$9:$I$162,9,FALSE)/$AH9 -> 3540 | CR9: 1 | CS9: 1 | CT9: 1 | CU9: 1 | CV9: 1 | CW9: 1 | CX9: 1 | CY9: 1 | CZ9: 1 | DA9: 1 | DB9: 1 | DC9: 1 | DD9: 1
A10: Res02_02 | B10: Final | C10: Residential | D10: Flats | E10: Houses - Residential Flats | F10: House with insulation DC - Residential Flats | G10: [khouses/y] | H10: 2.37 | I10: 2.37 | J10: 2.37 | K10: 0 | L10: 0 | M10: 0 | N10: 0 | O10: 0.9 | P10: 0 | Q10: 0 | R10: 0 | S10: 0 | T10: 0 | U10: 0 | V10: 0 | W10: 0 | X10: 0 | Y10: 0 | Z10: 0 | AA10: 0 | AB10: 0 | AC10: 0 | AD10: 0.05 | AE10: 0 | AF10: 40 | AG10: 40 | AH10: 1 | AI10: Operation | AJ10: Built Environment | AX10: none | BK10: 0 | BL10: =IF(AG10=1,0,1) -> 1 | BN10: =CB10 -> 1150 | BO10: =$BN$10/5 -> 230 | BP10: =$BN$10/5 -> 230 | BQ10: =$BN$10/5 -> 230 | BR10: =$BN$10/5 -> 230 | BS10: =$BN$10/5 -> 230 | BU10: =IF(BL10=1,BN10,0) -> 1150 | CB10: 1150 | CC10: 2185 | CD10: =CL10 -> 3220 | CE10: =CM10 -> 3300 | CF10: =CN10 -> 3390 | CG10: =CO10 -> 3460 | CH10: =CP10 -> 3540 | CI10: [1],[12] | CJ10: =VLOOKUP($E10,[2]Activities!$A$9:$I$162,3,FALSE)/$AH10 -> 3000 | CK10: =VLOOKUP($E10,[2]Activities!$A$9:$I$162,4,FALSE)/$AH10 -> 3120 | CL10: =VLOOKUP($E10,[2]Activities!$A$9:$I$162,5,FALSE)/$AH10 -> 3220 | CM10: =VLOOKUP($E10,[2]Activities!$A$9:$I$162,6,FALSE)/$AH10 -> 3300 | CN10: =VLOOKUP($E10,[2]Activities!$A$9:$I$162,7,FALSE)/$AH10 -> 3390 | CO10: =VLOOKUP($E10,[2]Activities!$A$9:$I$162,8,FALSE)/$AH10 -> 3460 | CP10: =VLOOKUP($E10,[2]Activities!$A$9:$I$162,9,FALSE)/$AH10 -> 3540 | CR10: 1 | CS10: 1 | CT10: 1 | CU10: 1 | CV10: 1 | CW10: 1 | CX10: 1 | CY10: 1 | CZ10: 1 | DA10: 1 | DB10: 1 | DC10: 1 | DD10: 1
A11: Res02_03 | B11: Final | C11: Residential | D11: Flats | E11: Houses - Residential Flats | F11: House with insulation B - Residential Flats | G11: [khouses/y] | H11: 8.2 | I11: 8.2 | J11: 8.2 | K11: 5.8 | L11: 5.8 | M11: 0 | N11: 0 | O11: 0.9 | P11: 0 | Q11: 0 | R11: 0 | S11: 0 | T11: 0 | U11: 0 | V11: 0 | W11: 0 | X11: 0 | Y11: 0 | Z11: 0 | AA11: 0 | AB11: 0 | AC11: 0 | AD11: 0.05 | AE11: 0 | AF11: 40 | AG11: 40 | AH11: 1 | AI11: Operation | AJ11: Built Environment | AX11: none | BK11: 0 | BL11: =IF(AG11=1,0,1) -> 1 | BN11: =CB11 -> 600 | BO11: =$BN$11/6 -> 100 | BP11: =$BN$11/6 -> 100 | BQ11: =$BN$11/6 -> 100 | BR11: =$BN$11/6 -> 100 | BS11: =$BN$11/6 -> 100 | BT11: =$BN$11/6 -> 100 | BU11: =IF(BL11=1,BN11,0) -> 600 | CB11: 600 | CC11: 1910 | CD11: =CL11 -> 3220 | CE11: =CM11 -> 3300 | CF11: =CN11 -> 3390 | CG11: =CO11 -> 3460 | CH11: =CP11 -> 3540 | CI11: [1],[12] | CJ11: =VLOOKUP($E11,[2]Activities!$A$9:$I$162,3,FALSE)/$AH11 -> 3000 | CK11: =VLOOKUP($E11,[2]Activities!$A$9:$I$162,4,FALSE)/$AH11 -> 3120 | CL11: =VLOOKUP($E11,[2]Activities!$A$9:$I$162,5,FALSE)/$AH11 -> 3220 | CM11: =VLOOKUP($E11,[2]Activities!$A$9:$I$162,6,FALSE)/$AH11 -> 3300 | CN11: =VLOOKUP($E11,[2]Activities!$A$9:$I$162,7,FALSE)/$AH11 -> 3390 | CO11: =VLOOKUP($E11,[2]Activities!$A$9:$I$162,8,FALSE)/$AH11 -> 3460 | CP11: =VLOOKUP($E11,[2]Activities!$A$9:$I$162,9,FALSE)/$AH11 -> 3540 | CR11: 1 | CS11: 1 | CT11: 1 | CU11: 1 | CV11: 1 | CW11: 1 | CX11: 1 | CY11: 1 | CZ11: 1 | DA11: 1 | DB11: 1 | DC11: 1 | DD11: 1
A12: Res02_04 | B12: Final | C12: Residential | D12: Flats | E12: Houses - Residential Flats | F12: House with insulation A - Residential Flats | G12: [khouses/y] | H12: 10.37 | I12: 10.11 | J12: 9.85 | K12: 7.2 | L12: 7.1 | M12: 1.3 | N12: 1.3 | O12: 0.9 | P12: 0 | Q12: 0 | R12: 0 | S12: 0 | T12: 0 | U12: 0 | V12: 0 | W12: 0 | X12: 0 | Y12: 0 | Z12: 0 | AA12: 0 | AB12: 0 | AC12: 0 | AD12: 0.05 | AE12: 0 | AF12: 40 | AG12: 40 | AH12: 1 | AI12: Operation | AJ12: Built Environment | AX12: none | BK12: 0 | BL12: =IF(AG12=1,0,1) -> 1 | BN12: =CB12 -> 250 | BO12: 0 | BP12: =$BN$12/5 -> 50 | BQ12: =$BN$12/5 -> 50 | BR12: =$BN$12/5 -> 50 | BS12: =$BN$12/5 -> 50 | BT12: =$BN$12/5 -> 50 | BU12: =IF(BL12=1,BN12,0) -> 250 | CB12: 250 | CC12: 1735 | CD12: =CL12 -> 3220 | CE12: =CM12 -> 3300 | CF12: =CN12 -> 3390 | CG12: =CO12 -> 3460 | CH12: =CP12 -> 3540 | CI12: [1],[12] | CJ12: =VLOOKUP($E12,[2]Activities!$A$9:$I$162,3,FALSE)/$AH12 -> 3000 | CK12: =VLOOKUP($E12,[2]Activities!$A$9:$I$162,4,FALSE)/$AH12 -> 3120 | CL12: =VLOOKUP($E12,[2]Activities!$A$9:$I$162,5,FALSE)/$AH12 -> 3220 | CM12: =VLOOKUP($E12,[2]Activities!$A$9:$I$162,6,FALSE)/$AH12 -> 3300 | CN12: =VLOOKUP($E12,[2]Activities!$A$9:$I$162,7,FALSE)/$AH12 -> 3390 | CO12: =VLOOKUP($E12,[2]Activities!$A$9:$I$162,8,FALSE)/$AH12 -> 3460 | CP12: =VLOOKUP($E12,[2]Activities!$A$9:$I$162,9,FALSE)/$AH12 -> 3540 | CX12: 1 | CY12: 1 | CZ12: 1 | DA12: 1 | DB12: 1 | DC12: 1 | DD12: 1
A13: Res02_05 | B13: Final | C13: Residential | D13: Flats | E13: Houses - Residential Flats | F13: House with insulation A+ - Residential Flats | G13: [khouses/y] | H13: 12.26 | I13: 11.65 | J13: 11.04 | K13: 8.1 | L13: 7.5 | M13: 1.7 | N13: 1.5 | O13: 0.9 | P13: 0 | Q13: 0 | R13: 0 | S13: 0 | T13: 0 | U13: 0 | V13: 0 | W13: 0 | X13: 0 | Y13: 0 | Z13: 0 | AA13: 0 | AB13: 0 | AC13: 0 | AD13: 0.05 | AE13: 0 | AF13: 40 | AG13: 40 | AH13: 1 | AI13: Operation | AJ13: Built Environment | AX13: none | BK13: 0 | BL13: =IF(AG13=1,0,1) -> 1 | BN13: =CB13 -> 100 | BO13: 0 | BP13: 0 | BQ13: =$BN$13/5 -> 20 | BR13: =$BN$13/5 -> 20 | BS13: =$BN$13/5 -> 20 | BT13: =$BN$13/5 -> 20 | BU13: =IF(BL13=1,BN13,0) -> 100 | CB13: 100 | CC13: 1660 | CD13: =CL13 -> 3220 | CE13: =CM13 -> 3300 | CF13: =CN13 -> 3390 | CG13: =CO13 -> 3460 | CH13: =CP13 -> 3540 | CI13: [1],[9],[12] | CJ13: =VLOOKUP($E13,[2]Activities!$A$9:$I$162,3,FALSE)/$AH13 -> 3000 | CK13: =VLOOKUP($E13,[2]Activities!$A$9:$I$162,4,FALSE)/$AH13 -> 3120 | CL13: =VLOOKUP($E13,[2]Activities!$A$9:$I$162,5,FALSE)/$AH13 -> 3220 | CM13: =VLOOKUP($E13,[2]Activities!$A$9:$I$162,6,FALSE)/$AH13 -> 3300 | CN13: =VLOOKUP($E13,[2]Activities!$A$9:$I$162,7,FALSE)/$AH13 -> 3390 | CO13: =VLOOKUP($E13,[2]Activities!$A$9:$I$162,8,FALSE)/$AH13 -> 3460 | CP13: =VLOOKUP($E13,[2]Activities!$A$9:$I$162,9,FALSE)/$AH13 -> 3540 | CX13: 1 | CY13: 1 | CZ13: 1 | DA13: 1 | DB13: 1 | DC13: 1 | DD13: 1
A14: Res03_01 | B14: Final | C14: Residential | D14: Terrace | E14: Houses - Residential Terrace | F14: House with insulation GFE - Residential Terrace | G14: [khouses/y] | H14: 0 | I14: 0 | J14: 0 | K14: 0 | L14: 0 | M14: 0 | N14: 0 | O14: 0.9 | P14: 0 | Q14: 0 | R14: 0 | S14: 0 | T14: 0 | U14: 0 | V14: 0 | W14: 0 | X14: 0 | Y14: 0 | Z14: 0 | AA14: 0 | AB14: 0 | AC14: 0 | AD14: 0.05 | AE14: 0 | AF14: 40 | AG14: 40 | AH14: 1 | AI14: Operation | AJ14: Built Environment | AX14: none | BK14: 0 | BL14: =IF(AG14=1,0,1) -> 1 | BN14: =CB14 -> 830 | BO14: =$BN$14/5 -> 166 | BP14: =$BN$14/5 -> 166 | BQ14: =$BN$14/5 -> 166 | BR14: =$BN$14/5 -> 166 | BS14: =$BN$14/5 -> 166 | BT14: 0 | BU14: =IF(BL14=1,BN14,0) -> 830 | CB14: 830 | CC14: =CK14 -> 3580 | CD14: =CL14 -> 3690 | CE14: =CM14 -> 3790 | CF14: =CN14 -> 3880 | CG14: =CO14 -> 3970 | CH14: =CP14 -> 4060 | CI14: [1],[9],[12] | CJ14: =VLOOKUP($E14,[2]Activities!$A$9:$I$162,3,FALSE)/$AH14 -> 3440 | CK14: =VLOOKUP($E14,[2]Activities!$A$9:$I$162,4,FALSE)/$AH14 -> 3580 | CL14: =VLOOKUP($E14,[2]Activities!$A$9:$I$162,5,FALSE)/$AH14 -> 3690 | CM14: =VLOOKUP($E14,[2]Activities!$A$9:$I$162,6,FALSE)/$AH14 -> 3790 | CN14: =VLOOKUP($E14,[2]Activities!$A$9:$I$162,7,FALSE)/$AH14 -> 3880 | CO14: =VLOOKUP($E14,[2]Activities!$A$9:$I$162,8,FALSE)/$AH14 -> 3970 | CP14: =VLOOKUP($E14,[2]Activities!$A$9:$I$162,9,FALSE)/$AH14 -> 4060 | CR14: 1 | CS14: 1 | CT14: 1 | CU14: 1 | CV14: 1 | CW14: 1 | CX14: 1 | CY14: 1 | CZ14: 1 | DA14: 1 | DB14: 1 | DC14: 1 | DD14: 1
A15: Res03_02 | B15: Final | C15: Residential | D15: Terrace | E15: Houses - Residential Terrace | F15: House with insulation DC - Residential Terrace | G15: [khouses/y] | H15: 3.18 | I15: 3.18 | J15: 3.18 | K15: 0 | L15: 0 | M15: 0 | N15: 0 | O15: 0.9 | P15: 0 | Q15: 0 | R15: 0 | S15: 0 | T15: 0 | U15: 0 | V15: 0 | W15: 0 | X15: 0 | Y15: 0 | Z15: 0 | AA15: 0 | AB15: 0 | AC15: 0 | AD15: 0.05 | AE15: 0 | AF15: 40 | AG15: 40 | AH15: 1 | AI15: Operation | AJ15: Built Environment | AX15: none | BK15: 0 | BL15: =IF(AG15=1,0,1) -> 1 | BN15: =CB15 -> 1270 | BO15: =$BN$15/5 -> 254 | BP15: =$BN$15/5 -> 254 | BQ15: =$BN$15/5 -> 254 | BR15: =$BN$15/5 -> 254 | BS15: =$BN$15/5 -> 254 | BU15: =IF(BL15=1,BN15,0) -> 1270 | CB15: 1270 | CC15: 2480 | CD15: =CL15 -> 3690 | CE15: =CM15 -> 3790 | CF15: =CN15 -> 3880 | CG15: =CO15 -> 3970 | CH15: =CP15 -> 4060 | CI15: [1],[37],[38] | CJ15: =VLOOKUP($E15,[2]Activities!$A$9:$I$162,3,FALSE)/$AH15 -> 3440 | CK15: =VLOOKUP($E15,[2]Activities!$A$9:$I$162,4,FALSE)/$AH15 -> 3580 | CL15: =VLOOKUP($E15,[2]Activities!$A$9:$I$162,5,FALSE)/$AH15 -> 3690 | CM15: =VLOOKUP($E15,[2]Activities!$A$9:$I$162,6,FALSE)/$AH15 -> 3790 | CN15: =VLOOKUP($E15,[2]Activities!$A$9:$I$162,7,FALSE)/$AH15 -> 3880 | CO15: =VLOOKUP($E15,[2]Activities!$A$9:$I$162,8,FALSE)/$AH15 -> 3970 | CP15: =VLOOKUP($E15,[2]Activities!$A$9:$I$162,9,FALSE)/$AH15 -> 4060 | CR15: 1 | CS15: 1 | CT15: 1 | CU15: 1 | CV15: 1 | CW15: 1 | CX15: 1 | CY15: 1 | CZ15: 1 | DA15: 1 | DB15: 1 | DC15: 1 | DD15: 1
A16: Res03_03 | B16: Final | C16: Residential | D16: Terrace | E16: Houses - Residential Terrace | F16: House with insulation B - Residential Terrace | G16: [khouses/y] | H16: 9.71 | I16: 9.71 | J16: 9.71 | K16: 6.5 | L16: 6.5 | M16: 0 | N16: 0 | O16: 0.9 | P16: 0 | Q16: 0 | R16: 0 | S16: 0 | T16: 0 | U16: 0 | V16: 0 | W16: 0 | X16: 0 | Y16: 0 | Z16: 0 | AA16: 0 | AB16: 0 | AC16: 0 | AD16: 0.05 | AE16: 0 | AF16: 40 | AG16: 40 | AH16: 1 | AI16: Operation | AJ16: Built Environment | AX16: none | BK16: 0 | BL16: =IF(AG16=1,0,1) -> 1 | BN16: =CB16 -> 840 | BO16: =$BN$16/6 -> 140 | BP16: =$BN$16/6 -> 140 | BQ16: =$BN$16/6 -> 140 | BR16: =$BN$16/6 -> 140 | BS16: =$BN$16/6 -> 140 | BT16: =$BN$16/6 -> 140 | BU16: =IF(BL16=1,BN16,0) -> 840 | CB16: 840 | CC16: 2265 | CD16: =CL16 -> 3690 | CE16: =CM16 -> 3790 | CF16: =CN16 -> 3880 | CG16: =CO16 -> 3970 | CH16: =CP16 -> 4060 | CI16: [1],[37],[38] | CJ16: =VLOOKUP($E16,[2]Activities!$A$9:$I$162,3,FALSE)/$AH16 -> 3440 | CK16: =VLOOKUP($E16,[2]Activities!$A$9:$I$162,4,FALSE)/$AH16 -> 3580 | CL16: =VLOOKUP($E16,[2]Activities!$A$9:$I$162,5,FALSE)/$AH16 -> 3690 | CM16: =VLOOKUP($E16,[2]Activities!$A$9:$I$162,6,FALSE)/$AH16 -> 3790 | CN16: =VLOOKUP($E16,[2]Activities!$A$9:$I$162,7,FALSE)/$AH16 -> 3880 | CO16: =VLOOKUP($E16,[2]Activities!$A$9:$I$162,8,FALSE)/$AH16 -> 3970 | CP16: =VLOOKUP($E16,[2]Activities!$A$9:$I$162,9,FALSE)/$AH16 -> 4060 | CR16: 1 | CS16: 1 | CT16: 1 | CU16: 1 | CV16: 1 | CW16: 1 | CX16: 1 | CY16: 1 | CZ16: 1 | DA16: 1 | DB16: 1 | DC16: 1 | DD16: 1
A17: Res03_04 | B17: Final | C17: Residential | D17: Terrace | E17: Houses - Residential Terrace | F17: House with insulation A - Residential Terrace | G17: [khouses/y] | H17: 12.9 | I17: 12.57 | J17: 12.25 | K17: 8.7 | L17: 8.4 | M17: 1.9 | N17: 1.9 | O17: 0.9 | P17: 0 | Q17: 0 | R17: 0 | S17: 0 | T17: 0 | U17: 0 | V17: 0 | W17: 0 | X17: 0 | Y17: 0 | Z17: 0 | AA17: 0 | AB17: 0 | AC17: 0 | AD17: 0.05 | AE17: 0 | AF17: 40 | AG17: 40 | AH17: 1 | AI17: Operation | AJ17: Built Environment | AX17: none | BK17: 0 | BL17: =IF(AG17=1,0,1) -> 1 | BN17: =CB17 -> 380 | BO17: 0 | BP17: =$BN$17/5 -> 76 | BQ17: =$BN$17/5 -> 76 | BR17: =$BN$17/5 -> 76 | BS17: =$BN$17/5 -> 76 | BT17: =$BN$17/5 -> 76 | BU17: =IF(BL17=1,BN17,0) -> 380 | CB17: 380 | CC17: 2035 | CD17: =CL17 -> 3690 | CE17: =CM17 -> 3790 | CF17: =CN17 -> 3880 | CG17: =CO17 -> 3970 | CH17: =CP17 -> 4060 | CI17: [1],[37],[38] | CJ17: =VLOOKUP($E17,[2]Activities!$A$9:$I$162,3,FALSE)/$AH17 -> 3440 | CK17: =VLOOKUP($E17,[2]Activities!$A$9:$I$162,4,FALSE)/$AH17 -> 3580 | CL17: =VLOOKUP($E17,[2]Activities!$A$9:$I$162,5,FALSE)/$AH17 -> 3690 | CM17: =VLOOKUP($E17,[2]Activities!$A$9:$I$162,6,FALSE)/$AH17 -> 3790 | CN17: =VLOOKUP($E17,[2]Activities!$A$9:$I$162,7,FALSE)/$AH17 -> 3880 | CO17: =VLOOKUP($E17,[2]Activities!$A$9:$I$162,8,FALSE)/$AH17 -> 3970 | CP17: =VLOOKUP($E17,[2]Activities!$A$9:$I$162,9,FALSE)/$AH17 -> 4060 | CX17: 1 | CY17: 1 | CZ17: 1 | DA17: 1 | DB17: 1 | DC17: 1 | DD17: 1
A18: Res03_05 | B18: Final | C18: Residential | D18: Terrace | E18: Houses - Residential Terrace | F18: House with insulation A+ - Residential Terrace | G18: [khouses/y] | H18: 15.69 | I18: 14.91 | J18: 14.12 | K18: 10.2 | L18: 9.5 | M18: 3 | N18: 2.5 | O18: 0.9 | P18: 0 | Q18: 0 | R18: 0 | S18: 0 | T18: 0 | U18: 0 | V18: 0 | W18: 0 | X18: 0 | Y18: 0 | Z18: 0 | AA18: 0 | AB18: 0 | AC18: 0 | AD18: 0.05 | AE18: 0 | AF18: 40 | AG18: 40 | AH18: 1 | AI18: Operation | AJ18: Built Environment | AX18: none | BK18: 0 | BL18: =IF(AG18=1,0,1) -> 1 | BN18: =CB18 -> 120 | BO18: 0 | BP18: 0 | BQ18: =$BN$18/5 -> 24 | BR18: =$BN$18/5 -> 24 | BS18: =$BN$18/5 -> 24 | BT18: =$BN$18/5 -> 24 | BU18: =IF(BL18=1,BN18,0) -> 120 | CB18: 120 | CC18: 1905 | CD18: =CL18 -> 3690 | CE18: =CM18 -> 3790 | CF18: =CN18 -> 3880 | CG18: =CO18 -> 3970 | CH18: =CP18 -> 4060 | CI18: [1],[37],[38] | CJ18: =VLOOKUP($E18,[2]Activities!$A$9:$I$162,3,FALSE)/$AH18 -> 3440 | CK18: =VLOOKUP($E18,[2]Activities!$A$9:$I$162,4,FALSE)/$AH18 -> 3580 | CL18: =VLOOKUP($E18,[2]Activities!$A$9:$I$162,5,FALSE)/$AH18 -> 3690 | CM18: =VLOOKUP($E18,[2]Activities!$A$9:$I$162,6,FALSE)/$AH18 -> 3790 | CN18: =VLOOKUP($E18,[2]Activities!$A$9:$I$162,7,FALSE)/$AH18 -> 3880 | CO18: =VLOOKUP($E18,[2]Activities!$A$9:$I$162,8,FALSE)/$AH18 -> 3970 | CP18: =VLOOKUP($E18,[2]Activities!$A$9:$I$162,9,FALSE)/$AH18 -> 4060 | CX18: 1 | CY18: 1 | CZ18: 1 | DA18: 1 | DB18: 1 | DC18: 1 | DD18: 1
A19: Res04_01 | B19: Final | C19: Residential | D19: Dwellings | E19: Houses - Residential Dwellings | F19: House with insulation GFE - Residential Dwellings | G19: [khouses/y] | H19: 0 | I19: 0 | J19: 0 | K19: 0 | L19: 0 | M19: 0 | N19: 0 | O19: 0.9 | P19: 0 | Q19: 0 | R19: 0 | S19: 0 | T19: 0 | U19: 0 | V19: 0 | W19: 0 | X19: 0 | Y19: 0 | Z19: 0 | AA19: 0 | AB19: 0 | AC19: 0 | AD19: 0.05 | AE19: 0 | AF19: 40 | AG19: 40 | AH19: 1 | AI19: Operation | AJ19: Built Environment | AX19: none | BK19: 0 | BL19: =IF(AG19=1,0,1) -> 1 | BN19: =CB19 -> 350 | BO19: =$BN$19/5 -> 70 | BP19: =$BN$19/5 -> 70 | BQ19: =$BN$19/5 -> 70 | BR19: =$BN$19/5 -> 70 | BS19: =$BN$19/5 -> 70 | BT19: 0 | BU19: =IF(BL19=1,BN19,0) -> 350 | CB19: 350 | CC19: =CK19 -> 1800 | CD19: =CL19 -> 1850 | CE19: =CM19 -> 1900 | CF19: =CN19 -> 1950 | CG19: =CO19 -> 1990 | CH19: =CP19 -> 2040 | CI19: [1],[37],[38] | CJ19: =VLOOKUP($E19,[2]Activities!$A$9:$I$162,3,FALSE)/$AH19 -> 1730 | CK19: =VLOOKUP($E19,[2]Activities!$A$9:$I$162,4,FALSE)/$AH19 -> 1800 | CL19: =VLOOKUP($E19,[2]Activities!$A$9:$I$162,5,FALSE)/$AH19 -> 1850 | CM19: =VLOOKUP($E19,[2]Activities!$A$9:$I$162,6,FALSE)/$AH19 -> 1900 | CN19: =VLOOKUP($E19,[2]Activities!$A$9:$I$162,7,FALSE)/$AH19 -> 1950 | CO19: =VLOOKUP($E19,[2]Activities!$A$9:$I$162,8,FALSE)/$AH19 -> 1990 | CP19: =VLOOKUP($E19,[2]Activities!$A$9:$I$162,9,FALSE)/$AH19 -> 2040 | CR19: 1 | CS19: 1 | CT19: 1 | CU19: 1 | CV19: 1 | CW19: 1 | CX19: 1 | CY19: 1 | CZ19: 1 | DA19: 1 | DB19: 1 | DC19: 1 | DD19: 1
A20: Res04_02 | B20: Final | C20: Residential | D20: Dwellings | E20: Houses - Residential Dwellings | F20: House with insulation DC - Residential Dwellings | G20: [khouses/y] | H20: 5.6 | I20: 5.6 | J20: 5.6 | K20: 0 | L20: 0 | M20: 0 | N20: 0 | O20: 0.9 | P20: 0 | Q20: 0 | R20: 0 | S20: 0 | T20: 0 | U20: 0 | V20: 0 | W20: 0 | X20: 0 | Y20: 0 | Z20: 0 | AA20: 0 | AB20: 0 | AC20: 0 | AD20: 0.05 | AE20: 0 | AF20: 40 | AG20: 40 | AH20: 1 | AI20: Operation | AJ20: Built Environment | AX20: none | BK20: 0 | BL20: =IF(AG20=1,0,1) -> 1 | BN20: =CB20 -> 540 | BO20: =$BN$20/5 -> 108 | BP20: =$BN$20/5 -> 108 | BQ20: =$BN$20/5 -> 108 | BR20: =$BN$20/5 -> 108 | BS20: =$BN$20/5 -> 108 | BU20: =IF(BL20=1,BN20,0) -> 540 | CB20: 540 | CC20: 1195 | CD20: =CL20 -> 1850 | CE20: =CM20 -> 1900 | CF20: =CN20 -> 1950 | CG20: =CO20 -> 1990 | CH20: =CP20 -> 2040 | CI20: [12] | CJ20: =VLOOKUP($E20,[2]Activities!$A$9:$I$162,3,FALSE)/$AH20 -> 1730 | CK20: =VLOOKUP($E20,[2]Activities!$A$9:$I$162,4,FALSE)/$AH20 -> 1800 | CL20: =VLOOKUP($E20,[2]Activities!$A$9:$I$162,5,FALSE)/$AH20 -> 1850 | CM20: =VLOOKUP($E20,[2]Activities!$A$9:$I$162,6,FALSE)/$AH20 -> 1900 | CN20: =VLOOKUP($E20,[2]Activities!$A$9:$I$162,7,FALSE)/$AH20 -> 1950 | CO20: =VLOOKUP($E20,[2]Activities!$A$9:$I$162,8,FALSE)/$AH20 -> 1990 | CP20: =VLOOKUP($E20,[2]Activities!$A$9:$I$162,9,FALSE)/$AH20 -> 2040 | CR20: 1 | CS20: 1 | CT20: 1 | CU20: 1 | CV20: 1 | CW20: 1 | CX20: 1 | CY20: 1 | CZ20: 1 | DA20: 1 | DB20: 1 | DC20: 1 | DD20: 1
A21: Res04_03 | B21: Final | C21: Residential | D21: Dwellings | E21: Houses - Residential Dwellings | F21: House with insulation B - Residential Dwellings | G21: [khouses/y] | H21: 17.19 | I21: 17.19 | J21: 17.19 | K21: 11.6 | L21: 11.6 | M21: 0 | N21: 0 | O21: 0.9 | P21: 0 | Q21: 0 | R21: 0 | S21: 0 | T21: 0 | U21: 0 | V21: 0 | W21: 0 | X21: 0 | Y21: 0 | Z21: 0 | AA21: 0 | AB21: 0 | AC21: 0 | AD21: 0.05 | AE21: 0 | AF21: 40 | AG21: 40 | AH21: 1 | AI21: Operation | AJ21: Built Environment | AX21: none | BK21: 0 | BL21: =IF(AG21=1,0,1) -> 1 | BN21: =CB21 -> 430 | BO21: =$BN$21/6 -> 71.666667 | BP21: =$BN$21/6 -> 71.666667 | BQ21: =$BN$21/6 -> 71.666667 | BR21: =$BN$21/6 -> 71.666667 | BS21: =$BN$21/6 -> 71.666667 | BT21: =$BN$21/6 -> 71.666667 | BU21: =IF(BL21=1,BN21,0) -> 430 | CB21: 430 | CC21: 1140 | CD21: =CL21 -> 1850 | CE21: =CM21 -> 1900 | CF21: =CN21 -> 1950 | CG21: =CO21 -> 1990 | CH21: =CP21 -> 2040 | CI21: [1],[12] | CJ21: =VLOOKUP($E21,[2]Activities!$A$9:$I$162,3,FALSE)/$AH21 -> 1730 | CK21: =VLOOKUP($E21,[2]Activities!$A$9:$I$162,4,FALSE)/$AH21 -> 1800 | CL21: =VLOOKUP($E21,[2]Activities!$A$9:$I$162,5,FALSE)/$AH21 -> 1850 | CM21: =VLOOKUP($E21,[2]Activities!$A$9:$I$162,6,FALSE)/$AH21 -> 1900 | CN21: =VLOOKUP($E21,[2]Activities!$A$9:$I$162,7,FALSE)/$AH21 -> 1950 | CO21: =VLOOKUP($E21,[2]Activities!$A$9:$I$162,8,FALSE)/$AH21 -> 1990 | CP21: =VLOOKUP($E21,[2]Activities!$A$9:$I$162,9,FALSE)/$AH21 -> 2040 | CR21: 1 | CS21: 1 | CT21: 1 | CU21: 1 | CV21: 1 | CW21: 1 | CX21: 1 | CY21: 1 | CZ21: 1 | DA21: 1 | DB21: 1 | DC21: 1 | DD21: 1
A22: Res04_04 | B22: Final | C22: Residential | D22: Dwellings | E22: Houses - Residential Dwellings | F22: House with insulation A - Residential Dwellings | G22: [khouses/y] | H22: 23.09 | I22: 22.51 | J22: 21.93 | K22: 15.8 | L22: 15 | M22: 3.4 | N22: 3.4 | O22: 0.9 | P22: 0 | Q22: 0 | R22: 0 | S22: 0 | T22: 0 | U22: 0 | V22: 0 | W22: 0 | X22: 0 | Y22: 0 | Z22: 0 | AA22: 0 | AB22: 0 | AC22: 0 | AD22: 0.05 | AE22: 0 | AF22: 40 | AG22: 40 | AH22: 1 | AI22: Operation | AJ22: Built Environment | AX22: none | BK22: 0 | BL22: =IF(AG22=1,0,1) -> 1 | BN22: =CB22 -> 260 | BO22: 0 | BP22: =$BN$22/5 -> 52 | BQ22: =$BN$22/5 -> 52 | BR22: =$BN$22/5 -> 52 | BS22: =$BN$22/5 -> 52 | BT22: =$BN$22/5 -> 52 | BU22: =IF(BL22=1,BN22,0) -> 260 | CB22: 260 | CC22: 1055 | CD22: =CL22 -> 1850 | CE22: =CM22 -> 1900 | CF22: =CN22 -> 1950 | CG22: =CO22 -> 1990 | CH22: =CP22 -> 2040 | CI22: [1],[12] | CJ22: =VLOOKUP($E22,[2]Activities!$A$9:$I$162,3,FALSE)/$AH22 -> 1730 | CK22: =VLOOKUP($E22,[2]Activities!$A$9:$I$162,4,FALSE)/$AH22 -> 1800 | CL22: =VLOOKUP($E22,[2]Activities!$A$9:$I$162,5,FALSE)/$AH22 -> 1850 | CM22: =VLOOKUP($E22,[2]Activities!$A$9:$I$162,6,FALSE)/$AH22 -> 1900 | CN22: =VLOOKUP($E22,[2]Activities!$A$9:$I$162,7,FALSE)/$AH22 -> 1950 | CO22: =VLOOKUP($E22,[2]Activities!$A$9:$I$162,8,FALSE)/$AH22 -> 1990 | CP22: =VLOOKUP($E22,[2]Activities!$A$9:$I$162,9,FALSE)/$AH22 -> 2040 | CX22: 1 | CY22: 1 | CZ22: 1 | DA22: 1 | DB22: 1 | DC22: 1 | DD22: 1
A23: Res04_05 | B23: Final | C23: Residential | D23: Dwellings | E23: Houses - Residential Dwellings | F23: House with insulation A+ - Residential Dwellings | G23: [khouses/y] | H23: 28.28 | I23: 26.86 | J23: 25.45 | K23: 18.6 | L23: 18 | M23: 6 | N23: 5 | O23: 0.9 | P23: 0 | Q23: 0 | R23: 0 | S23: 0 | T23: 0 | U23: 0 | V23: 0 | W23: 0 | X23: 0 | Y23: 0 | Z23: 0 | AA23: 0 | AB23: 0 | AC23: 0 | AD23: 0.05 | AE23: 0 | AF23: 40 | AG23: 40 | AH23: 1 | AI23: Operation | AJ23: Built Environment | AX23: none | BK23: 0 | BL23: =IF(AG23=1,0,1) -> 1 | BN23: =CB23 -> 150 | BO23: 0 | BP23: 0 | BQ23: =$BN$23/5 -> 30 | BR23: =$BN$23/5 -> 30 | BS23: =$BN$23/5 -> 30 | BT23: =$BN$23/5 -> 30 | BU23: =IF(BL23=1,BN23,0) -> 150 | CB23: 150 | CC23: 1000 | CD23: =CL23 -> 1850 | CE23: =CM23 -> 1900 | CF23: =CN23 -> 1950 | CG23: =CO23 -> 1990 | CH23: =CP23 -> 2040 | CI23: [1],[D] | CJ23: =VLOOKUP($E23,[2]Activities!$A$9:$I$162,3,FALSE)/$AH23 -> 1730 | CK23: =VLOOKUP($E23,[2]Activities!$A$9:$I$162,4,FALSE)/$AH23 -> 1800 | CL23: =VLOOKUP($E23,[2]Activities!$A$9:$I$162,5,FALSE)/$AH23 -> 1850 | CM23: =VLOOKUP($E23,[2]Activities!$A$9:$I$162,6,FALSE)/$AH23 -> 1900 | CN23: =VLOOKUP($E23,[2]Activities!$A$9:$I$162,7,FALSE)/$AH23 -> 1950 | CO23: =VLOOKUP($E23,[2]Activities!$A$9:$I$162,8,FALSE)/$AH23 -> 1990 | CP23: =VLOOKUP($E23,[2]Activities!$A$9:$I$162,9,FALSE)/$AH23 -> 2040 | CX23: 1 | CY23: 1 | CZ23: 1 | DA23: 1 | DB23: 1 | DC23: 1 | DD23: 1
A24: Ser01_01 | B24: Final | C24: Services | D24: Appliances | E24: Electricity demand - Services | F24: Dummy standard electricity consumption - Services | G24: [PJ/y] | H24: 0 | I24: 0 | J24: 0 | K24: 0 | L24: 0 | M24: 0 | N24: 0 | O24: 0 | P24: 0 | Q24: 0 | R24: 0 | S24: 0 | T24: 0 | U24: 0 | V24: 0 | W24: 0 | X24: 0 | Y24: 0 | Z24: 0 | AA24: 0 | AB24: 0 | AC24: 0 | AD24: 0.05 | AE24: 0 | AF24: 1 | AG24: 1 | AH24: 1 | AI24: Operation | AJ24: Standard Load | AX24: none | BK24: 0 | BL24: =IF(AG24=1,0,1) -> 0 | BO24: 0 | BP24: 0 | BQ24: 0 | BR24: 0 | BS24: 0 | BT24: 0 | BU24: =IF(BL24=1,BN24,0) -> 0 | CB24: =CJ24 -> 122 | CC24: =CK24 -> 124 | CD24: =CL24 -> 126 | CE24: =CM24 -> 128 | CF24: =CN24 -> 130 | CG24: =CO24 -> 132 | CH24: =CP24 -> 134 | CI24: [39] | CJ24: =VLOOKUP($E24,[2]Activities!$A$9:$I$162,3,FALSE)/$AH24 -> 122 | CK24: =VLOOKUP($E24,[2]Activities!$A$9:$I$162,4,FALSE)/$AH24 -> 124 | CL24: =VLOOKUP($E24,[2]Activities!$A$9:$I$162,5,FALSE)/$AH24 -> 126 | CM24: =VLOOKUP($E24,[2]Activities!$A$9:$I$162,6,FALSE)/$AH24 -> 128 | CN24: =VLOOKUP($E24,[2]Activities!$A$9:$I$162,7,FALSE)/$AH24 -> 130 | CO24: =VLOOKUP($E24,[2]Activities!$A$9:$I$162,8,FALSE)/$AH24 -> 132 | CP24: =VLOOKUP($E24,[2]Activities!$A$9:$I$162,9,FALSE)/$AH24 -> 134
A25: Ser01_02 | B25: Final | C25: Services | D25: Appliances | E25: Electricity demand - Services | F25: Flexible standard electricity consumption - Services | G25: [PJ/y] | H25: 0.5 | I25: 0.5 | J25: 0.5 | K25: 0.3 | L25: 0.1 | M25: 0 | N25: 0 | O25: 0.9 | P25: 0 | Q25: 0 | R25: 0 | S25: 0 | T25: 0 | U25: 0 | V25: 0 | W25: 0 | X25: 0 | Y25: 0 | Z25: 0 | AA25: 0 | AB25: 0 | AC25: 0 | AD25: 0.05 | AE25: 0 | AF25: 15 | AG25: 15 | AH25: 1 | AI25: Operation | AJ25: Standard Load | AX25: DR shifting | AY25: Electricity NL - LV | AZ25: 0.0002 | BB25: 1 day [d] | BC25: 0.01 | BD25: 0.7 | BK25: 1 | BL25: =IF(AG25=1,0,1) -> 1 | BN25: =CB25 -> 0.5 | BO25: 0 | BP25: 0 | BQ25: 0.5 | BR25: 0 | BS25: 0 | BT25: 0 | BU25: =IF(BL25=1,BN25,0) -> 0.5 | CB25: 0.5 | CC25: 1 | CD25: 2 | CE25: 4 | CF25: 10 | CG25: 20 | CH25: 40 | CI25: [39] | CJ25: =VLOOKUP($E25,[2]Activities!$A$9:$I$162,3,FALSE)/$AH25 -> 122 | CK25: =VLOOKUP($E25,[2]Activities!$A$9:$I$162,4,FALSE)/$AH25 -> 124 | CL25: =VLOOKUP($E25,[2]Activities!$A$9:$I$162,5,FALSE)/$AH25 -> 126 | CM25: =VLOOKUP($E25,[2]Activities!$A$9:$I$162,6,FALSE)/$AH25 -> 128 | CN25: =VLOOKUP($E25,[2]Activities!$A$9:$I$162,7,FALSE)/$AH25 -> 130 | CO25: =VLOOKUP($E25,[2]Activities!$A$9:$I$162,8,FALSE)/$AH25 -> 132 | CP25: =VLOOKUP($E25,[2]Activities!$A$9:$I$162,9,FALSE)/$AH25 -> 134
A26: Ser02_01 | B26: Final | C26: Services | D26: Buildings | E26: Space - Services | F26: Space with insulation GFE - Services | G26: [Mm2/y] | H26: 0 | I26: 0 | J26: 0 | K26: 0 | L26: 0 | M26: 0 | N26: 0 | O26: 0.9 | P26: 0.32 | Q26: 0.32 | R26: 0.32 | S26: 0.32 | T26: 0.32 | U26: 0.32 | V26: 0.32 | W26: 0 | X26: 0 | Y26: 0 | Z26: 0 | AA26: 0 | AB26: 0 | AC26: 0 | AD26: 0.05 | AE26: 0 | AF26: 25 | AG26: 25 | AH26: 1 | AI26: Operation | AJ26: Built Environment | AX26: none | BK26: 0 | BL26: =IF(AG26=1,0,1) -> 1 | BN26: 190 | BO26: 100 | BP26: 60 | BQ26: 30 | BR26: 0 | BS26: 0 | BT26: 0 | BU26: =IF(BL26=1,BN26,0) -> 190 | CB26: 190 | CC26: =CK26 -> 530 | CD26: =CL26 -> 540 | CE26: =CM26 -> 550 | CF26: =CN26 -> 555 | CG26: =CO26 -> 560 | CH26: =CP26 -> 560 | CI26: [39] | CJ26: =VLOOKUP($E26,[2]Activities!$A$9:$I$162,3,FALSE)/$AH26 -> 515 | CK26: =VLOOKUP($E26,[2]Activities!$A$9:$I$162,4,FALSE)/$AH26 -> 530 | CL26: =VLOOKUP($E26,[2]Activities!$A$9:$I$162,5,FALSE)/$AH26 -> 540 | CM26: =VLOOKUP($E26,[2]Activities!$A$9:$I$162,6,FALSE)/$AH26 -> 550 | CN26: =VLOOKUP($E26,[2]Activities!$A$9:$I$162,7,FALSE)/$AH26 -> 555 | CO26: =VLOOKUP($E26,[2]Activities!$A$9:$I$162,8,FALSE)/$AH26 -> 560 | CP26: =VLOOKUP($E26,[2]Activities!$A$9:$I$162,9,FALSE)/$AH26 -> 560 | CR26: 1 | CS26: 1 | CT26: 1 | CU26: 1 | CV26: 1 | CW26: 1 | CX26: 1 | CY26: 1 | CZ26: 1 | DA26: 1 | DB26: 1 | DC26: 1 | DD26: 1
A27: Ser02_02 | B27: Final | C27: Services | D27: Buildings | E27: Space - Services | F27: Space with insulation DC - Services | G27: [Mm2/y] | H27: 21.9 | I27: 21.9 | J27: 21.9 | K27: 0 | L27: 0 | M27: 0 | N27: 0 | O27: 0.9 | P27: 0.32 | Q27: 0.32 | R27: 0.32 | S27: 0.32 | T27: 0.32 | U27: 0.32 | V27: 0.32 | W27: 0 | X27: 0 | Y27: 0 | Z27: 0 | AA27: 0 | AB27: 0 | AC27: 0 | AD27: 0.05 | AE27: 0 | AF27: 25 | AG27: 25 | AH27: 1 | AI27: Operation | AJ27: Built Environment | AX27: none | BK27: 0 | BL27: =IF(AG27=1,0,1) -> 1 | BN27: 100 | BO27: 50 | BP27: 30 | BQ27: 15 | BR27: 5 | BS27: 0 | BT27: 0 | BU27: =IF(BL27=1,BN27,0) -> 100 | CB27: 100 | CC27: =CK27 -> 530 | CD27: =CL27 -> 540 | CE27: =CM27 -> 550 | CF27: =CN27 -> 555 | CG27: =CO27 -> 560 | CH27: =CP27 -> 560 | CI27: [1] | CJ27: =VLOOKUP($E27,[2]Activities!$A$9:$I$162,3,FALSE)/$AH27 -> 515 | CK27: =VLOOKUP($E27,[2]Activities!$A$9:$I$162,4,FALSE)/$AH27 -> 530 | CL27: =VLOOKUP($E27,[2]Activities!$A$9:$I$162,5,FALSE)/$AH27 -> 540 | CM27: =VLOOKUP($E27,[2]Activities!$A$9:$I$162,6,FALSE)/$AH27 -> 550 | CN27: =VLOOKUP($E27,[2]Activities!$A$9:$I$162,7,FALSE)/$AH27 -> 555 | CO27: =VLOOKUP($E27,[2]Activities!$A$9:$I$162,8,FALSE)/$AH27 -> 560 | CP27: =VLOOKUP($E27,[2]Activities!$A$9:$I$162,9,FALSE)/$AH27 -> 560 | CR27: 1 | CS27: 1 | CT27: 1 | CU27: 1 | CV27: 1 | CW27: 1 | CX27: 1 | CY27: 1 | CZ27: 1 | DA27: 1 | DB27: 1 | DC27: 1 | DD27: 1
A28: Ser02_03 | B28: Final | C28: Services | D28: Buildings | E28: Space - Services | F28: Space with insulation B - Services | G28: [Mm2/y] | H28: 95.3 | I28: 95.3 | J28: 95.3 | K28: 73.1 | L28: 73.1 | M28: 22 | N28: 22 | O28: 0.9 | P28: 0.32 | Q28: 0.32 | R28: 0.32 | S28: 0.32 | T28: 0.32 | U28: 0.32 | V28: 0.32 | W28: 0 | X28: 0 | Y28: 0 | Z28: 0 | AA28: 0 | AB28: 0 | AC28: 0 | AD28: 0.05 | AE28: 0 | AF28: 25 | AG28: 25 | AH28: 1 | AI28: Operation | AJ28: Built Environment | AX28: none | BK28: 0 | BL28: =IF(AG28=1,0,1) -> 1 | BN28: 210 | BO28: 10 | BP28: 50 | BQ28: 70 | BR28: 50 | BS28: 30 | BU28: =IF(BL28=1,BN28,0) -> 210 | CB28: 210 | CC28: =CK28 -> 530 | CD28: =CL28 -> 540 | CE28: =CM28 -> 550 | CF28: =CN28 -> 555 | CG28: =CO28 -> 560 | CH28: =CP28 -> 560 | CI28: [1],[12] | CJ28: =VLOOKUP($E28,[2]Activities!$A$9:$I$162,3,FALSE)/$AH28 -> 515 | CK28: =VLOOKUP($E28,[2]Activities!$A$9:$I$162,4,FALSE)/$AH28 -> 530 | CL28: =VLOOKUP($E28,[2]Activities!$A$9:$I$162,5,FALSE)/$AH28 -> 540 | CM28: =VLOOKUP($E28,[2]Activities!$A$9:$I$162,6,FALSE)/$AH28 -> 550 | CN28: =VLOOKUP($E28,[2]Activities!$A$9:$I$162,7,FALSE)/$AH28 -> 555 | CO28: =VLOOKUP($E28,[2]Activities!$A$9:$I$162,8,FALSE)/$AH28 -> 560 | CP28: =VLOOKUP($E28,[2]Activities!$A$9:$I$162,9,FALSE)/$AH28 -> 560 | CR28: 1 | CS28: 1 | CT28: 1 | CU28: 1 | CV28: 1 | CW28: 1 | CX28: 1 | CY28: 1 | CZ28: 1 | DA28: 1 | DB28: 1 | DC28: 1 | DD28: 1
A29: Ser02_04 | B29: Final | C29: Services | D29: Buildings | E29: Space - Services | F29: Space with insulation A - Services | G29: [Mm2/y] | H29: 109.9 | I29: 107.2 | J29: 104.5 | K29: 82.6 | L29: 77.7 | M29: 26 | N29: 24 | O29: 0.9 | P29: 0.32 | Q29: 0.32 | R29: 0.32 | S29: 0.32 | T29: 0.32 | U29: 0.32 | V29: 0.32 | W29: 0 | X29: 0 | Y29: 0 | Z29: 0 | AA29: 0 | AB29: 0 | AC29: 0 | AD29: 0.05 | AE29: 0 | AF29: 25 | AG29: 25 | AH29: 1 | AI29: Operation | AJ29: Built Environment | AX29: none | BK29: 0 | BL29: =IF(AG29=1,0,1) -> 1 | BN29: 10 | BQ29: 0 | BR29: 0 | BS29: 10 | BT29: 0 | BU29: =IF(BL29=1,BN29,0) -> 10 | CB29: 10 | CC29: =CK29 -> 530 | CD29: =CL29 -> 540 | CE29: =CM29 -> 550 | CF29: =CN29 -> 555 | CG29: =CO29 -> 560 | CH29: =CP29 -> 560 | CI29: [12] | CJ29: =VLOOKUP($E29,[2]Activities!$A$9:$I$162,3,FALSE)/$AH29 -> 515 | CK29: =VLOOKUP($E29,[2]Activities!$A$9:$I$162,4,FALSE)/$AH29 -> 530 | CL29: =VLOOKUP($E29,[2]Activities!$A$9:$I$162,5,FALSE)/$AH29 -> 540 | CM29: =VLOOKUP($E29,[2]Activities!$A$9:$I$162,6,FALSE)/$AH29 -> 550 | CN29: =VLOOKUP($E29,[2]Activities!$A$9:$I$162,7,FALSE)/$AH29 -> 555 | CO29: =VLOOKUP($E29,[2]Activities!$A$9:$I$162,8,FALSE)/$AH29 -> 560 | CP29: =VLOOKUP($E29,[2]Activities!$A$9:$I$162,9,FALSE)/$AH29 -> 560 | CX29: 1 | CY29: 1 | CZ29: 1 | DA29: 1 | DB29: 1 | DC29: 1 | DD29: 1
A30: Ser02_05 | B30: Final | C30: Services | D30: Buildings | E30: Space - Services | F30: Space with insulation A+ - Services | G30: [Mm2/y] | H30: 122.64 | I30: 116.5 | J30: 110.4 | K30: 88.5 | L30: 82.5 | M30: 30 | N30: 28 | O30: 0.9 | P30: 0.32 | Q30: 0.32 | R30: 0.32 | S30: 0.32 | T30: 0.32 | U30: 0.32 | V30: 0.32 | W30: 0 | X30: 0 | Y30: 0 | Z30: 0 | AA30: 0 | AB30: 0 | AC30: 0 | AD30: 0.05 | AE30: 0 | AF30: 25 | AG30: 25 | AH30: 1 | AI30: Operation | AJ30: Built Environment | AX30: none | BK30: 0 | BL30: =IF(AG30=1,0,1) -> 1 | BN30: 5 | BQ30: 0 | BR30: 0 | BS30: 5 | BT30: 0 | BU30: =IF(BL30=1,BN30,0) -> 5 | CB30: 5 | CC30: =CK30 -> 530 | CD30: =CL30 -> 540 | CE30: =CM30 -> 550 | CF30: =CN30 -> 555 | CG30: =CO30 -> 560 | CH30: =CP30 -> 560 | CI30: [12] | CJ30: =VLOOKUP($E30,[2]Activities!$A$9:$I$162,3,FALSE)/$AH30 -> 515 | CK30: =VLOOKUP($E30,[2]Activities!$A$9:$I$162,4,FALSE)/$AH30 -> 530 | CL30: =VLOOKUP($E30,[2]Activities!$A$9:$I$162,5,FALSE)/$AH30 -> 540 | CM30: =VLOOKUP($E30,[2]Activities!$A$9:$I$162,6,FALSE)/$AH30 -> 550 | CN30: =VLOOKUP($E30,[2]Activities!$A$9:$I$162,7,FALSE)/$AH30 -> 555 | CO30: =VLOOKUP($E30,[2]Activities!$A$9:$I$162,8,FALSE)/$AH30 -> 560 | CP30: =VLOOKUP($E30,[2]Activities!$A$9:$I$162,9,FALSE)/$AH30 -> 560 | CX30: 1 | CY30: 1 | CZ30: 1 | DA30: 1 | DB30: 1 | DC30: 1 | DD30: 1
A31: Agr01_01 | B31: Final | C31: Agriculture | D31: Appliances | E31: Electricity demand - Agricuture | F31: Dummy standard electricity consumption - Agriculture | G31: [PJ/y] | H31: 0 | I31: 0 | J31: 0 | K31: 0 | L31: 0 | M31: 0 | N31: 0 | O31: 0 | P31: 0 | Q31: 0 | R31: 0 | S31: 0 | T31: 0 | U31: 0 | V31: 0 | W31: 0 | X31: 0 | Y31: 0 | Z31: 0 | AA31: 0 | AB31: 0 | AC31: 0 | AD31: 0.05 | AE31: 0 | AF31: 1 | AG31: 1 | AH31: 1 | AI31: Operation | AJ31: Standard Load | AX31: none | BK31: 0 | BL31: =IF(AG31=1,0,1) -> 0 | BQ31: 0 | BR31: 0 | BS31: 0 | BT31: 0 | BU31: =IF(BL31=1,BN31,0) -> 0 | CB31: =CJ31 -> 36 | CC31: =CK31 -> 37 | CD31: =CL31 -> 38 | CE31: =CM31 -> 39 | CF31: =CN31 -> 40 | CG31: =CO31 -> 41 | CH31: =CP31 -> 42 | CI31: [1],[9],[12] | CJ31: =VLOOKUP($E31,[2]Activities!$A$9:$I$162,3,FALSE)/$AH31 -> 36 | CK31: =VLOOKUP($E31,[2]Activities!$A$9:$I$162,4,FALSE)/$AH31 -> 37 | CL31: =VLOOKUP($E31,[2]Activities!$A$9:$I$162,5,FALSE)/$AH31 -> 38 | CM31: =VLOOKUP($E31,[2]Activities!$A$9:$I$162,6,FALSE)/$AH31 -> 39 | CN31: =VLOOKUP($E31,[2]Activities!$A$9:$I$162,7,FALSE)/$AH31 -> 40 | CO31: =VLOOKUP($E31,[2]Activities!$A$9:$I$162,8,FALSE)/$AH31 -> 41 | CP31: =VLOOKUP($E31,[2]Activities!$A$9:$I$162,9,FALSE)/$AH31 -> 42
A32: Agr02_01 | B32: Final | C32: Agriculture | D32: Heat demand horticulture | E32: Heat demand - Agriculture Horticulture | F32: Dummy balance heat consumption - Agriculture Horticulture | G32: [PJ/y] | H32: 0 | I32: 0 | J32: 0 | K32: 0 | L32: 0 | M32: 0 | N32: 0 | O32: 0 | P32: 0 | Q32: 0 | R32: 0 | S32: 0 | T32: 0 | U32: 0 | V32: 0 | W32: 0 | X32: 0 | Y32: 0 | Z32: 0 | AA32: 0 | AB32: 0 | AC32: 0 | AD32: 0.05 | AE32: 0 | AF32: 1 | AG32: 1 | AH32: 1 | AI32: Operation | AJ32: Flat high spread | AX32: none | BK32: 0 | BL32: =IF(AG32=1,0,1) -> 0 | BO32: 0 | BP32: 0 | BQ32: 0 | BR32: 0 | BS32: 0 | BT32: 0 | BU32: =IF(BL32=1,BN32,0) -> 0 | CB32: =CJ32 -> 88 | CC32: =CK32 -> 90 | CD32: =CL32 -> 92 | CE32: =CM32 -> 94 | CF32: =CN32 -> 96 | CG32: =CO32 -> 98 | CH32: =CP32 -> 100 | CI32: [1],[9],[12] | CJ32: =VLOOKUP($E32,[2]Activities!$A$9:$I$162,3,FALSE)/$AH32 -> 88 | CK32: =VLOOKUP($E32,[2]Activities!$A$9:$I$162,4,FALSE)/$AH32 -> 90 | CL32: =VLOOKUP($E32,[2]Activities!$A$9:$I$162,5,FALSE)/$AH32 -> 92 | CM32: =VLOOKUP($E32,[2]Activities!$A$9:$I$162,6,FALSE)/$AH32 -> 94 | CN32: =VLOOKUP($E32,[2]Activities!$A$9:$I$162,7,FALSE)/$AH32 -> 96 | CO32: =VLOOKUP($E32,[2]Activities!$A$9:$I$162,8,FALSE)/$AH32 -> 98 | CP32: =VLOOKUP($E32,[2]Activities!$A$9:$I$162,9,FALSE)/$AH32 -> 100
A33: Agr03_01 | B33: Final | C33: Agriculture | D33: Heat demand other | E33: Heat demand - Agriculture Other | F33: Dummy balance heat consumption - Agriculture Other | G33: [PJ/y] | H33: 0 | I33: 0 | J33: 0 | K33: 0 | L33: 0 | M33: 0 | N33: 0 | O33: 0 | P33: 0 | Q33: 0 | R33: 0 | S33: 0 | T33: 0 | U33: 0 | V33: 0 | W33: 0 | X33: 0 | Y33: 0 | Z33: 0 | AA33: 0 | AB33: 0 | AC33: 0 | AD33: 0.05 | AE33: 0 | AF33: 1 | AG33: 1 | AH33: 1 | AI33: Operation | AJ33: Flat high spread | AX33: none | BK33: 0 | BL33: =IF(AG33=1,0,1) -> 0 | BO33: 0 | BP33: 0 | BQ33: 0 | BR33: 0 | BS33: 0 | BT33: 0 | BU33: =IF(BL33=1,BN33,0) -> 0 | CB33: =CJ33 -> 8.4 | CC33: =CK33 -> 8.6 | CD33: =CL33 -> 8.8 | CE33: =CM33 -> 9 | CF33: =CN33 -> 9.2 | CG33: =CO33 -> 9.4 | CH33: =CP33 -> 9.6 | CI33: [1],[9],[12] | CJ33: =VLOOKUP($E33,[2]Activities!$A$9:$I$162,3,FALSE)/$AH33 -> 8.4 | CK33: =VLOOKUP($E33,[2]Activities!$A$9:$I$162,4,FALSE)/$AH33 -> 8.6 | CL33: =VLOOKUP($E33,[2]Activities!$A$9:$I$162,5,FALSE)/$AH33 -> 8.8 | CM33: =VLOOKUP($E33,[2]Activities!$A$9:$I$162,6,FALSE)/$AH33 -> 9 | CN33: =VLOOKUP($E33,[2]Activities!$A$9:$I$162,7,FALSE)/$AH33 -> 9.2 | CO33: =VLOOKUP($E33,[2]Activities!$A$9:$I$162,8,FALSE)/$AH33 -> 9.4 | CP33: =VLOOKUP($E33,[2]Activities!$A$9:$I$162,9,FALSE)/$AH33 -> 9.6
A34: Agr04_01 | B34: Final | C34: Agriculture | D34: Machinery | E34: Machinery - Agriculture | F34: Fuel based machinery - Agriculture | G34: [PJ/y] | H34: 265 | I34: 265 | J34: 265 | K34: 265 | L34: 265 | M34: 265 | N34: 265 | O34: 0.9 | P34: 0 | Q34: 0 | R34: 0 | S34: 0 | T34: 0 | U34: 0 | V34: 0 | W34: 0 | X34: 0 | Y34: 0 | Z34: 0 | AA34: 0 | AB34: 0 | AC34: 0 | AD34: 0.05 | AE34: 0 | AF34: 15 | AG34: 15 | AH34: 1 | AI34: Operation | AJ34: Flat high spread | AX34: none | BK34: 0 | BL34: =IF(AG34=1,0,1) -> 1 | BN34: 20.7 | BO34: 6.9 | BP34: 6.9 | BQ34: 6.9 | BU34: =IF(BL34=1,BN34,0) -> 20.7 | CB34: =CJ34 -> 23 | CC34: =CK34 -> 24 | CD34: =CL34 -> 25 | CE34: =CM34 -> 26 | CF34: =CN34 -> 27 | CG34: =CO34 -> 28 | CH34: =CP34 -> 29 | CI34: [12] | CJ34: =VLOOKUP($E34,[2]Activities!$A$9:$I$162,3,FALSE)/$AH34 -> 23 | CK34: =VLOOKUP($E34,[2]Activities!$A$9:$I$162,4,FALSE)/$AH34 -> 24 | CL34: =VLOOKUP($E34,[2]Activities!$A$9:$I$162,5,FALSE)/$AH34 -> 25 | CM34: =VLOOKUP($E34,[2]Activities!$A$9:$I$162,6,FALSE)/$AH34 -> 26 | CN34: =VLOOKUP($E34,[2]Activities!$A$9:$I$162,7,FALSE)/$AH34 -> 27 | CO34: =VLOOKUP($E34,[2]Activities!$A$9:$I$162,8,FALSE)/$AH34 -> 28 | CP34: =VLOOKUP($E34,[2]Activities!$A$9:$I$162,9,FALSE)/$AH34 -> 29
A35: Agr04_02 | B35: Final | C35: Agriculture | D35: Machinery | E35: Machinery - Agriculture | F35: Hybrid machinery - Agriculture | G35: [PJ/y] | H35: 570 | I35: 541.5 | J35: 514.43 | K35: 488.7 | L35: 464.27 | M35: 441.06 | N35: 419 | O35: 0.9 | P35: 0 | Q35: 0 | R35: 0 | S35: 0 | T35: 0 | U35: 0 | V35: 0 | W35: 0 | X35: 0 | Y35: 0 | Z35: 0 | AA35: 0 | AB35: 0 | AC35: 0 | AD35: 0.05 | AE35: 0 | AF35: 15 | AG35: 15 | AH35: 1 | AI35: Operation | AJ35: Flat high spread | AX35: none | BK35: 0 | BL35: =IF(AG35=1,0,1) -> 1 | BN35: 2.1 | BO35: 0.07 | BP35: 0.5 | BQ35: 1.5 | BU35: =IF(BL35=1,BN35,0) -> 2.1 | CB35: =CJ35 -> 23 | CC35: =CK35 -> 24 | CD35: =CL35 -> 25 | CE35: =CM35 -> 26 | CF35: =CN35 -> 27 | CG35: =CO35 -> 28 | CH35: =CP35 -> 29 | CI35: [1] | CJ35: =VLOOKUP($E35,[2]Activities!$A$9:$I$162,3,FALSE)/$AH35 -> 23 | CK35: =VLOOKUP($E35,[2]Activities!$A$9:$I$162,4,FALSE)/$AH35 -> 24 | CL35: =VLOOKUP($E35,[2]Activities!$A$9:$I$162,5,FALSE)/$AH35 -> 25 | CM35: =VLOOKUP($E35,[2]Activities!$A$9:$I$162,6,FALSE)/$AH35 -> 26 | CN35: =VLOOKUP($E35,[2]Activities!$A$9:$I$162,7,FALSE)/$AH35 -> 27 | CO35: =VLOOKUP($E35,[2]Activities!$A$9:$I$162,8,FALSE)/$AH35 -> 28 | CP35: =VLOOKUP($E35,[2]Activities!$A$9:$I$162,9,FALSE)/$AH35 -> 29
A36: IBM01_01 | B36: Final | C36: Industry | D36: Basic Metals | E36: Steel production - Basic Metals Industry | F36: Blast furnace BOF - Steel Production | G36: [Mton_Steel/y] | H36: 550.5 | I36: 550.5 | J36: 550.5 | K36: 550.5 | L36: 550.5 | M36: 550.5 | N36: 550.5 | O36: 0.9 | P36: 34.6 | Q36: 34.6 | R36: 34.6 | S36: 34.6 | T36: 34.6 | U36: 34.6 | V36: 34.6 | W36: 170 | X36: 170 | Y36: 170 | Z36: 170 | AA36: 170 | AB36: 170 | AC36: 170 | AD36: 0.05 | AE36: 0 | AF36: 30 | AG36: 30 | AH36: 1 | AI36: Operation | AJ36: Flat low night | AX36: none | BK36: 0 | BL36: =IF(AG36=1,0,1) -> 1 | BN36: 7 | BR36: 7 | BU36: =IF(BL36=1,BN36,0) -> 7 | CB36: 7 | CC36: 7 | CD36: =CL36 -> 7 | CE36: =CM36 -> 7 | CF36: =CN36 -> 7 | CG36: =CO36 -> 7 | CH36: =CP36 -> 7 | CI36: [51] | CJ36: =VLOOKUP($E36,[2]Activities!$A$9:$I$162,3,FALSE)/$AH36 -> 7 | CK36: =VLOOKUP($E36,[2]Activities!$A$9:$I$162,4,FALSE)/$AH36 -> 7 | CL36: =VLOOKUP($E36,[2]Activities!$A$9:$I$162,5,FALSE)/$AH36 -> 7 | CM36: =VLOOKUP($E36,[2]Activities!$A$9:$I$162,6,FALSE)/$AH36 -> 7 | CN36: =VLOOKUP($E36,[2]Activities!$A$9:$I$162,7,FALSE)/$AH36 -> 7 | CO36: =VLOOKUP($E36,[2]Activities!$A$9:$I$162,8,FALSE)/$AH36 -> 7 | CP36: =VLOOKUP($E36,[2]Activities!$A$9:$I$162,9,FALSE)/$AH36 -> 7
A37: IBM01_02 | B37: Final | C37: Industry | D37: Basic Metals | E37: Steel production - Basic Metals Industry | F37: Blast furnace BOF wCCUS (end-of-pipe) - Steel Production | G37: [Mton_Steel/y] | H37: 795 | I37: 795 | J37: 795 | K37: 795 | L37: 795 | M37: 795 | N37: 795 | O37: 0.9 | P37: 60.9 | Q37: 60.9 | R37: 60.9 | S37: 60.9 | T37: 60.9 | U37: 60.9 | V37: 60.9 | W37: 170 | X37: 170 | Y37: 170 | Z37: 170 | AA37: 170 | AB37: 170 | AC37: 170 | AD37: 0.05 | AE37: 0 | AF37: 30 | AG37: 30 | AH37: 1 | AI37: Operation | AJ37: Flat low night | AX37: none | BK37: 0 | BL37: =IF(AG37=1,0,1) -> 1 | BN37: 0 | BU37: =IF(BL37=1,BN37,0) -> 0 | CB37: 0 | CC37: 4 | CD37: 7 | CE37: =CM37 -> 7 | CF37: =CN37 -> 7 | CG37: =CO37 -> 7 | CH37: =CP37 -> 7 | CI37: [51] | CJ37: =VLOOKUP($E37,[2]Activities!$A$9:$I$162,3,FALSE)/$AH37 -> 7 | CK37: =VLOOKUP($E37,[2]Activities!$A$9:$I$162,4,FALSE)/$AH37 -> 7 | CL37: =VLOOKUP($E37,[2]Activities!$A$9:$I$162,5,FALSE)/$AH37 -> 7 | CM37: =VLOOKUP($E37,[2]Activities!$A$9:$I$162,6,FALSE)/$AH37 -> 7 | CN37: =VLOOKUP($E37,[2]Activities!$A$9:$I$162,7,FALSE)/$AH37 -> 7 | CO37: =VLOOKUP($E37,[2]Activities!$A$9:$I$162,8,FALSE)/$AH37 -> 7 | CP37: =VLOOKUP($E37,[2]Activities!$A$9:$I$162,9,FALSE)/$AH37 -> 7
A38: IBM01_03 | B38: Final | C38: Industry | D38: Basic Metals | E38: Steel production - Basic Metals Industry | F38: Blast furnace BOF with top gas recycling wCCUS (end-of-pipe) - Steel Production | G38: [Mton_Steel/y] | H38: 815 | I38: 815 | J38: 815 | K38: 815 | L38: 815 | M38: 815 | N38: 815 | O38: 0.9 | P38: 67.8 | Q38: 67.8 | R38: 67.8 | S38: 67.8 | T38: 67.8 | U38: 67.8 | V38: 67.8 | W38: 170 | X38: 170 | Y38: 170 | Z38: 170 | AA38: 170 | AB38: 170 | AC38: 170 | AD38: 0.05 | AE38: 0 | AF38: 30 | AG38: 30 | AH38: 1 | AI38: Operation | AJ38: Flat low night | AX38: none | BK38: 0 | BL38: =IF(AG38=1,0,1) -> 1 | BN38: 0 | BU38: =IF(BL38=1,BN38,0) -> 0 | CB38: 0 | CC38: 4 | CD38: 7 | CE38: =CM38 -> 7 | CF38: =CN38 -> 7 | CG38: =CO38 -> 7 | CH38: =CP38 -> 7 | CI38: [51] | CJ38: =VLOOKUP($E38,[2]Activities!$A$9:$I$162,3,FALSE)/$AH38 -> 7 | CK38: =VLOOKUP($E38,[2]Activities!$A$9:$I$162,4,FALSE)/$AH38 -> 7 | CL38: =VLOOKUP($E38,[2]Activities!$A$9:$I$162,5,FALSE)/$AH38 -> 7 | CM38: =VLOOKUP($E38,[2]Activities!$A$9:$I$162,6,FALSE)/$AH38 -> 7 | CN38: =VLOOKUP($E38,[2]Activities!$A$9:$I$162,7,FALSE)/$AH38 -> 7 | CO38: =VLOOKUP($E38,[2]Activities!$A$9:$I$162,8,FALSE)/$AH38 -> 7 | CP38: =VLOOKUP($E38,[2]Activities!$A$9:$I$162,9,FALSE)/$AH38 -> 7
A39: IBM01_04 | B39: Final | C39: Industry | D39: Basic Metals | E39: Steel production - Basic Metals Industry | F39: Hisarna - Steel Production | G39: [Mton_Steel/y] | H39: 575 | I39: 470 | J39: 370 | K39: 360 | L39: 345 | M39: 335 | N39: 320 | O39: 0.9 | P39: 70.9 | Q39: 70.9 | R39: 62.6 | S39: 62.6 | T39: 52 | U39: 52 | V39: 42.2 | W39: 170 | X39: 170 | Y39: 170 | Z39: 170 | AA39: 170 | AB39: 170 | AC39: 170 | AD39: 0.05 | AE39: 0 | AF39: 30 | AG39: 30 | AH39: 1 | AI39: Operation | AJ39: Flat low night | AX39: none | BK39: 0 | BL39: =IF(AG39=1,0,1) -> 1 | BN39: 0 | BU39: =IF(BL39=1,BN39,0) -> 0 | CB39: 0.06 | CC39: 4 | CD39: =CL39 -> 7 | CE39: =CM39 -> 7 | CF39: =CN39 -> 7 | CG39: =CO39 -> 7 | CH39: =CP39 -> 7 | CI39: [51] | CJ39: =VLOOKUP($E39,[2]Activities!$A$9:$I$162,3,FALSE)/$AH39 -> 7 | CK39: =VLOOKUP($E39,[2]Activities!$A$9:$I$162,4,FALSE)/$AH39 -> 7 | CL39: =VLOOKUP($E39,[2]Activities!$A$9:$I$162,5,FALSE)/$AH39 -> 7 | CM39: =VLOOKUP($E39,[2]Activities!$A$9:$I$162,6,FALSE)/$AH39 -> 7 | CN39: =VLOOKUP($E39,[2]Activities!$A$9:$I$162,7,FALSE)/$AH39 -> 7 | CO39: =VLOOKUP($E39,[2]Activities!$A$9:$I$162,8,FALSE)/$AH39 -> 7 | CP39: =VLOOKUP($E39,[2]Activities!$A$9:$I$162,9,FALSE)/$AH39 -> 7
A40: IBM01_05 | B40: Final | C40: Industry | D40: Basic Metals | E40: Steel production - Basic Metals Industry | F40: Hisarna wCCUS (cryogenic) - Steel Production | G40: [Mton_Steel/y] | H40: 840 | I40: 690 | J40: 545 | K40: 545 | L40: 545 | M40: 545 | N40: 545 | O40: 0.9 | P40: 97.7 | Q40: 97.7 | R40: 86.3 | S40: 86.3 | T40: 77 | U40: 77 | V40: 68.3 | W40: 170 | X40: 170 | Y40: 170 | Z40: 170 | AA40: 170 | AB40: 170 | AC40: 170 | AD40: 0.05 | AE40: 0 | AF40: 30 | AG40: 30 | AH40: 1 | AI40: Operation | AJ40: Flat low night | AX40: none | BK40: 0 | BL40: =IF(AG40=1,0,1) -> 1 | BN40: 0 | BU40: =IF(BL40=1,BN40,0) -> 0 | CB40: 0 | CC40: 4 | CD40: =CL40 -> 7 | CE40: =CM40 -> 7 | CF40: =CN40 -> 7 | CG40: =CO40 -> 7 | CH40: =CP40 -> 7 | CI40: [51] | CJ40: =VLOOKUP($E40,[2]Activities!$A$9:$I$162,3,FALSE)/$AH40 -> 7 | CK40: =VLOOKUP($E40,[2]Activities!$A$9:$I$162,4,FALSE)/$AH40 -> 7 | CL40: =VLOOKUP($E40,[2]Activities!$A$9:$I$162,5,FALSE)/$AH40 -> 7 | CM40: =VLOOKUP($E40,[2]Activities!$A$9:$I$162,6,FALSE)/$AH40 -> 7 | CN40: =VLOOKUP($E40,[2]Activities!$A$9:$I$162,7,FALSE)/$AH40 -> 7 | CO40: =VLOOKUP($E40,[2]Activities!$A$9:$I$162,8,FALSE)/$AH40 -> 7 | CP40: =VLOOKUP($E40,[2]Activities!$A$9:$I$162,9,FALSE)/$AH40 -> 7
A41: IBM01_06 | B41: Final | C41: Industry | D41: Basic Metals | E41: Steel production - Basic Metals Industry | F41: Hisarna biomass wCCUS (cryogenic) - Steel Production | G41: [Mton_Steel/y] | H41: 900 | I41: 750 | J41: 600 | K41: 600 | L41: 600 | M41: 600 | N41: 600 | O41: 0.9 | P41: 105 | Q41: 105 | R41: 90 | S41: 90 | T41: 80 | U41: 80 | V41: 70 | W41: 170 | X41: 170 | Y41: 170 | Z41: 170 | AA41: 170 | AB41: 170 | AC41: 170 | AD41: 0.05 | AE41: 0 | AF41: 30 | AG41: 30 | AH41: 1 | AI41: Operation | AJ41: Flat low night | AX41: none | BK41: 0 | BL41: =IF(AG41=1,0,1) -> 1 | BN41: 0 | BU41: =IF(BL41=1,BN41,0) -> 0 | CB41: 0 | CC41: 4 | CD41: =CL41 -> 7 | CE41: =CM41 -> 7 | CF41: =CN41 -> 7 | CG41: =CO41 -> 7 | CH41: =CP41 -> 7 | CI41: [51] | CJ41: =VLOOKUP($E41,[2]Activities!$A$9:$I$162,3,FALSE)/$AH41 -> 7 | CK41: =VLOOKUP($E41,[2]Activities!$A$9:$I$162,4,FALSE)/$AH41 -> 7 | CL41: =VLOOKUP($E41,[2]Activities!$A$9:$I$162,5,FALSE)/$AH41 -> 7 | CM41: =VLOOKUP($E41,[2]Activities!$A$9:$I$162,6,FALSE)/$AH41 -> 7 | CN41: =VLOOKUP($E41,[2]Activities!$A$9:$I$162,7,FALSE)/$AH41 -> 7 | CO41: =VLOOKUP($E41,[2]Activities!$A$9:$I$162,8,FALSE)/$AH41 -> 7 | CP41: =VLOOKUP($E41,[2]Activities!$A$9:$I$162,9,FALSE)/$AH41 -> 7
A42: IBM01_07 | B42: Final | C42: Industry | D42: Basic Metals | E42: Steel production - Basic Metals Industry | F42: Direct reduction from natural gas - Steel Production | G42: [Mton_Steel/y] | H42: 435 | I42: 435 | J42: 435 | K42: 435 | L42: 435 | M42: 435 | N42: 435 | O42: 0.9 | P42: 13 | Q42: 13 | R42: 13 | S42: 13 | T42: 13 | U42: 13 | V42: 13 | W42: 170 | X42: 170 | Y42: 170 | Z42: 170 | AA42: 170 | AB42: 170 | AC42: 170 | AD42: 0.05 | AE42: 0 | AF42: 30 | AG42: 30 | AH42: 1 | AI42: Operation | AJ42: Flat low night | AX42: none | BK42: 0 | BL42: =IF(AG42=1,0,1) -> 1 | BN42: 0 | BU42: =IF(BL42=1,BN42,0) -> 0 | CB42: 0 | CC42: 4 | CD42: 7 | CE42: =CM42 -> 7 | CF42: =CN42 -> 7 | CG42: =CO42 -> 7 | CH42: =CP42 -> 7 | CI42: [51] | CJ42: =VLOOKUP($E42,[2]Activities!$A$9:$I$162,3,FALSE)/$AH42 -> 7 | CK42: =VLOOKUP($E42,[2]Activities!$A$9:$I$162,4,FALSE)/$AH42 -> 7 | CL42: =VLOOKUP($E42,[2]Activities!$A$9:$I$162,5,FALSE)/$AH42 -> 7 | CM42: =VLOOKUP($E42,[2]Activities!$A$9:$I$162,6,FALSE)/$AH42 -> 7 | CN42: =VLOOKUP($E42,[2]Activities!$A$9:$I$162,7,FALSE)/$AH42 -> 7 | CO42: =VLOOKUP($E42,[2]Activities!$A$9:$I$162,8,FALSE)/$AH42 -> 7 | CP42: =VLOOKUP($E42,[2]Activities!$A$9:$I$162,9,FALSE)/$AH42 -> 7
A43: IBM01_08 | B43: Final | C43: Industry | D43: Basic Metals | E43: Steel production - Basic Metals Industry | F43: Direct reduction from hydrogen - Steel Production | G43: [Mton_Steel/y] | H43: 435 | I43: 435 | J43: 435 | K43: 435 | L43: 435 | M43: 435 | N43: 435 | O43: 0.9 | P43: 13 | Q43: 13 | R43: 13 | S43: 13 | T43: 13 | U43: 13 | V43: 13 | W43: 170 | X43: 170 | Y43: 170 | Z43: 170 | AA43: 170 | AB43: 170 | AC43: 170 | AD43: 0.05 | AE43: 0 | AF43: 30 | AG43: 30 | AH43: 1 | AI43: Operation | AJ43: Flat low night | AX43: none | BK43: 0 | BL43: =IF(AG43=1,0,1) -> 1 | BN43: 0 | BU43: =IF(BL43=1,BN43,0) -> 0 | CB43: 0 | CD43: 7 | CE43: 7 | CF43: =CN43 -> 7 | CG43: =CO43 -> 7 | CH43: =CP43 -> 7 | CI43: [51] | CJ43: =VLOOKUP($E43,[2]Activities!$A$9:$I$162,3,FALSE)/$AH43 -> 7 | CK43: =VLOOKUP($E43,[2]Activities!$A$9:$I$162,4,FALSE)/$AH43 -> 7 | CL43: =VLOOKUP($E43,[2]Activities!$A$9:$I$162,5,FALSE)/$AH43 -> 7 | CM43: =VLOOKUP($E43,[2]Activities!$A$9:$I$162,6,FALSE)/$AH43 -> 7 | CN43: =VLOOKUP($E43,[2]Activities!$A$9:$I$162,7,FALSE)/$AH43 -> 7 | CO43: =VLOOKUP($E43,[2]Activities!$A$9:$I$162,8,FALSE)/$AH43 -> 7 | CP43: =VLOOKUP($E43,[2]Activities!$A$9:$I$162,9,FALSE)/$AH43 -> 7
A44: IBM01_09 | B44: Final | C44: Industry | D44: Basic Metals | E44: Steel production - Basic Metals Industry | F44: Direct reduction from hydrogen w/biomass - Steel Production | G44: [Mton_Steel/y] | H44: 435 | I44: 435 | J44: 435 | K44: 435 | L44: 435 | M44: 435 | N44: 435 | O44: 0.9 | P44: 13 | Q44: 13 | R44: 13 | S44: 13 | T44: 13 | U44: 13 | V44: 13 | W44: 170 | X44: 170 | Y44: 170 | Z44: 170 | AA44: 170 | AB44: 170 | AC44: 170 | AD44: 0.05 | AE44: 0 | AF44: 30 | AG44: 30 | AH44: 1 | AI44: Operation | AJ44: Flat low night | AX44: none | BK44: 0 | BL44: =IF(AG44=1,0,1) -> 1 | BN44: 0 | BU44: =IF(BL44=1,BN44,0) -> 0 | CB44: 0 | CF44: =CN44 -> 7 | CG44: =CO44 -> 7 | CH44: =CP44 -> 7 | CI44: [51] | CJ44: =VLOOKUP($E44,[2]Activities!$A$9:$I$162,3,FALSE)/$AH44 -> 7 | CK44: =VLOOKUP($E44,[2]Activities!$A$9:$I$162,4,FALSE)/$AH44 -> 7 | CL44: =VLOOKUP($E44,[2]Activities!$A$9:$I$162,5,FALSE)/$AH44 -> 7 | CM44: =VLOOKUP($E44,[2]Activities!$A$9:$I$162,6,FALSE)/$AH44 -> 7 | CN44: =VLOOKUP($E44,[2]Activities!$A$9:$I$162,7,FALSE)/$AH44 -> 7 | CO44: =VLOOKUP($E44,[2]Activities!$A$9:$I$162,8,FALSE)/$AH44 -> 7 | CP44: =VLOOKUP($E44,[2]Activities!$A$9:$I$162,9,FALSE)/$AH44 -> 7
A45: IBM01_10 | B45: Final | C45: Industry | D45: Basic Metals | E45: Steel production - Basic Metals Industry | F45: Low temperature electro winning - Steel Production | G45: [Mton_Steel/y] | H45: 1000 | I45: 950 | J45: 900 | K45: 835 | L45: 770 | M45: 705 | N45: 640 | O45: 0.9 | P45: 70 | Q45: 70 | R45: 60 | S45: 60 | T45: 53 | U45: 53 | V45: 45 | W45: 170 | X45: 170 | Y45: 170 | Z45: 170 | AA45: 170 | AB45: 170 | AC45: 170 | AD45: 0.05 | AE45: 0 | AF45: 30 | AG45: 30 | AH45: 1 | AI45: Shedding | AJ45: Flat | AR45: 0.0013 | AS45: 0.9 | AT45: 1 hour [h] | AX45: none | BK45: 1 | BL45: =IF(AG45=1,0,1) -> 1 | BN45: 0 | BU45: =IF(BL45=1,BN45,0) -> 0 | CD45: 4 | CE45: 10 | CF45: 10 | CG45: 10 | CH45: 10 | CI45: [51] | CJ45: =VLOOKUP($E45,[2]Activities!$A$9:$I$162,3,FALSE)/$AH45 -> 7 | CK45: =VLOOKUP($E45,[2]Activities!$A$9:$I$162,4,FALSE)/$AH45 -> 7 | CL45: =VLOOKUP($E45,[2]Activities!$A$9:$I$162,5,FALSE)/$AH45 -> 7 | CM45: =VLOOKUP($E45,[2]Activities!$A$9:$I$162,6,FALSE)/$AH45 -> 7 | CN45: =VLOOKUP($E45,[2]Activities!$A$9:$I$162,7,FALSE)/$AH45 -> 7 | CO45: =VLOOKUP($E45,[2]Activities!$A$9:$I$162,8,FALSE)/$AH45 -> 7 | CP45: =VLOOKUP($E45,[2]Activities!$A$9:$I$162,9,FALSE)/$AH45 -> 7
A46: IBM01_11 | B46: Final | C46: Industry | D46: Basic Metals | E46: Steel production - Basic Metals Industry | F46: High temperature electro winning - Steel Production | G46: [Mton_Steel/y] | H46: 1100 | I46: 980 | J46: 950 | K46: 890 | L46: 830 | M46: 770 | N46: 710 | O46: 0.9 | P46: 85 | Q46: 85 | R46: 75 | S46: 75 | T46: 66 | U46: 66 | V46: 58 | W46: 170 | X46: 170 | Y46: 170 | Z46: 170 | AA46: 170 | AB46: 170 | AC46: 170 | AD46: 0.05 | AE46: 0 | AF46: 30 | AG46: 30 | AH46: 1 | AI46: Shedding | AJ46: Flat | AR46: 0.0015 | AS46: 0.9 | AT46: 1 hour [h] | AX46: none | BK46: 1 | BL46: =IF(AG46=1,0,1) -> 1 | BN46: 0 | BU46: =IF(BL46=1,BN46,0) -> 0 | CD46: 4 | CE46: 10 | CF46: 10 | CG46: 10 | CH46: 10 | CI46: [51] | CJ46: =VLOOKUP($E46,[2]Activities!$A$9:$I$162,3,FALSE)/$AH46 -> 7 | CK46: =VLOOKUP($E46,[2]Activities!$A$9:$I$162,4,FALSE)/$AH46 -> 7 | CL46: =VLOOKUP($E46,[2]Activities!$A$9:$I$162,5,FALSE)/$AH46 -> 7 | CM46: =VLOOKUP($E46,[2]Activities!$A$9:$I$162,6,FALSE)/$AH46 -> 7 | CN46: =VLOOKUP($E46,[2]Activities!$A$9:$I$162,7,FALSE)/$AH46 -> 7 | CO46: =VLOOKUP($E46,[2]Activities!$A$9:$I$162,8,FALSE)/$AH46 -> 7 | CP46: =VLOOKUP($E46,[2]Activities!$A$9:$I$162,9,FALSE)/$AH46 -> 7
A47: IBM01_12 | B47: Final | C47: Industry | D47: Basic Metals | E47: Steel production - Basic Metals Industry | F47: Scrap-fed EAF - Steel Production | G47: [Mton_Steel/y] | H47: =455*(103.88/100) -> 472.654 | I47: =455*(103.88/100) -> 472.654 | J47: =455*(103.88/100) -> 472.654 | K47: =455*(103.88/100) -> 472.654 | L47: =455*(103.88/100) -> 472.654 | M47: =455*(103.88/100) -> 472.654 | N47: =455*(103.88/100) -> 472.654 | O47: 0.9 | P47: =39*(103.88/100) -> 40.5132 | Q47: =39*(103.88/100) -> 40.5132 | R47: =39*(103.88/100) -> 40.5132 | S47: =39*(103.88/100) -> 40.5132 | T47: =39*(103.88/100) -> 40.5132 | U47: =39*(103.88/100) -> 40.5132 | V47: =39*(103.88/100) -> 40.5132 | W47: =W36*1.2 -> 204 | X47: =X36*1.2 -> 204 | Y47: =Y36*1.2 -> 204 | Z47: =Z36*1.2 -> 204 | AA47: =AA36*1.2 -> 204 | AB47: =AB36*1.2 -> 204 | AC47: =AC36*1.2 -> 204 | AD47: 0.05 | AE47: 0 | AF47: 20 | AG47: 20 | AH47: 1 | AI47: Operation | AJ47: Flat low night | AX47: none | BL47: =IF(AG47=1,0,1) -> 1 | BN47: 0 | CC47: 4 | CD47: 7 | CE47: 7 | CF47: 7 | CG47: 7 | CH47: 7 | CJ47: =VLOOKUP($E47,[2]Activities!$A$9:$I$248,3,FALSE)/$AH47 -> 7 | CK47: =VLOOKUP($E47,[2]Activities!$A$9:$I$248,4,FALSE)/$AH47 -> 7 | CL47: =VLOOKUP($E47,[2]Activities!$A$9:$I$248,5,FALSE)/$AH47 -> 7 | CM47: =VLOOKUP($E47,[2]Activities!$A$9:$I$248,6,FALSE)/$AH47 -> 7 | CN47: =VLOOKUP($E47,[2]Activities!$A$9:$I$248,7,FALSE)/$AH47 -> 7 | CO47: =VLOOKUP($E47,[2]Activities!$A$9:$I$248,8,FALSE)/$AH47 -> 7 | CP47: =VLOOKUP($E47,[2]Activities!$A$9:$I$248,9,FALSE)/$AH47 -> 7
A48: IBM01_13 | B48: Final | C48: Industry | D48: Basic Metals | E48: Steel production - Basic Metals Industry | F48: Scrap-fed EAF with syngas fuel - Steel Production | G48: [Mton_Steel/y] | H48: =455*(103.88/100) -> 472.654 | I48: =455*(103.88/100) -> 472.654 | J48: =455*(103.88/100) -> 472.654 | K48: =455*(103.88/100) -> 472.654 | L48: =455*(103.88/100) -> 472.654 | M48: =455*(103.88/100) -> 472.654 | N48: =455*(103.88/100) -> 472.654 | O48: 0.9 | P48: =39*(103.88/100) -> 40.5132 | Q48: =39*(103.88/100) -> 40.5132 | R48: =39*(103.88/100) -> 40.5132 | S48: =39*(103.88/100) -> 40.5132 | T48: =39*(103.88/100) -> 40.5132 | U48: =39*(103.88/100) -> 40.5132 | V48: =39*(103.88/100) -> 40.5132 | W48: =W37*1.2 -> 204 | X48: =X37*1.2 -> 204 | Y48: =Y37*1.2 -> 204 | Z48: =Z37*1.2 -> 204 | AA48: =AA37*1.2 -> 204 | AB48: =AB37*1.2 -> 204 | AC48: =AC37*1.2 -> 204 | AD48: 0.05 | AE48: 0 | AF48: 20 | AG48: 20 | AH48: 1 | AI48: Operation | AJ48: Flat low night | AX48: none | BL48: =IF(AG48=1,0,1) -> 1 | BN48: 0 | CC48: 4 | CD48: 7 | CE48: 7 | CF48: 7 | CG48: 7 | CH48: 7 | CJ48: =VLOOKUP($E48,[2]Activities!$A$9:$I$248,3,FALSE)/$AH48 -> 7 | CK48: =VLOOKUP($E48,[2]Activities!$A$9:$I$248,4,FALSE)/$AH48 -> 7 | CL48: =VLOOKUP($E48,[2]Activities!$A$9:$I$248,5,FALSE)/$AH48 -> 7 | CM48: =VLOOKUP($E48,[2]Activities!$A$9:$I$248,6,FALSE)/$AH48 -> 7 | CN48: =VLOOKUP($E48,[2]Activities!$A$9:$I$248,7,FALSE)/$AH48 -> 7 | CO48: =VLOOKUP($E48,[2]Activities!$A$9:$I$248,8,FALSE)/$AH48 -> 7 | CP48: =VLOOKUP($E48,[2]Activities!$A$9:$I$248,9,FALSE)/$AH48 -> 7
A49: IBM01_15 | B49: Final | C49: Industry | D49: Basic Metals | E49: Steel production - Basic Metals Industry | F49: DRI-fed EAF - Steel Production | G49: [Mton_Steel/y] | H49: =455*(103.88/100) -> 472.654 | I49: =455*(103.88/100) -> 472.654 | J49: =455*(103.88/100) -> 472.654 | K49: =455*(103.88/100) -> 472.654 | L49: =455*(103.88/100) -> 472.654 | M49: =455*(103.88/100) -> 472.654 | N49: =455*(103.88/100) -> 472.654 | O49: 0.9 | P49: =39*(103.88/100) -> 40.5132 | Q49: =39*(103.88/100) -> 40.5132 | R49: =39*(103.88/100) -> 40.5132 | S49: =39*(103.88/100) -> 40.5132 | T49: =39*(103.88/100) -> 40.5132 | U49: =39*(103.88/100) -> 40.5132 | V49: =39*(103.88/100) -> 40.5132 | W49: =W39*1.2 -> 204 | X49: =X39*1.2 -> 204 | Y49: =Y39*1.2 -> 204 | Z49: =Z39*1.2 -> 204 | AA49: =AA39*1.2 -> 204 | AB49: =AB39*1.2 -> 204 | AC49: =AC39*1.2 -> 204 | AD49: 0.05 | AE49: 0 | AF49: 20 | AG49: 20 | AH49: 1 | AI49: Operation | AJ49: Flat low night | AX49: none | BL49: =IF(AG49=1,0,1) -> 1 | BN49: 0 | CC49: 4 | CD49: 7 | CE49: 7 | CF49: 7 | CG49: 7 | CH49: 7 | CJ49: =VLOOKUP($E49,[2]Activities!$A$9:$I$248,3,FALSE)/$AH49 -> 7 | CK49: =VLOOKUP($E49,[2]Activities!$A$9:$I$248,4,FALSE)/$AH49 -> 7 | CL49: =VLOOKUP($E49,[2]Activities!$A$9:$I$248,5,FALSE)/$AH49 -> 7 | CM49: =VLOOKUP($E49,[2]Activities!$A$9:$I$248,6,FALSE)/$AH49 -> 7 | CN49: =VLOOKUP($E49,[2]Activities!$A$9:$I$248,7,FALSE)/$AH49 -> 7 | CO49: =VLOOKUP($E49,[2]Activities!$A$9:$I$248,8,FALSE)/$AH49 -> 7 | CP49: =VLOOKUP($E49,[2]Activities!$A$9:$I$248,9,FALSE)/$AH49 -> 7
A50: IBM01_16 | B50: Final | C50: Industry | D50: Basic Metals | E50: Steel production - Basic Metals Industry | F50: DRI-fed EAF with syngas fuel - Steel Production | G50: [Mton_Steel/y] | H50: =455*(103.88/100) -> 472.654 | I50: =455*(103.88/100) -> 472.654 | J50: =455*(103.88/100) -> 472.654 | K50: =455*(103.88/100) -> 472.654 | L50: =455*(103.88/100) -> 472.654 | M50: =455*(103.88/100) -> 472.654 | N50: =455*(103.88/100) -> 472.654 | O50: 0.9 | P50: =39*(103.88/100) -> 40.5132 | Q50: =39*(103.88/100) -> 40.5132 | R50: =39*(103.88/100) -> 40.5132 | S50: =39*(103.88/100) -> 40.5132 | T50: =39*(103.88/100) -> 40.5132 | U50: =39*(103.88/100) -> 40.5132 | V50: =39*(103.88/100) -> 40.5132 | W50: =W40*1.2 -> 204 | X50: =X40*1.2 -> 204 | Y50: =Y40*1.2 -> 204 | Z50: =Z40*1.2 -> 204 | AA50: =AA40*1.2 -> 204 | AB50: =AB40*1.2 -> 204 | AC50: =AC40*1.2 -> 204 | AD50: 0.05 | AE50: 0 | AF50: 20 | AG50: 20 | AH50: 1 | AI50: Operation | AJ50: Flat low night | AX50: none | BL50: =IF(AG50=1,0,1) -> 1 | BN50: 0 | CC50: 4 | CD50: 7 | CE50: 7 | CF50: 7 | CG50: 7 | CH50: 7 | CJ50: =VLOOKUP($E50,[2]Activities!$A$9:$I$248,3,FALSE)/$AH50 -> 7 | CK50: =VLOOKUP($E50,[2]Activities!$A$9:$I$248,4,FALSE)/$AH50 -> 7 | CL50: =VLOOKUP($E50,[2]Activities!$A$9:$I$248,5,FALSE)/$AH50 -> 7 | CM50: =VLOOKUP($E50,[2]Activities!$A$9:$I$248,6,FALSE)/$AH50 -> 7 | CN50: =VLOOKUP($E50,[2]Activities!$A$9:$I$248,7,FALSE)/$AH50 -> 7 | CO50: =VLOOKUP($E50,[2]Activities!$A$9:$I$248,8,FALSE)/$AH50 -> 7 | CP50: =VLOOKUP($E50,[2]Activities!$A$9:$I$248,9,FALSE)/$AH50 -> 7
A51: IBM01_17 | B51: Final | C51: Industry | D51: Basic Metals | E51: Steel production - Basic Metals Industry | F51: DRI-fed EAF with syngas fuel and biomass reducing agent - Steel Production | G51: [Mton_Steel/y] | H51: =455*(103.88/100) -> 472.654 | I51: =455*(103.88/100) -> 472.654 | J51: =455*(103.88/100) -> 472.654 | K51: =455*(103.88/100) -> 472.654 | L51: =455*(103.88/100) -> 472.654 | M51: =455*(103.88/100) -> 472.654 | N51: =455*(103.88/100) -> 472.654 | O51: 0.9 | P51: =39*(103.88/100) -> 40.5132 | Q51: =39*(103.88/100) -> 40.5132 | R51: =39*(103.88/100) -> 40.5132 | S51: =39*(103.88/100) -> 40.5132 | T51: =39*(103.88/100) -> 40.5132 | U51: =39*(103.88/100) -> 40.5132 | V51: =39*(103.88/100) -> 40.5132 | W51: =W41*1.2 -> 204 | X51: =X41*1.2 -> 204 | Y51: =Y41*1.2 -> 204 | Z51: =Z41*1.2 -> 204 | AA51: =AA41*1.2 -> 204 | AB51: =AB41*1.2 -> 204 | AC51: =AC41*1.2 -> 204 | AD51: 0.05 | AE51: 0 | AF51: 20 | AG51: 20 | AH51: 1 | AI51: Operation | AJ51: Flat low night | AX51: none | BL51: =IF(AG51=1,0,1) -> 1 | BN51: 0 | CC51: 4 | CD51: 7 | CE51: 7 | CF51: 7 | CG51: 7 | CH51: 7 | CJ51: =VLOOKUP($E51,[2]Activities!$A$9:$I$248,3,FALSE)/$AH51 -> 7 | CK51: =VLOOKUP($E51,[2]Activities!$A$9:$I$248,4,FALSE)/$AH51 -> 7 | CL51: =VLOOKUP($E51,[2]Activities!$A$9:$I$248,5,FALSE)/$AH51 -> 7 | CM51: =VLOOKUP($E51,[2]Activities!$A$9:$I$248,6,FALSE)/$AH51 -> 7 | CN51: =VLOOKUP($E51,[2]Activities!$A$9:$I$248,7,FALSE)/$AH51 -> 7 | CO51: =VLOOKUP($E51,[2]Activities!$A$9:$I$248,8,FALSE)/$AH51 -> 7 | CP51: =VLOOKUP($E51,[2]Activities!$A$9:$I$248,9,FALSE)/$AH51 -> 7
A52: IBM02_01 | B52: Final | C52: Industry | D52: Basic Metals | E52: Aluminum production - Basic Metals Industry | F52: Hall Heroult + oil anodes + casting - Aluminum Production | G52: [Mton_Al/y] | H52: 450 | I52: 450 | J52: 450 | K52: 450 | L52: 450 | M52: 450 | N52: 450 | O52: 0.9 | P52: 135 | Q52: 135 | R52: 135 | S52: 135 | T52: 135 | U52: 135 | V52: 135 | W52: 0 | X52: 0 | Y52: 0 | Z52: 0 | AA52: 0 | AB52: 0 | AC52: 0 | AD52: 0.05 | AE52: 0 | AF52: 30 | AG52: 30 | AH52: 1 | AI52: Operation | AJ52: Flat low night | AX52: DR shifting | AY52: Electricity NL - HV | AZ52: 0.0085 | BB52: 3 days [r] | BC52: 0.01 | BD52: 0.2 | BK52: 0 | BL52: =IF(AG52=1,0,1) -> 1 | BN52: =CB52 -> 0.28 | BP52: =BN52 -> 0.28 | BU52: =IF(BL52=1,BN52,0) -> 0.28 | CB52: =CJ52 -> 0.28 | CC52: =CK52 -> 0.29 | CD52: =CL52 -> 0.3 | CE52: =CM52 -> 0.3 | CF52: =CN52 -> 0.31 | CG52: =CO52 -> 0.32 | CH52: =CP52 -> 0.33 | CI52: [52] | CJ52: =VLOOKUP($E52,[2]Activities!$A$9:$I$162,3,FALSE)/$AH52 -> 0.28 | CK52: =VLOOKUP($E52,[2]Activities!$A$9:$I$162,4,FALSE)/$AH52 -> 0.29 | CL52: =VLOOKUP($E52,[2]Activities!$A$9:$I$162,5,FALSE)/$AH52 -> 0.3 | CM52: =VLOOKUP($E52,[2]Activities!$A$9:$I$162,6,FALSE)/$AH52 -> 0.3 | CN52: =VLOOKUP($E52,[2]Activities!$A$9:$I$162,7,FALSE)/$AH52 -> 0.31 | CO52: =VLOOKUP($E52,[2]Activities!$A$9:$I$162,8,FALSE)/$AH52 -> 0.32 | CP52: =VLOOKUP($E52,[2]Activities!$A$9:$I$162,9,FALSE)/$AH52 -> 0.33
A53: IBM02_02 | B53: Final | C53: Industry | D53: Basic Metals | E53: Aluminum production - Basic Metals Industry | F53: Hall Heroult + biomass anodes + casting - Aluminum Production | G53: [Mton_Al/y] | H53: 455 | I53: 455 | J53: 455 | K53: 455 | L53: 455 | M53: 455 | N53: 455 | O53: 0.9 | P53: 138 | Q53: 138 | R53: 138 | S53: 138 | T53: 138 | U53: 138 | V53: 138 | W53: 0 | X53: 0 | Y53: 0 | Z53: 0 | AA53: 0 | AB53: 0 | AC53: 0 | AD53: 0.05 | AE53: 0 | AF53: 30 | AG53: 30 | AH53: 1 | AI53: Operation | AJ53: Flat low night | AX53: DR shifting | AY53: Electricity NL - HV | AZ53: 0.0085 | BB53: 3 days [r] | BC53: 0.01 | BD53: 0.2 | BK53: 0 | BL53: =IF(AG53=1,0,1) -> 1 | BN53: 0 | BU53: =IF(BL53=1,BN53,0) -> 0 | CC53: =CK53 -> 0.29 | CD53: =CL53 -> 0.3 | CE53: =CM53 -> 0.3 | CF53: =CN53 -> 0.31 | CG53: =CO53 -> 0.32 | CH53: =CP53 -> 0.33 | CI53: [52] | CJ53: =VLOOKUP($E53,[2]Activities!$A$9:$I$162,3,FALSE)/$AH53 -> 0.28 | CK53: =VLOOKUP($E53,[2]Activities!$A$9:$I$162,4,FALSE)/$AH53 -> 0.29 | CL53: =VLOOKUP($E53,[2]Activities!$A$9:$I$162,5,FALSE)/$AH53 -> 0.3 | CM53: =VLOOKUP($E53,[2]Activities!$A$9:$I$162,6,FALSE)/$AH53 -> 0.3 | CN53: =VLOOKUP($E53,[2]Activities!$A$9:$I$162,7,FALSE)/$AH53 -> 0.31 | CO53: =VLOOKUP($E53,[2]Activities!$A$9:$I$162,8,FALSE)/$AH53 -> 0.32 | CP53: =VLOOKUP($E53,[2]Activities!$A$9:$I$162,9,FALSE)/$AH53 -> 0.33
A54: IBM02_03 | B54: Final | C54: Industry | D54: Basic Metals | E54: Aluminum production - Basic Metals Industry | F54: Hall Heroult + inert anodes + casting - Aluminum Production | G54: [Mton_Al/y] | H54: 460 | I54: 460 | J54: 460 | K54: 460 | L54: 460 | M54: 460 | N54: 460 | O54: 0.9 | P54: 140 | Q54: 140 | R54: 140 | S54: 140 | T54: 140 | U54: 140 | V54: 140 | W54: 0 | X54: 0 | Y54: 0 | Z54: 0 | AA54: 0 | AB54: 0 | AC54: 0 | AD54: 0.05 | AE54: 0 | AF54: 30 | AG54: 30 | AH54: 1 | AI54: Operation | AJ54: Flat low night | AX54: DR shifting | AY54: Electricity NL - HV | AZ54: 0.0085 | BB54: 3 days [r] | BC54: 0.01 | BD54: 0.2 | BK54: 0 | BL54: =IF(AG54=1,0,1) -> 1 | BN54: 0 | BU54: =IF(BL54=1,BN54,0) -> 0 | CC54: =CK54 -> 0.29 | CD54: =CL54 -> 0.3 | CE54: =CM54 -> 0.3 | CF54: =CN54 -> 0.31 | CG54: =CO54 -> 0.32 | CH54: =CP54 -> 0.33 | CI54: [52] | CJ54: =VLOOKUP($E54,[2]Activities!$A$9:$I$162,3,FALSE)/$AH54 -> 0.28 | CK54: =VLOOKUP($E54,[2]Activities!$A$9:$I$162,4,FALSE)/$AH54 -> 0.29 | CL54: =VLOOKUP($E54,[2]Activities!$A$9:$I$162,5,FALSE)/$AH54 -> 0.3 | CM54: =VLOOKUP($E54,[2]Activities!$A$9:$I$162,6,FALSE)/$AH54 -> 0.3 | CN54: =VLOOKUP($E54,[2]Activities!$A$9:$I$162,7,FALSE)/$AH54 -> 0.31 | CO54: =VLOOKUP($E54,[2]Activities!$A$9:$I$162,8,FALSE)/$AH54 -> 0.32 | CP54: =VLOOKUP($E54,[2]Activities!$A$9:$I$162,9,FALSE)/$AH54 -> 0.33
A55: IBM02_04 | B55: Final | C55: Industry | D55: Basic Metals | E55: Aluminum production - Basic Metals Industry | F55: Hall Heroult + oil anodes w/wet cathodes + casting - Aluminum Production | G55: [Mton_Al/y] | H55: 490 | I55: 490 | J55: 490 | K55: 490 | L55: 490 | M55: 490 | N55: 490 | O55: 0.9 | P55: 145 | Q55: 145 | R55: 145 | S55: 145 | T55: 145 | U55: 145 | V55: 145 | W55: 0 | X55: 0 | Y55: 0 | Z55: 0 | AA55: 0 | AB55: 0 | AC55: 0 | AD55: 0.05 | AE55: 0 | AF55: 30 | AG55: 30 | AH55: 1 | AI55: Operation | AJ55: Flat low night | AX55: DR shifting | AY55: Electricity NL - HV | AZ55: 0.006 | BB55: 3 days [r] | BC55: 0.01 | BD55: 0.2 | BK55: 0 | BL55: =IF(AG55=1,0,1) -> 1 | BN55: 0 | BU55: =IF(BL55=1,BN55,0) -> 0 | CC55: =CK55 -> 0.29 | CD55: =CL55 -> 0.3 | CE55: =CM55 -> 0.3 | CF55: =CN55 -> 0.31 | CG55: =CO55 -> 0.32 | CH55: =CP55 -> 0.33 | CI55: [52] | CJ55: =VLOOKUP($E55,[2]Activities!$A$9:$I$162,3,FALSE)/$AH55 -> 0.28 | CK55: =VLOOKUP($E55,[2]Activities!$A$9:$I$162,4,FALSE)/$AH55 -> 0.29 | CL55: =VLOOKUP($E55,[2]Activities!$A$9:$I$162,5,FALSE)/$AH55 -> 0.3 | CM55: =VLOOKUP($E55,[2]Activities!$A$9:$I$162,6,FALSE)/$AH55 -> 0.3 | CN55: =VLOOKUP($E55,[2]Activities!$A$9:$I$162,7,FALSE)/$AH55 -> 0.31 | CO55: =VLOOKUP($E55,[2]Activities!$A$9:$I$162,8,FALSE)/$AH55 -> 0.32 | CP55: =VLOOKUP($E55,[2]Activities!$A$9:$I$162,9,FALSE)/$AH55 -> 0.33
A56: IBM02_05 | B56: Final | C56: Industry | D56: Basic Metals | E56: Aluminum production - Basic Metals Industry | F56: Hall Heroult + biomass anodes w/wet cathodes + casting - Aluminum Production | G56: [Mton_Al/y] | H56: 495 | I56: 495 | J56: 495 | K56: 495 | L56: 495 | M56: 495 | N56: 495 | O56: 0.9 | P56: 148 | Q56: 148 | R56: 148 | S56: 148 | T56: 148 | U56: 148 | V56: 148 | W56: 0 | X56: 0 | Y56: 0 | Z56: 0 | AA56: 0 | AB56: 0 | AC56: 0 | AD56: 0.05 | AE56: 0 | AF56: 30 | AG56: 30 | AH56: 1 | AI56: Operation | AJ56: Flat low night | AX56: DR shifting | AY56: Electricity NL - HV | AZ56: 0.006 | BB56: 3 days [r] | BC56: 0.01 | BD56: 0.2 | BK56: 0 | BL56: =IF(AG56=1,0,1) -> 1 | BN56: 0 | BU56: =IF(BL56=1,BN56,0) -> 0 | CC56: =CK56 -> 0.29 | CD56: =CL56 -> 0.3 | CE56: =CM56 -> 0.3 | CF56: =CN56 -> 0.31 | CG56: =CO56 -> 0.32 | CH56: =CP56 -> 0.33 | CI56: [52] | CJ56: =VLOOKUP($E56,[2]Activities!$A$9:$I$162,3,FALSE)/$AH56 -> 0.28 | CK56: =VLOOKUP($E56,[2]Activities!$A$9:$I$162,4,FALSE)/$AH56 -> 0.29 | CL56: =VLOOKUP($E56,[2]Activities!$A$9:$I$162,5,FALSE)/$AH56 -> 0.3 | CM56: =VLOOKUP($E56,[2]Activities!$A$9:$I$162,6,FALSE)/$AH56 -> 0.3 | CN56: =VLOOKUP($E56,[2]Activities!$A$9:$I$162,7,FALSE)/$AH56 -> 0.31 | CO56: =VLOOKUP($E56,[2]Activities!$A$9:$I$162,8,FALSE)/$AH56 -> 0.32 | CP56: =VLOOKUP($E56,[2]Activities!$A$9:$I$162,9,FALSE)/$AH56 -> 0.33
A57: IBM02_06 | B57: Final | C57: Industry | D57: Basic Metals | E57: Aluminum production - Basic Metals Industry | F57: Hall Heroult + inert anodes w/wet cathodes + casting - Aluminum Production | G57: [Mton_Al/y] | H57: 500 | I57: 500 | J57: 500 | K57: 500 | L57: 500 | M57: 500 | N57: 500 | O57: 0.9 | P57: 150 | Q57: 150 | R57: 150 | S57: 150 | T57: 150 | U57: 150 | V57: 150 | W57: 0 | X57: 0 | Y57: 0 | Z57: 0 | AA57: 0 | AB57: 0 | AC57: 0 | AD57: 0.05 | AE57: 0 | AF57: 30 | AG57: 30 | AH57: 1 | AI57: Operation | AJ57: Flat low night | AX57: DR shifting | AY57: Electricity NL - HV | AZ57: 0.006 | BB57: 3 days [r] | BC57: 0.01 | BD57: 0.2 | BK57: 0 | BL57: =IF(AG57=1,0,1) -> 1 | BN57: 0 | BU57: =IF(BL57=1,BN57,0) -> 0 | CC57: =CK57 -> 0.29 | CD57: =CL57 -> 0.3 | CE57: =CM57 -> 0.3 | CF57: =CN57 -> 0.31 | CG57: =CO57 -> 0.32 | CH57: =CP57 -> 0.33 | CI57: [52] | CJ57: =VLOOKUP($E57,[2]Activities!$A$9:$I$162,3,FALSE)/$AH57 -> 0.28 | CK57: =VLOOKUP($E57,[2]Activities!$A$9:$I$162,4,FALSE)/$AH57 -> 0.29 | CL57: =VLOOKUP($E57,[2]Activities!$A$9:$I$162,5,FALSE)/$AH57 -> 0.3 | CM57: =VLOOKUP($E57,[2]Activities!$A$9:$I$162,6,FALSE)/$AH57 -> 0.3 | CN57: =VLOOKUP($E57,[2]Activities!$A$9:$I$162,7,FALSE)/$AH57 -> 0.31 | CO57: =VLOOKUP($E57,[2]Activities!$A$9:$I$162,8,FALSE)/$AH57 -> 0.32 | CP57: =VLOOKUP($E57,[2]Activities!$A$9:$I$162,9,FALSE)/$AH57 -> 0.33
A58: IBM03_01 | B58: Final | C58: Industry | D58: Basic Metals | E58: Zinc production - Basic Metals Industry | F58: Reference technology - Zinc Production | G58: [Mton_Zn/y] | H58: 300 | I58: 300 | J58: 300 | K58: 300 | L58: 300 | M58: 300 | N58: 300 | O58: 0.9 | P58: 90 | Q58: 90 | R58: 90 | S58: 90 | T58: 90 | U58: 90 | V58: 90 | W58: 0 | X58: 0 | Y58: 0 | Z58: 0 | AA58: 0 | AB58: 0 | AC58: 0 | AD58: 0.05 | AE58: 0 | AF58: 30 | AG58: 30 | AH58: 1 | AI58: Operation | AJ58: Flat low night | AX58: DR shifting | AY58: Electricity NL - HV | AZ58: 0.004 | BB58: 3 days [r] | BC58: 0.01 | BD58: 0.2 | BK58: 0 | BL58: =IF(AG58=1,0,1) -> 1 | BN58: =CB58 -> 0.25 | BP58: =BN58 -> 0.25 | BU58: =IF(BL58=1,BN58,0) -> 0.25 | CB58: =CJ58 -> 0.25 | CC58: =CK58 -> 0.26 | CD58: =CL58 -> 0.27 | CE58: =CM58 -> 0.27 | CF58: =CN58 -> 0.28 | CG58: =CO58 -> 0.29 | CH58: =CP58 -> 0.3 | CI58: [53] | CJ58: =VLOOKUP($E58,[2]Activities!$A$9:$I$162,3,FALSE)/$AH58 -> 0.25 | CK58: =VLOOKUP($E58,[2]Activities!$A$9:$I$162,4,FALSE)/$AH58 -> 0.26 | CL58: =VLOOKUP($E58,[2]Activities!$A$9:$I$162,5,FALSE)/$AH58 -> 0.27 | CM58: =VLOOKUP($E58,[2]Activities!$A$9:$I$162,6,FALSE)/$AH58 -> 0.27 | CN58: =VLOOKUP($E58,[2]Activities!$A$9:$I$162,7,FALSE)/$AH58 -> 0.28 | CO58: =VLOOKUP($E58,[2]Activities!$A$9:$I$162,8,FALSE)/$AH58 -> 0.29 | CP58: =VLOOKUP($E58,[2]Activities!$A$9:$I$162,9,FALSE)/$AH58 -> 0.3
A59: IFE01_01 | B59: Final | C59: Industry | D59: Fertilizers | E59: Nitric Acid production - Fertilizers Industry | F59: Nitric Acid production from Ammonia -Fertilizers | G59: [Mton_AN] | H59: 130 | I59: 130 | J59: 130 | K59: 130 | L59: 130 | M59: 130 | N59: 130 | O59: 0.9 | P59: 3.9 | Q59: 3.9 | R59: 3.9 | S59: 3.9 | T59: 3.9 | U59: 3.9 | V59: 3.9 | W59: 0 | X59: 0 | Y59: 0 | Z59: 0 | AA59: 0 | AB59: 0 | AC59: 0 | AD59: 0.05 | AE59: 0 | AF59: 30 | AG59: 30 | AH59: 1 | AI59: Operation | AJ59: Flat low night 6 days | AX59: none | BK59: 0 | BL59: =IF(AG59=1,0,1) -> 1 | BN59: =CB59 -> 2.4 | BO59: =$BN$59/4 -> 0.6 | BP59: =$BN$59/4 -> 0.6 | BQ59: =$BN$59/4 -> 0.6 | BR59: =$BN$59/4 -> 0.6 | BU59: =IF(BL59=1,BN59,0) -> 2.4 | CB59: =CJ59 -> 2.4 | CC59: =CK59 -> 2.5 | CD59: =CL59 -> 2.6 | CE59: =CM59 -> 2.7 | CF59: =CN59 -> 2.8 | CG59: =CO59 -> 2.9 | CH59: =CP59 -> 3 | CI59: [54],[36] | CJ59: =VLOOKUP($E59,[2]Activities!$A$9:$I$162,3,FALSE)/$AH59 -> 2.4 | CK59: =VLOOKUP($E59,[2]Activities!$A$9:$I$162,4,FALSE)/$AH59 -> 2.5 | CL59: =VLOOKUP($E59,[2]Activities!$A$9:$I$162,5,FALSE)/$AH59 -> 2.6 | CM59: =VLOOKUP($E59,[2]Activities!$A$9:$I$162,6,FALSE)/$AH59 -> 2.7 | CN59: =VLOOKUP($E59,[2]Activities!$A$9:$I$162,7,FALSE)/$AH59 -> 2.8 | CO59: =VLOOKUP($E59,[2]Activities!$A$9:$I$162,8,FALSE)/$AH59 -> 2.9 | CP59: =VLOOKUP($E59,[2]Activities!$A$9:$I$162,9,FALSE)/$AH59 -> 3
A60: IFE02_01 | B60: Final | C60: Industry | D60: Fertilizers | E60: Urea production - Fertilizers Industry | F60: Urea production from Ammonia - Fertilizers | G60: [Mton_Urea] | H60: 185 | I60: 185 | J60: 185 | K60: 185 | L60: 185 | M60: 185 | N60: 185 | O60: 0.9 | P60: 6 | Q60: 6 | R60: 6 | S60: 6 | T60: 6 | U60: 6 | V60: 6 | W60: 1.5 | X60: 1.5 | Y60: 1.5 | Z60: 1.5 | AA60: 1.5 | AB60: 1.5 | AC60: 1.5 | AD60: 0.05 | AE60: 0 | AF60: 30 | AG60: 30 | AH60: 1 | AI60: Operation | AJ60: Flat low night 6 days | AX60: none | BK60: 0 | BL60: =IF(AG60=1,0,1) -> 1 | BN60: =CB60 -> 1.8 | BO60: =$BN$60/4 -> 0.45 | BP60: =$BN$60/4 -> 0.45 | BQ60: =$BN$60/4 -> 0.45 | BR60: =$BN$60/4 -> 0.45 | BU60: =IF(BL60=1,BN60,0) -> 1.8 | CB60: =CJ60 -> 1.8 | CC60: =CK60 -> 1.87 | CD60: =CL60 -> 1.94 | CE60: =CM60 -> 2.01 | CF60: =CN60 -> 2.08 | CG60: =CO60 -> 2.15 | CH60: =CP60 -> 2.22 | CI60: [54],[36] | CJ60: =VLOOKUP($E60,[2]Activities!$A$9:$I$162,3,FALSE)/$AH60 -> 1.8 | CK60: =VLOOKUP($E60,[2]Activities!$A$9:$I$162,4,FALSE)/$AH60 -> 1.87 | CL60: =VLOOKUP($E60,[2]Activities!$A$9:$I$162,5,FALSE)/$AH60 -> 1.94 | CM60: =VLOOKUP($E60,[2]Activities!$A$9:$I$162,6,FALSE)/$AH60 -> 2.01 | CN60: =VLOOKUP($E60,[2]Activities!$A$9:$I$162,7,FALSE)/$AH60 -> 2.08 | CO60: =VLOOKUP($E60,[2]Activities!$A$9:$I$162,8,FALSE)/$AH60 -> 2.15 | CP60: =VLOOKUP($E60,[2]Activities!$A$9:$I$162,9,FALSE)/$AH60 -> 2.22
A61: IFE02_02 | B61: Final | C61: Industry | D61: Fertilizers | E61: Urea production - Fertilizers Industry | F61: Urea production from Ammonia and CCUS - Fertilizers | G61: [Mton_Urea] | H61: 185 | I61: 185 | J61: 185 | K61: 185 | L61: 185 | M61: 185 | N61: 185 | O61: 0.9 | P61: 6 | Q61: 6 | R61: 6 | S61: 6 | T61: 6 | U61: 6 | V61: 6 | W61: 0 | X61: 0 | Y61: 0 | Z61: 0 | AA61: 0 | AB61: 0 | AC61: 0 | AD61: 0.05 | AE61: 0 | AF61: 30 | AG61: 30 | AH61: 1 | AI61: Operation | AJ61: Flat low night 6 days | AX61: none | BK61: 0 | BL61: =IF(AG61=1,0,1) -> 1 | BN61: 0 | BU61: =IF(BL61=1,BN61,0) -> 0 | CD61: =CL61 -> 1.94 | CE61: =CM61 -> 2.01 | CF61: =CN61 -> 2.08 | CG61: =CO61 -> 2.15 | CH61: =CP61 -> 2.22 | CI61: [54],[36] | CJ61: =VLOOKUP($E61,[2]Activities!$A$9:$I$162,3,FALSE)/$AH61 -> 1.8 | CK61: =VLOOKUP($E61,[2]Activities!$A$9:$I$162,4,FALSE)/$AH61 -> 1.87 | CL61: =VLOOKUP($E61,[2]Activities!$A$9:$I$162,5,FALSE)/$AH61 -> 1.94 | CM61: =VLOOKUP($E61,[2]Activities!$A$9:$I$162,6,FALSE)/$AH61 -> 2.01 | CN61: =VLOOKUP($E61,[2]Activities!$A$9:$I$162,7,FALSE)/$AH61 -> 2.08 | CO61: =VLOOKUP($E61,[2]Activities!$A$9:$I$162,8,FALSE)/$AH61 -> 2.15 | CP61: =VLOOKUP($E61,[2]Activities!$A$9:$I$162,9,FALSE)/$AH61 -> 2.22
A62: IFE03_01 | B62: Final | C62: Industry | D62: Fertilizers | E62: Other Ammonia based fertilizers - Fertilizers Industry | F62: Ammonia demand for other fertilizers - Fertilizers | G62: [Mton_NH3] | H62: 0 | I62: 0 | J62: 0 | K62: 0 | L62: 0 | M62: 0 | N62: 0 | O62: 0.9 | P62: 0 | Q62: 0 | R62: 0 | S62: 0 | T62: 0 | U62: 0 | V62: 0 | W62: 0 | X62: 0 | Y62: 0 | Z62: 0 | AA62: 0 | AB62: 0 | AC62: 0 | AD62: 0.05 | AE62: 0 | AF62: 1 | AG62: 1 | AH62: 1 | AI62: Operation | AJ62: Flat low night 6 days | AX62: none | BK62: 0 | BL62: =IF(AG62=1,0,1) -> 0 | BU62: =IF(BL62=1,BN62,0) -> 0 | CB62: =CJ62 -> 1.2 | CC62: =CK62 -> 1.25 | CD62: =CL62 -> 1.3 | CE62: =CM62 -> 1.35 | CF62: =CN62 -> 1.4 | CG62: =CO62 -> 1.45 | CH62: =CP62 -> 1.5 | CI62: [54],[36] | CJ62: =VLOOKUP($E62,[2]Activities!$A$9:$I$162,3,FALSE)/$AH62 -> 1.2 | CK62: =VLOOKUP($E62,[2]Activities!$A$9:$I$162,4,FALSE)/$AH62 -> 1.25 | CL62: =VLOOKUP($E62,[2]Activities!$A$9:$I$162,5,FALSE)/$AH62 -> 1.3 | CM62: =VLOOKUP($E62,[2]Activities!$A$9:$I$162,6,FALSE)/$AH62 -> 1.35 | CN62: =VLOOKUP($E62,[2]Activities!$A$9:$I$162,7,FALSE)/$AH62 -> 1.4 | CO62: =VLOOKUP($E62,[2]Activities!$A$9:$I$162,8,FALSE)/$AH62 -> 1.45 | CP62: =VLOOKUP($E62,[2]Activities!$A$9:$I$162,9,FALSE)/$AH62 -> 1.5
A63: ICH01_01 | B63: Conversion | C63: Industry | D63: Chemicals | E63: Ethylene intermediate | F63: Existing naphtha steam cracker - Petrochemical industry | G63: [Mton_Ey/y] | H63: 725 | I63: 725 | J63: 725 | K63: 725 | L63: 725 | M63: 725 | N63: 725 | O63: 0.9 | P63: 36 | Q63: 36 | R63: 36 | S63: 36 | T63: 36 | U63: 36 | V63: 36 | W63: 0 | X63: 0 | Y63: 0 | Z63: 0 | AA63: 0 | AB63: 0 | AC63: 0 | AD63: 0.05 | AE63: 0 | AF63: 30 | AG63: 30 | AH63: 1 | AI63: Operation | AJ63: Flat low spread | AX63: none | BK63: 0 | BL63: =IF(AG63=1,0,1) -> 1 | BN63: 4 | BQ63: 1.3 | BR63: 1.3 | BS63: 1.28 | BU63: =IF(BL63=1,BN63,0) -> 4 | CB63: 5 | CC63: 4 | CD63: 4 | CE63: 3.8 | CF63: 3.3 | CG63: 2.5 | CH63: 2 | CI63: [1],[12],[55],[36] | CJ63: =VLOOKUP($E63,[2]Activities!$A$9:$I$162,3,FALSE)/$AH63 -> 0 | CK63: =VLOOKUP($E63,[2]Activities!$A$9:$I$162,4,FALSE)/$AH63 -> 0 | CL63: =VLOOKUP($E63,[2]Activities!$A$9:$I$162,5,FALSE)/$AH63 -> 0 | CM63: =VLOOKUP($E63,[2]Activities!$A$9:$I$162,6,FALSE)/$AH63 -> 0 | CN63: =VLOOKUP($E63,[2]Activities!$A$9:$I$162,7,FALSE)/$AH63 -> 0 | CO63: =VLOOKUP($E63,[2]Activities!$A$9:$I$162,8,FALSE)/$AH63 -> 0 | CP63: =VLOOKUP($E63,[2]Activities!$A$9:$I$162,9,FALSE)/$AH63 -> 0 | CT63: 1 | CU63: 1 | CV63: 1 | CW63: 1
A64: ICH01_02 | B64: Conversion | C64: Industry | D64: Chemicals | E64: Ethylene intermediate | F64: Existing naphtha steam cracker wCCUS (MEA postcombustion) - Petrochemical industry | G64: [Mton_Ey/y] | H64: 1100 | I64: 1100 | J64: 1100 | K64: 1100 | L64: 1100 | M64: 1100 | N64: 1100 | O64: 0.9 | P64: 48 | Q64: 48 | R64: 48 | S64: 48 | T64: 48 | U64: 48 | V64: 48 | W64: 0 | X64: 0 | Y64: 0 | Z64: 0 | AA64: 0 | AB64: 0 | AC64: 0 | AD64: 0.05 | AE64: 0 | AF64: 30 | AG64: 30 | AH64: 1 | AI64: Operation | AJ64: Flat low spread | AX64: none | BK64: 0 | BL64: =IF(AG64=1,0,1) -> 1 | BN64: 0 | BU64: =IF(BL64=1,BN64,0) -> 0 | CC64: 1 | CD64: 2.5 | CE64: =CE63 -> 3.8 | CF64: =CF63 -> 3.3 | CG64: =CG63 -> 2.5 | CH64: =CH63 -> 2 | CI64: [1],[12],[55] | CJ64: =VLOOKUP($E64,[2]Activities!$A$9:$I$162,3,FALSE)/$AH64 -> 0 | CK64: =VLOOKUP($E64,[2]Activities!$A$9:$I$162,4,FALSE)/$AH64 -> 0 | CL64: =VLOOKUP($E64,[2]Activities!$A$9:$I$162,5,FALSE)/$AH64 -> 0 | CM64: =VLOOKUP($E64,[2]Activities!$A$9:$I$162,6,FALSE)/$AH64 -> 0 | CN64: =VLOOKUP($E64,[2]Activities!$A$9:$I$162,7,FALSE)/$AH64 -> 0 | CO64: =VLOOKUP($E64,[2]Activities!$A$9:$I$162,8,FALSE)/$AH64 -> 0 | CP64: =VLOOKUP($E64,[2]Activities!$A$9:$I$162,9,FALSE)/$AH64 -> 0 | CV64: 1 | CW64: 1
A65: ICH01_03 | B65: Conversion | C65: Industry | D65: Chemicals | E65: Ethylene intermediate | F65: Existing bio-naphtha steam cracker wCCUS (MEA postcombustion) - Petrochemical industry | G65: [Mton_Ey/y] | H65: 1100 | I65: 1100 | J65: 1100 | K65: 1100 | L65: 1100 | M65: 1100 | N65: 1100 | O65: 0.9 | P65: 48 | Q65: 48 | R65: 48 | S65: 48 | T65: 48 | U65: 48 | V65: 48 | W65: 0 | X65: 0 | Y65: 0 | Z65: 0 | AA65: 0 | AB65: 0 | AC65: 0 | AD65: 0.05 | AE65: 0 | AF65: 30 | AG65: 30 | AH65: 1 | AI65: Operation | AJ65: Flat low spread | AX65: none | BK65: 0 | BL65: =IF(AG65=1,0,1) -> 1 | BN65: 0 | BU65: =IF(BL65=1,BN65,0) -> 0 | CC65: 1 | CD65: 2.5 | CE65: =CE64 -> 3.8 | CF65: =CF64 -> 3.3 | CG65: =CG64 -> 2.5 | CH65: =CH64 -> 2 | CI65: [1],[12],[55] | CJ65: =VLOOKUP($E65,[2]Activities!$A$9:$I$162,3,FALSE)/$AH65 -> 0 | CK65: =VLOOKUP($E65,[2]Activities!$A$9:$I$162,4,FALSE)/$AH65 -> 0 | CL65: =VLOOKUP($E65,[2]Activities!$A$9:$I$162,5,FALSE)/$AH65 -> 0 | CM65: =VLOOKUP($E65,[2]Activities!$A$9:$I$162,6,FALSE)/$AH65 -> 0 | CN65: =VLOOKUP($E65,[2]Activities!$A$9:$I$162,7,FALSE)/$AH65 -> 0 | CO65: =VLOOKUP($E65,[2]Activities!$A$9:$I$162,8,FALSE)/$AH65 -> 0 | CP65: =VLOOKUP($E65,[2]Activities!$A$9:$I$162,9,FALSE)/$AH65 -> 0
A66: ICH01_04 | B66: Conversion | C66: Industry | D66: Chemicals | E66: Ethylene intermediate | F66: Existing syn-naphtha steam cracker wCCUS (MEA postcombustion) - Petrochemical industry | G66: [Mton_Ey/y] | H66: 1100 | I66: 1100 | J66: 1100 | K66: 1100 | L66: 1100 | M66: 1100 | N66: 1100 | O66: 0.9 | P66: 48 | Q66: 48 | R66: 48 | S66: 48 | T66: 48 | U66: 48 | V66: 48 | W66: 0 | X66: 0 | Y66: 0 | Z66: 0 | AA66: 0 | AB66: 0 | AC66: 0 | AD66: 0.05 | AE66: 0 | AF66: 30 | AG66: 30 | AH66: 1 | AI66: Operation | AJ66: Flat low spread | AX66: none | BK66: 0 | BL66: =IF(AG66=1,0,1) -> 1 | BN66: 0 | BU66: =IF(BL66=1,BN66,0) -> 0 | CC66: 1 | CD66: 2.5 | CE66: =CE65 -> 3.8 | CF66: =CF65 -> 3.3 | CG66: =CG65 -> 2.5 | CH66: =CH65 -> 2 | CI66: [1],[12],[55] | CJ66: =VLOOKUP($E66,[2]Activities!$A$9:$I$162,3,FALSE)/$AH66 -> 0 | CK66: =VLOOKUP($E66,[2]Activities!$A$9:$I$162,4,FALSE)/$AH66 -> 0 | CL66: =VLOOKUP($E66,[2]Activities!$A$9:$I$162,5,FALSE)/$AH66 -> 0 | CM66: =VLOOKUP($E66,[2]Activities!$A$9:$I$162,6,FALSE)/$AH66 -> 0 | CN66: =VLOOKUP($E66,[2]Activities!$A$9:$I$162,7,FALSE)/$AH66 -> 0 | CO66: =VLOOKUP($E66,[2]Activities!$A$9:$I$162,8,FALSE)/$AH66 -> 0 | CP66: =VLOOKUP($E66,[2]Activities!$A$9:$I$162,9,FALSE)/$AH66 -> 0
A67: ICH01_05 | B67: Conversion | C67: Industry | D67: Chemicals | E67: Ethylene intermediate | F67: Electrified naphtha steam cracker - Petrochemical industry | G67: [Mton_Ey/y] | H67: 970 | I67: 970 | J67: 970 | K67: 970 | L67: 970 | M67: 970 | N67: 970 | O67: 0.9 | P67: 51 | Q67: 51 | R67: 51 | S67: 51 | T67: 51 | U67: 51 | V67: 51 | W67: 0 | X67: 0 | Y67: 0 | Z67: 0 | AA67: 0 | AB67: 0 | AC67: 0 | AD67: 0.05 | AE67: 0 | AF67: 25 | AG67: 25 | AH67: 1 | AI67: Shedding | AJ67: Flat | AR67: 0.0025 | AS67: 0.9 | AT67: 1 hour [h] | AX67: none | BK67: 0 | BL67: 1 | BN67: 0 | BU67: 0 | CB67: 0 | CC67: 1 | CD67: 2.5 | CE67: =CE66 -> 3.8 | CF67: =CF66 -> 3.3 | CG67: =CG66 -> 2.5 | CH67: =CH66 -> 2 | CI67: [12],[55] | CJ67: 5 | CK67: 5 | CL67: 5 | CM67: 5 | CN67: 5 | CO67: 5 | CP67: 5
A68: ICH01_06 | B68: Conversion | C68: Industry | D68: Chemicals | E68: Ethylene intermediate | F68: Electrified bio-naphtha steam cracker - Petrochemical industry | G68: [Mton_Ey/y] | H68: 1200 | I68: 1200 | J68: 1200 | K68: 1200 | L68: 1200 | M68: 1200 | N68: 1200 | O68: 0.9 | P68: 51 | Q68: 51 | R68: 51 | S68: 51 | T68: 51 | U68: 51 | V68: 51 | W68: 0 | X68: 0 | Y68: 0 | Z68: 0 | AA68: 0 | AB68: 0 | AC68: 0 | AD68: 0.05 | AE68: 0 | AF68: 30 | AG68: 30 | AH68: 1 | AI68: Shedding | AJ68: Flat | AR68: 0.0025 | AS68: 0.9 | AT68: 1 hour [h] | AX68: none | BK68: 0 | BL68: =IF(AG68=1,0,1) -> 1 | BN68: 0 | BU68: =IF(BL68=1,BN68,0) -> 0 | CB68: 0 | CC68: 1 | CD68: 2.5 | CE68: =CE67 -> 3.8 | CF68: =CF67 -> 3.3 | CG68: =CG67 -> 2.5 | CH68: =CH67 -> 2 | CI68: [12],[55] | CJ68: =VLOOKUP($E68,[2]Activities!$A$9:$I$162,3,FALSE)/$AH68 -> 0 | CK68: =VLOOKUP($E68,[2]Activities!$A$9:$I$162,4,FALSE)/$AH68 -> 0 | CL68: =VLOOKUP($E68,[2]Activities!$A$9:$I$162,5,FALSE)/$AH68 -> 0 | CM68: =VLOOKUP($E68,[2]Activities!$A$9:$I$162,6,FALSE)/$AH68 -> 0 | CN68: =VLOOKUP($E68,[2]Activities!$A$9:$I$162,7,FALSE)/$AH68 -> 0 | CO68: =VLOOKUP($E68,[2]Activities!$A$9:$I$162,8,FALSE)/$AH68 -> 0 | CP68: =VLOOKUP($E68,[2]Activities!$A$9:$I$162,9,FALSE)/$AH68 -> 0
A69: ICH01_07 | B69: Conversion | C69: Industry | D69: Chemicals | E69: Ethylene intermediate | F69: Electrified syn-naphtha steam cracker - Petrochemical industry | G69: [Mton_Ey/y] | H69: 1200 | I69: 1200 | J69: 1200 | K69: 1200 | L69: 1200 | M69: 1200 | N69: 1200 | O69: 0.9 | P69: 51 | Q69: 51 | R69: 51 | S69: 51 | T69: 51 | U69: 51 | V69: 51 | W69: 0 | X69: 0 | Y69: 0 | Z69: 0 | AA69: 0 | AB69: 0 | AC69: 0 | AD69: 0.05 | AE69: 0 | AF69: 30 | AG69: 30 | AH69: 1 | AI69: Shedding | AJ69: Flat | AR69: 0.0025 | AS69: 0.9 | AT69: 1 hour [h] | AX69: none | BK69: 0 | BL69: =IF(AG69=1,0,1) -> 1 | BN69: 0 | BU69: =IF(BL69=1,BN69,0) -> 0 | CC69: 1 | CD69: 2.5 | CE69: =CE68 -> 3.8 | CF69: =CF68 -> 3.3 | CG69: =CG68 -> 2.5 | CH69: =CH68 -> 2 | CI69: [12],[55] | CJ69: =VLOOKUP($E69,[2]Activities!$A$9:$I$162,3,FALSE)/$AH69 -> 0 | CK69: =VLOOKUP($E69,[2]Activities!$A$9:$I$162,4,FALSE)/$AH69 -> 0 | CL69: =VLOOKUP($E69,[2]Activities!$A$9:$I$162,5,FALSE)/$AH69 -> 0 | CM69: =VLOOKUP($E69,[2]Activities!$A$9:$I$162,6,FALSE)/$AH69 -> 0 | CN69: =VLOOKUP($E69,[2]Activities!$A$9:$I$162,7,FALSE)/$AH69 -> 0 | CO69: =VLOOKUP($E69,[2]Activities!$A$9:$I$162,8,FALSE)/$AH69 -> 0 | CP69: =VLOOKUP($E69,[2]Activities!$A$9:$I$162,9,FALSE)/$AH69 -> 0
A70: ICH01_08 | B70: Conversion | C70: Industry | D70: Chemicals | E70: Ethylene intermediate | F70: Hydrogen fueled naphtha steam cracker - Petrochemical industry | G70: [Mton_Ey/y] | H70: 1060 | I70: 1060 | J70: 1060 | K70: 1060 | L70: 1060 | M70: 1060 | N70: 1060 | O70: 0.9 | P70: 38.5 | Q70: 38.5 | R70: 38.5 | S70: 38.5 | T70: 38.5 | U70: 38.5 | V70: 38.5 | W70: 0 | X70: 0 | Y70: 0 | Z70: 0 | AA70: 0 | AB70: 0 | AC70: 0 | AD70: 0.05 | AE70: 0 | AF70: 25 | AG70: 25 | AH70: 1 | AI70: Operation | AJ70: Flat low spread | AX70: none | BK70: 0 | BL70: 1 | BN70: 0 | BU70: 0 | CB70: 0 | CC70: 1 | CD70: 2.5 | CE70: =CE69 -> 3.8 | CF70: =CF69 -> 3.3 | CG70: =CG69 -> 2.5 | CH70: =CH69 -> 2 | CI70: [12],[55] | CJ70: 5 | CK70: 5 | CL70: 5 | CM70: 5 | CN70: 5 | CO70: 5 | CP70: 5
A71: ICH01_09 | B71: Conversion | C71: Industry | D71: Chemicals | E71: Ethylene intermediate | F71: Hydrogen fueled bio-naphtha steam cracker - Petrochemical industry | G71: [Mton_Ey/y] | H71: 1300 | I71: 1300 | J71: 1300 | K71: 1300 | L71: 1300 | M71: 1300 | N71: 1300 | O71: 0.9 | P71: 38.5 | Q71: 38.5 | R71: 38.5 | S71: 38.5 | T71: 38.5 | U71: 38.5 | V71: 38.5 | W71: 0 | X71: 0 | Y71: 0 | Z71: 0 | AA71: 0 | AB71: 0 | AC71: 0 | AD71: 0.05 | AE71: 0 | AF71: 30 | AG71: 30 | AH71: 1 | AI71: Operation | AJ71: Flat low spread | AX71: none | BK71: 0 | BL71: =IF(AG71=1,0,1) -> 1 | BN71: 0 | BU71: =IF(BL71=1,BN71,0) -> 0 | CC71: 1 | CD71: 2.5 | CE71: =CE70 -> 3.8 | CF71: =CF70 -> 3.3 | CG71: =CG70 -> 2.5 | CH71: =CH70 -> 2 | CI71: [12],[55] | CJ71: =VLOOKUP($E71,[2]Activities!$A$9:$I$162,3,FALSE)/$AH71 -> 0 | CK71: =VLOOKUP($E71,[2]Activities!$A$9:$I$162,4,FALSE)/$AH71 -> 0 | CL71: =VLOOKUP($E71,[2]Activities!$A$9:$I$162,5,FALSE)/$AH71 -> 0 | CM71: =VLOOKUP($E71,[2]Activities!$A$9:$I$162,6,FALSE)/$AH71 -> 0 | CN71: =VLOOKUP($E71,[2]Activities!$A$9:$I$162,7,FALSE)/$AH71 -> 0 | CO71: =VLOOKUP($E71,[2]Activities!$A$9:$I$162,8,FALSE)/$AH71 -> 0 | CP71: =VLOOKUP($E71,[2]Activities!$A$9:$I$162,9,FALSE)/$AH71 -> 0
A72: ICH01_10 | B72: Conversion | C72: Industry | D72: Chemicals | E72: Ethylene intermediate | F72: Hydrogen fueled syn-naphtha steam cracker - Petrochemical industry | G72: [Mton_Ey/y] | H72: 1300 | I72: 1300 | J72: 1300 | K72: 1300 | L72: 1300 | M72: 1300 | N72: 1300 | O72: 0.9 | P72: 38.5 | Q72: 38.5 | R72: 38.5 | S72: 38.5 | T72: 38.5 | U72: 38.5 | V72: 38.5 | W72: 0 | X72: 0 | Y72: 0 | Z72: 0 | AA72: 0 | AB72: 0 | AC72: 0 | AD72: 0.05 | AE72: 0 | AF72: 30 | AG72: 30 | AH72: 1 | AI72: Operation | AJ72: Flat low spread | AX72: none | BK72: 0 | BL72: =IF(AG72=1,0,1) -> 1 | BN72: 0 | BU72: =IF(BL72=1,BN72,0) -> 0 | CC72: 1 | CD72: 2.5 | CE72: =CE71 -> 3.8 | CF72: =CF71 -> 3.3 | CG72: =CG71 -> 2.5 | CH72: =CH71 -> 2 | CI72: [12],[55] | CJ72: =VLOOKUP($E72,[2]Activities!$A$9:$I$162,3,FALSE)/$AH72 -> 0 | CK72: =VLOOKUP($E72,[2]Activities!$A$9:$I$162,4,FALSE)/$AH72 -> 0 | CL72: =VLOOKUP($E72,[2]Activities!$A$9:$I$162,5,FALSE)/$AH72 -> 0 | CM72: =VLOOKUP($E72,[2]Activities!$A$9:$I$162,6,FALSE)/$AH72 -> 0 | CN72: =VLOOKUP($E72,[2]Activities!$A$9:$I$162,7,FALSE)/$AH72 -> 0 | CO72: =VLOOKUP($E72,[2]Activities!$A$9:$I$162,8,FALSE)/$AH72 -> 0 | CP72: =VLOOKUP($E72,[2]Activities!$A$9:$I$162,9,FALSE)/$AH72 -> 0
A73: ICH01_11 | B73: Conversion | C73: Industry | D73: Chemicals | E73: Ethylene intermediate | F73: Ethylene from bioethanol dehydration - Petrochemical industry | G73: [Mton_Ey/y] | H73: 1200 | I73: 1050 | J73: 850 | K73: 800 | L73: 750 | M73: 700 | N73: 650 | O73: 0.9 | P73: 28 | Q73: 28 | R73: 28 | S73: 28 | T73: 28 | U73: 28 | V73: 28 | W73: 0 | X73: 0 | Y73: 0 | Z73: 0 | AA73: 0 | AB73: 0 | AC73: 0 | AD73: 0.05 | AE73: 0 | AF73: 30 | AG73: 30 | AH73: 1 | AI73: Operation | AJ73: Flat low spread | AX73: none | BK73: 0 | BL73: =IF(AG73=1,0,1) -> 1 | BN73: 0 | BU73: =IF(BL73=1,BN73,0) -> 0 | CC73: 1 | CD73: 2.5 | CE73: =CE72 -> 3.8 | CF73: =CF72 -> 3.3 | CG73: =CG72 -> 2.5 | CH73: =CH72 -> 2 | CI73: [55],[67] | CJ73: =VLOOKUP($E73,[2]Activities!$A$9:$I$162,3,FALSE)/$AH73 -> 0 | CK73: =VLOOKUP($E73,[2]Activities!$A$9:$I$162,4,FALSE)/$AH73 -> 0 | CL73: =VLOOKUP($E73,[2]Activities!$A$9:$I$162,5,FALSE)/$AH73 -> 0 | CM73: =VLOOKUP($E73,[2]Activities!$A$9:$I$162,6,FALSE)/$AH73 -> 0 | CN73: =VLOOKUP($E73,[2]Activities!$A$9:$I$162,7,FALSE)/$AH73 -> 0 | CO73: =VLOOKUP($E73,[2]Activities!$A$9:$I$162,8,FALSE)/$AH73 -> 0 | CP73: =VLOOKUP($E73,[2]Activities!$A$9:$I$162,9,FALSE)/$AH73 -> 0
A74: ICH01_12 | B74: Conversion | C74: Industry | D74: Chemicals | E74: Propylene intermediate | F74: Methanol to olefins - Petrochemical industry | G74: [Mton_Ey/y] | H74: 2200 | I74: 2100 | J74: 1900 | K74: 1600 | L74: 1500 | M74: 1400 | N74: 1300 | O74: 0.9 | P74: 90 | Q74: 85 | R74: 80 | S74: 75 | T74: 70 | U74: 65 | V74: 60 | W74: 0 | X74: 0 | Y74: 0 | Z74: 0 | AA74: 0 | AB74: 0 | AC74: 0 | AD74: 0.05 | AE74: 0 | AF74: 30 | AG74: 30 | AH74: 1 | AI74: Operation | AJ74: Flat low spread | AX74: none | BK74: 0 | BL74: =IF(AG74=1,0,1) -> 1 | BN74: 0 | BU74: =IF(BL74=1,BN74,0) -> 0 | CC74: 1 | CD74: 2.5 | CE74: =CE73 -> 3.8 | CF74: =CF73 -> 3.3 | CG74: =CG73 -> 2.5 | CH74: =CH73 -> 2 | CI74: [55],[64] | CJ74: =VLOOKUP($E74,[2]Activities!$A$9:$I$162,3,FALSE)/$AH74 -> 0 | CK74: =VLOOKUP($E74,[2]Activities!$A$9:$I$162,4,FALSE)/$AH74 -> 0 | CL74: =VLOOKUP($E74,[2]Activities!$A$9:$I$162,5,FALSE)/$AH74 -> 0 | CM74: =VLOOKUP($E74,[2]Activities!$A$9:$I$162,6,FALSE)/$AH74 -> 0 | CN74: =VLOOKUP($E74,[2]Activities!$A$9:$I$162,7,FALSE)/$AH74 -> 0 | CO74: =VLOOKUP($E74,[2]Activities!$A$9:$I$162,8,FALSE)/$AH74 -> 0 | CP74: =VLOOKUP($E74,[2]Activities!$A$9:$I$162,9,FALSE)/$AH74 -> 0
A75: ICH01_13 | B75: Conversion | C75: Industry | D75: Chemicals | E75: Ethylene intermediate | F75: Ethylene imports - Petrochemical industry | G75: [Mton_Ey/y] | H75: 0 | I75: 0 | J75: 0 | K75: 0 | L75: 0 | M75: 0 | N75: 0 | O75: 0.9 | P75: 0 | Q75: 0 | R75: 0 | S75: 0 | T75: 0 | U75: 0 | V75: 0 | W75: 2000 | X75: 2500 | Y75: 3000 | Z75: 3500 | AA75: 4000 | AB75: 4500 | AC75: 5000 | AD75: 0.05 | AE75: 0 | AF75: 1 | AG75: 1 | AH75: 1 | AI75: Operation | AJ75: Flat | AX75: none | BK75: 0 | BL75: =IF(AG75=1,0,1) -> 0 | BU75: =IF(BL75=1,BN75,0) -> 0 | CB75: =CJ75 -> 0 | CC75: 1 | CD75: 2.5 | CE75: =CE74 -> 3.8 | CF75: =CF74 -> 3.3 | CG75: =CG74 -> 2.5 | CH75: =CH74 -> 2 | CI75: [55] | CJ75: =VLOOKUP($E75,[2]Activities!$A$9:$I$162,3,FALSE)/$AH75 -> 0 | CK75: =VLOOKUP($E75,[2]Activities!$A$9:$I$162,4,FALSE)/$AH75 -> 0 | CL75: =VLOOKUP($E75,[2]Activities!$A$9:$I$162,5,FALSE)/$AH75 -> 0 | CM75: =VLOOKUP($E75,[2]Activities!$A$9:$I$162,6,FALSE)/$AH75 -> 0 | CN75: =VLOOKUP($E75,[2]Activities!$A$9:$I$162,7,FALSE)/$AH75 -> 0 | CO75: =VLOOKUP($E75,[2]Activities!$A$9:$I$162,8,FALSE)/$AH75 -> 0 | CP75: =VLOOKUP($E75,[2]Activities!$A$9:$I$162,9,FALSE)/$AH75 -> 0
A76: ICH01_14 | B76: Conversion | C76: Industry | D76: Chemicals | E76: Propylene intermediate | F76: Propylene from PDH alkenation of LPG - Petrochemicals | G76: [Mton_Py/y] | H76: 1100 | I76: 1100 | J76: 1100 | K76: 1100 | L76: 1100 | M76: 1100 | N76: 1100 | O76: 0.9 | P76: 52 | Q76: 52 | R76: 52 | S76: 52 | T76: 52 | U76: 52 | V76: 52 | W76: 0 | X76: 0 | Y76: 0 | Z76: 0 | AA76: 0 | AB76: 0 | AC76: 0 | AD76: 0.05 | AF76: 30 | AG76: 30 | AH76: 1 | AI76: Operation | AJ76: Flat low spread | AX76: none | BK76: 0 | BL76: =IF(AG76=1,0,1) -> 1 | BN76: 0.12 | BP76: 0.12 | BU76: =IF(BL76=1,BN76,0) -> 0.12 | CB76: 1 | CC76: 0.12 | CD76: 0.12 | CE76: 0.12 | CF76: 0.12 | CG76: 0.12 | CH76: 0.12 | CI76: [55] | CJ76: =VLOOKUP($E76,[2]Activities!$A$9:$I$162,3,FALSE)/$AH76 -> 0 | CK76: =VLOOKUP($E76,[2]Activities!$A$9:$I$162,4,FALSE)/$AH76 -> 0 | CL76: =VLOOKUP($E76,[2]Activities!$A$9:$I$162,5,FALSE)/$AH76 -> 0 | CM76: =VLOOKUP($E76,[2]Activities!$A$9:$I$162,6,FALSE)/$AH76 -> 0 | CN76: =VLOOKUP($E76,[2]Activities!$A$9:$I$162,7,FALSE)/$AH76 -> 0 | CO76: =VLOOKUP($E76,[2]Activities!$A$9:$I$162,8,FALSE)/$AH76 -> 0 | CP76: =VLOOKUP($E76,[2]Activities!$A$9:$I$162,9,FALSE)/$AH76 -> 0
A77: ICH01_15 | B77: Final | C77: Industry | D77: Chemicals | E77: Propylene production - Chemical Industry | F77: Propylene from ethanol dehydration, ethene dimerization and metathesis - Petrochemicals | G77: [Mton_Py/y] | H77: 1500 | I77: 1350 | J77: 1100 | K77: 1000 | L77: 950 | M77: 900 | N77: 850 | O77: 0.9 | P77: 34 | Q77: 34 | R77: 34 | S77: 34 | T77: 34 | U77: 34 | V77: 34 | W77: 0 | X77: 0 | Y77: 0 | Z77: 0 | AA77: 0 | AB77: 0 | AC77: 0 | AD77: 0.05 | AF77: 30 | AG77: 30 | AH77: 1 | AI77: Operation | AJ77: Flat low spread | AX77: none | BK77: 0 | BL77: =IF(AG77=1,0,1) -> 1 | BN77: 0 | BU77: =IF(BL77=1,BN77,0) -> 0 | CD77: 0.05 | CE77: 0.1 | CF77: 0.5 | CG77: 1 | CH77: 1.5 | CI77: [55],[67] | CJ77: =VLOOKUP($E77,[2]Activities!$A$9:$I$162,3,FALSE)/$AH77 -> 1.735 | CK77: =VLOOKUP($E77,[2]Activities!$A$9:$I$162,4,FALSE)/$AH77 -> 1.735 | CL77: =VLOOKUP($E77,[2]Activities!$A$9:$I$162,5,FALSE)/$AH77 -> 1.735 | CM77: =VLOOKUP($E77,[2]Activities!$A$9:$I$162,6,FALSE)/$AH77 -> 1.5962 | CN77: =VLOOKUP($E77,[2]Activities!$A$9:$I$162,7,FALSE)/$AH77 -> 1.3186 | CO77: =VLOOKUP($E77,[2]Activities!$A$9:$I$162,8,FALSE)/$AH77 -> 0.9022 | CP77: =VLOOKUP($E77,[2]Activities!$A$9:$I$162,9,FALSE)/$AH77 -> 0.694
A78: ICH01_16 | B78: Conversion | C78: Industry | D78: Chemicals | E78: Propylene production - Chemical Industry | F78: Propylene imports - Petrochemical industry | G78: [Mton_Py/y] | H78: 0 | I78: 0 | J78: 0 | K78: 0 | L78: 0 | M78: 0 | N78: 0 | O78: 0.9 | P78: 0 | Q78: 0 | R78: 0 | S78: 0 | T78: 0 | U78: 0 | V78: 0 | W78: 2000 | X78: 2500 | Y78: 3000 | Z78: 3500 | AA78: 4000 | AB78: 4500 | AC78: 5000 | AD78: 0.05 | AE78: 0 | AF78: 1 | AG78: 1 | AH78: 1 | AI78: Operation | AJ78: Flat | AX78: none | BK78: 0 | BL78: =IF(AG78=1,0,1) -> 0 | BU78: =IF(BL78=1,BN78,0) -> 0 | CB78: =CJ78 -> 1.735 | CC78: =CK78 -> 1.735 | CD78: =CL78 -> 1.735 | CE78: =CM78 -> 1.5962 | CF78: =CN78 -> 1.3186 | CG78: =CO78 -> 0.9022 | CH78: =CP78 -> 0.694 | CI78: [55] | CJ78: =VLOOKUP($E78,[2]Activities!$A$9:$I$162,3,FALSE)/$AH78 -> 1.735 | CK78: =VLOOKUP($E78,[2]Activities!$A$9:$I$162,4,FALSE)/$AH78 -> 1.735 | CL78: =VLOOKUP($E78,[2]Activities!$A$9:$I$162,5,FALSE)/$AH78 -> 1.735 | CM78: =VLOOKUP($E78,[2]Activities!$A$9:$I$162,6,FALSE)/$AH78 -> 1.5962 | CN78: =VLOOKUP($E78,[2]Activities!$A$9:$I$162,7,FALSE)/$AH78 -> 1.3186 | CO78: =VLOOKUP($E78,[2]Activities!$A$9:$I$162,8,FALSE)/$AH78 -> 0.9022 | CP78: =VLOOKUP($E78,[2]Activities!$A$9:$I$162,9,FALSE)/$AH78 -> 0.694
A79: ICH01_17 | B79: Conversion | C79: Industry | D79: Chemicals | E79: Other HVC production - Chemical Industry | F79: Other HVC imports - Petrochemical industry | G79: [Mton_HVC/y] | H79: 0 | I79: 0 | J79: 0 | K79: 0 | L79: 0 | M79: 0 | N79: 0 | O79: 0.9 | P79: 0 | Q79: 0 | R79: 0 | S79: 0 | T79: 0 | U79: 0 | V79: 0 | W79: 2000 | X79: 2500 | Y79: 3000 | Z79: 3500 | AA79: 4000 | AB79: 4500 | AC79: 5000 | AD79: 0.05 | AE79: 0 | AF79: 1 | AG79: 1 | AH79: 1 | AI79: Operation | AJ79: Flat | AX79: none | BK79: 0 | BL79: =IF(AG79=1,0,1) -> 0 | BU79: =IF(BL79=1,BN79,0) -> 0 | CB79: =CJ79 -> 0.6 | CC79: =CK79 -> 0.6 | CD79: =CL79 -> 0.6 | CE79: =CM79 -> 0.55 | CF79: =CN79 -> 0.48 | CG79: =CO79 -> 0.35 | CH79: =CP79 -> 0.3 | CI79: [55] | CJ79: =VLOOKUP($E79,[2]Activities!$A$9:$I$162,3,FALSE)/$AH79 -> 0.6 | CK79: =VLOOKUP($E79,[2]Activities!$A$9:$I$162,4,FALSE)/$AH79 -> 0.6 | CL79: =VLOOKUP($E79,[2]Activities!$A$9:$I$162,5,FALSE)/$AH79 -> 0.6 | CM79: =VLOOKUP($E79,[2]Activities!$A$9:$I$162,6,FALSE)/$AH79 -> 0.55 | CN79: =VLOOKUP($E79,[2]Activities!$A$9:$I$162,7,FALSE)/$AH79 -> 0.48 | CO79: =VLOOKUP($E79,[2]Activities!$A$9:$I$162,8,FALSE)/$AH79 -> 0.35 | CP79: =VLOOKUP($E79,[2]Activities!$A$9:$I$162,9,FALSE)/$AH79 -> 0.3
A80: ICH01_18 | B80: Final | C80: Industry | D80: Chemicals | E80: LDPE production - Chemical Industry | F80: High-pressure polymerisation of low-density polyethylene (LDPE) | G80: [Mton_LDPE/y] | H80: =(141*1.0658)/0.3 -> 500.926 | I80: =(141*1.0658)/0.3 -> 500.926 | J80: =(141*1.0658)/0.3 -> 500.926 | K80: =(141*1.0658)/0.3 -> 500.926 | L80: =(141*1.0658)/0.3 -> 500.926 | M80: =(141*1.0658)/0.3 -> 500.926 | N80: =(141*1.0658)/0.3 -> 500.926 | O80: 0.9 | P80: =H80*0.05 -> 25.0463 | Q80: =I80*0.05 -> 25.0463 | R80: =J80*0.05 -> 25.0463 | S80: =K80*0.05 -> 25.0463 | T80: =L80*0.05 -> 25.0463 | U80: =M80*0.05 -> 25.0463 | V80: =N80*0.05 -> 25.0463 | W80: =(18*1.0658) -> 19.1844 | X80: =(18*1.0658) -> 19.1844 | Y80: =(18*1.0658) -> 19.1844 | Z80: =(18*1.0658) -> 19.1844 | AA80: =(18*1.0658) -> 19.1844 | AB80: =(18*1.0658) -> 19.1844 | AC80: =(18*1.0658) -> 19.1844 | AD80: 0.05 | AF80: 25 | AG80: 25 | AH80: 1 | AI80: Operation | AJ80: Flat | AX80: none | BL80: 1 | BN80: =CJ80 -> 0.73 | BO80: =BN80 -> 0.73 | BP80: =BO80 -> 0.73 | BQ80: =BP80 -> 0.73 | BR80: =BQ80 -> 0.73 | BU80: =IF(BL80=1,BN80,0) -> 0.73 | CB80: 5 | CC80: 5 | CD80: 5 | CE80: 5 | CF80: 5 | CG80: 5 | CH80: 5 | CI80: [D] | CJ80: =VLOOKUP($E80,[2]Activities!$A$9:$I$199,3,FALSE)/$AH80 -> 0.73 | CK80: =VLOOKUP($E80,[2]Activities!$A$9:$I$199,4,FALSE)/$AH80 -> 0.73 | CL80: =VLOOKUP($E80,[2]Activities!$A$9:$I$199,5,FALSE)/$AH80 -> 0.73 | CM80: =VLOOKUP($E80,[2]Activities!$A$9:$I$199,6,FALSE)/$AH80 -> 0.6935 | CN80: =VLOOKUP($E80,[2]Activities!$A$9:$I$199,7,FALSE)/$AH80 -> 0.60225 | CO80: =VLOOKUP($E80,[2]Activities!$A$9:$I$199,8,FALSE)/$AH80 -> 0.45625 | CP80: =VLOOKUP($E80,[2]Activities!$A$9:$I$199,9,FALSE)/$AH80 -> 0.365
A81: ICH01_19 | B81: Final | C81: Industry | D81: Chemicals | E81: LLDPE production - Chemical Industry | F81: Solution polymerisation of linear low-density polyethylene (LLDPE) | G81: [Mton_LLDPE/y] | H81: =(154*1.0658)/0.25 -> 656.5328 | I81: =(154*1.0658)/0.25 -> 656.5328 | J81: =(154*1.0658)/0.25 -> 656.5328 | K81: =(154*1.0658)/0.25 -> 656.5328 | L81: =(154*1.0658)/0.25 -> 656.5328 | M81: =(154*1.0658)/0.25 -> 656.5328 | N81: =(154*1.0658)/0.25 -> 656.5328 | O81: 0.9 | P81: =H81*0.05 -> 32.82664 | Q81: =I81*0.05 -> 32.82664 | R81: =J81*0.05 -> 32.82664 | S81: =K81*0.05 -> 32.82664 | T81: =L81*0.05 -> 32.82664 | U81: =M81*0.05 -> 32.82664 | V81: =N81*0.05 -> 32.82664 | W81: =(36*1.0658) -> 38.3688 | X81: =(36*1.0658) -> 38.3688 | Y81: =(36*1.0658) -> 38.3688 | Z81: =(36*1.0658) -> 38.3688 | AA81: =(36*1.0658) -> 38.3688 | AB81: =(36*1.0658) -> 38.3688 | AC81: =(36*1.0658) -> 38.3688 | AD81: 0.05 | AF81: 25 | AG81: 25 | AH81: 1 | AI81: Operation | AJ81: Flat | AX81: none | BL81: 1 | BN81: =CJ81 -> 0.8 | BO81: =BN81 -> 0.8 | BP81: =BO81 -> 0.8 | BQ81: =BP81 -> 0.8 | BR81: =BQ81 -> 0.8 | BU81: =IF(BL81=1,BN81,0) -> 0.8 | CB81: 5 | CC81: 5 | CD81: 5 | CE81: 5 | CF81: 5 | CG81: 5 | CH81: 5 | CI81: [D] | CJ81: =VLOOKUP($E81,[2]Activities!$A$9:$I$199,3,FALSE)/$AH81 -> 0.8 | CK81: =VLOOKUP($E81,[2]Activities!$A$9:$I$199,4,FALSE)/$AH81 -> 0.8 | CL81: =VLOOKUP($E81,[2]Activities!$A$9:$I$199,5,FALSE)/$AH81 -> 0.8 | CM81: =VLOOKUP($E81,[2]Activities!$A$9:$I$199,6,FALSE)/$AH81 -> 0.76 | CN81: =VLOOKUP($E81,[2]Activities!$A$9:$I$199,7,FALSE)/$AH81 -> 0.66 | CO81: =VLOOKUP($E81,[2]Activities!$A$9:$I$199,8,FALSE)/$AH81 -> 0.5 | CP81: =VLOOKUP($E81,[2]Activities!$A$9:$I$199,9,FALSE)/$AH81 -> 0.4
A82: ICH01_20 | B82: Final | C82: Industry | D82: Chemicals | E82: HDPE production - Chemical Industry | F82: Suspension/slurry polymerisation of high-density polyethylene (HDPE) | G82: [Mton_HDPE/y] | H82: =(AVERAGE(108,138)*1.0658)/0.2 -> 655.467 | I82: =(AVERAGE(108,138)*1.0658)/0.2 -> 655.467 | J82: =(AVERAGE(108,138)*1.0658)/0.2 -> 655.467 | K82: =(AVERAGE(108,138)*1.0658)/0.2 -> 655.467 | L82: =(AVERAGE(108,138)*1.0658)/0.2 -> 655.467 | M82: =(AVERAGE(108,138)*1.0658)/0.2 -> 655.467 | N82: =(AVERAGE(108,138)*1.0658)/0.2 -> 655.467 | O82: 0.9 | P82: =H82*0.05 -> 32.77335 | Q82: =I82*0.05 -> 32.77335 | R82: =J82*0.05 -> 32.77335 | S82: =K82*0.05 -> 32.77335 | T82: =L82*0.05 -> 32.77335 | U82: =M82*0.05 -> 32.77335 | V82: =N82*0.05 -> 32.77335 | W82: =(AVERAGE(30,30)*1.0658) -> 31.974 | X82: =(AVERAGE(30,30)*1.0658) -> 31.974 | Y82: =(AVERAGE(30,30)*1.0658) -> 31.974 | Z82: =(AVERAGE(30,30)*1.0658) -> 31.974 | AA82: =(AVERAGE(30,30)*1.0658) -> 31.974 | AB82: =(AVERAGE(30,30)*1.0658) -> 31.974 | AC82: =(AVERAGE(30,30)*1.0658) -> 31.974 | AD82: 0.05 | AF82: 25 | AG82: 25 | AH82: 1 | AI82: Operation | AJ82: Flat | AX82: none | BL82: 1 | BN82: =CJ82 -> 0.31 | BO82: =BN82 -> 0.31 | BP82: =BO82 -> 0.31 | BQ82: =BP82 -> 0.31 | BR82: =BQ82 -> 0.31 | BU82: =IF(BL82=1,BN82,0) -> 0.31 | CB82: 5 | CC82: 5 | CD82: 5 | CE82: 5 | CF82: 5 | CG82: 5 | CH82: 5 | CI82: [D] | CJ82: =VLOOKUP($E82,[2]Activities!$A$9:$I$199,3,FALSE)/$AH82 -> 0.31 | CK82: =VLOOKUP($E82,[2]Activities!$A$9:$I$199,4,FALSE)/$AH82 -> 0.31 | CL82: =VLOOKUP($E82,[2]Activities!$A$9:$I$199,5,FALSE)/$AH82 -> 0.31 | CM82: =VLOOKUP($E82,[2]Activities!$A$9:$I$199,6,FALSE)/$AH82 -> 0.2945 | CN82: =VLOOKUP($E82,[2]Activities!$A$9:$I$199,7,FALSE)/$AH82 -> 0.25575 | CO82: =VLOOKUP($E82,[2]Activities!$A$9:$I$199,8,FALSE)/$AH82 -> 0.19375 | CP82: =VLOOKUP($E82,[2]Activities!$A$9:$I$199,9,FALSE)/$AH82 -> 0.155
A83: ICH01_21 | B83: Final | C83: Industry | D83: Chemicals | E83: Polypropylene production - Chemical Industry | F83: Gas-phase polymerisation of polypropylene (PP) | G83: [Mton_PP/y] | H83: =(AVERAGE(90/0.2,114/0.25)*1.0658) -> 482.8074 | I83: =(AVERAGE(90/0.2,114/0.25)*1.0658) -> 482.8074 | J83: =(AVERAGE(90/0.2,114/0.25)*1.0658) -> 482.8074 | K83: =(AVERAGE(90/0.2,114/0.25)*1.0658) -> 482.8074 | L83: =(AVERAGE(90/0.2,114/0.25)*1.0658) -> 482.8074 | M83: =(AVERAGE(90/0.2,114/0.25)*1.0658) -> 482.8074 | N83: =(AVERAGE(90/0.2,114/0.25)*1.0658) -> 482.8074 | O83: 0.9 | P83: =H83*0.05 -> 24.14037 | Q83: =I83*0.05 -> 24.14037 | R83: =J83*0.05 -> 24.14037 | S83: =K83*0.05 -> 24.14037 | T83: =L83*0.05 -> 24.14037 | U83: =M83*0.05 -> 24.14037 | V83: =N83*0.05 -> 24.14037 | W83: =(AVERAGE(36,30)*1.0658) -> 35.1714 | X83: =(AVERAGE(36,30)*1.0658) -> 35.1714 | Y83: =(AVERAGE(36,30)*1.0658) -> 35.1714 | Z83: =(AVERAGE(36,30)*1.0658) -> 35.1714 | AA83: =(AVERAGE(36,30)*1.0658) -> 35.1714 | AB83: =(AVERAGE(36,30)*1.0658) -> 35.1714 | AC83: =(AVERAGE(36,30)*1.0658) -> 35.1714 | AD83: 0.05 | AF83: 25 | AG83: 25 | AH83: 1 | AI83: Operation | AJ83: Flat | AX83: none | BL83: 1 | BN83: =CJ83 -> 0.75 | BO83: =BN83 -> 0.75 | BP83: =BO83 -> 0.75 | BQ83: =BP83 -> 0.75 | BR83: =BQ83 -> 0.75 | BU83: =IF(BL83=1,BN83,0) -> 0.75 | CB83: 5 | CC83: 5 | CD83: 5 | CE83: 5 | CF83: 5 | CG83: 5 | CH83: 5 | CI83: [D] | CJ83: =VLOOKUP($E83,[2]Activities!$A$9:$I$199,3,FALSE)/$AH83 -> 0.75 | CK83: =VLOOKUP($E83,[2]Activities!$A$9:$I$199,4,FALSE)/$AH83 -> 0.75 | CL83: =VLOOKUP($E83,[2]Activities!$A$9:$I$199,5,FALSE)/$AH83 -> 0.75 | CM83: =VLOOKUP($E83,[2]Activities!$A$9:$I$199,6,FALSE)/$AH83 -> 0.69 | CN83: =VLOOKUP($E83,[2]Activities!$A$9:$I$199,7,FALSE)/$AH83 -> 0.57 | CO83: =VLOOKUP($E83,[2]Activities!$A$9:$I$199,8,FALSE)/$AH83 -> 0.39 | CP83: =VLOOKUP($E83,[2]Activities!$A$9:$I$199,9,FALSE)/$AH83 -> 0.3
A84: ICH01_22 | B84: Final | C84: Industry | D84: Chemicals | E84: Propylene production - chemical industry | F84: Dummy - conversion of propylene use to propylene final | G84: [Mton_Py/y] | H84: 0 | I84: 0 | J84: 0 | K84: 0 | L84: 0 | M84: 0 | N84: 0 | O84: 0 | P84: 0 | Q84: 0 | R84: 0 | S84: 0 | T84: 0 | U84: 0 | V84: 0 | W84: 0 | X84: 0 | Y84: 0 | Z84: 0 | AA84: 0 | AB84: 0 | AC84: 0 | AD84: 0.05 | AF84: 25 | AG84: 25 | AH84: 1 | AI84: Operation | AJ84: Flat | AX84: none | BL84: 1 | BN84: =CJ84 -> 1.735 | BO84: =BN84 -> 1.735 | BP84: =BO84 -> 1.735 | BQ84: =BP84 -> 1.735 | BR84: =BQ84 -> 1.735 | CB84: 10 | CC84: 10 | CD84: 10 | CE84: 10 | CF84: 10 | CG84: 10 | CH84: 10 | CI84: [D] | CJ84: =VLOOKUP($E84,[2]Activities!$A$9:$I$199,3,FALSE)/$AH84 -> 1.735 | CK84: =VLOOKUP($E84,[2]Activities!$A$9:$I$199,4,FALSE)/$AH84 -> 1.735 | CL84: =VLOOKUP($E84,[2]Activities!$A$9:$I$199,5,FALSE)/$AH84 -> 1.735 | CM84: =VLOOKUP($E84,[2]Activities!$A$9:$I$199,6,FALSE)/$AH84 -> 1.5962 | CN84: =VLOOKUP($E84,[2]Activities!$A$9:$I$199,7,FALSE)/$AH84 -> 1.3186 | CO84: =VLOOKUP($E84,[2]Activities!$A$9:$I$199,8,FALSE)/$AH84 -> 0.9022 | CP84: =VLOOKUP($E84,[2]Activities!$A$9:$I$199,9,FALSE)/$AH84 -> 0.694
A85: ICH01_23 | B85: Final | C85: Industry | D85: Chemicals | E85: Ethylene production - chemical industry | F85: Dummy - conversion of ethylene use to ethylene final | G85: [Mton_Ey/y] | H85: 0 | I85: 0 | J85: 0 | K85: 0 | L85: 0 | M85: 0 | N85: 0 | O85: 0 | P85: 0 | Q85: 0 | R85: 0 | S85: 0 | T85: 0 | U85: 0 | V85: 0 | W85: 0 | X85: 0 | Y85: 0 | Z85: 0 | AA85: 0 | AB85: 0 | AC85: 0 | AD85: 0.05 | AF85: 25 | AG85: 25 | AH85: 1 | AI85: Operation | AJ85: Flat | AX85: none | BL85: 1 | BN85: =CJ85 -> 1.5003866 | BO85: =BN85 -> 1.5003866 | BP85: =BO85 -> 1.5003866 | BQ85: =BP85 -> 1.5003866 | BR85: =BQ85 -> 1.5003866 | CB85: 10 | CC85: 10 | CD85: 10 | CE85: 10 | CF85: 10 | CG85: 10 | CH85: 10 | CI85: [D] | CJ85: =VLOOKUP($E85,[2]Activities!$A$9:$I$199,3,FALSE)/$AH85 -> 1.5003866 | CK85: =VLOOKUP($E85,[2]Activities!$A$9:$I$199,4,FALSE)/$AH85 -> 1.4899537 | CL85: =VLOOKUP($E85,[2]Activities!$A$9:$I$199,5,FALSE)/$AH85 -> 1.4795208 | CM85: =VLOOKUP($E85,[2]Activities!$A$9:$I$199,6,FALSE)/$AH85 -> 1.353725 | CN85: =VLOOKUP($E85,[2]Activities!$A$9:$I$199,7,FALSE)/$AH85 -> 1.0288025 | CO85: =VLOOKUP($E85,[2]Activities!$A$9:$I$199,8,FALSE)/$AH85 -> 0.50475346 | CP85: =VLOOKUP($E85,[2]Activities!$A$9:$I$199,9,FALSE)/$AH85 -> 0.24242846
A86: ICH01_24 | B86: Final | C86: Industry | D86: Chemicals | E86: PTA production - Chemical Industry | F86: Dummy - conversion of PTA intermediate to PTA final | G86: [Mton_PTA/y] | H86: 0 | I86: 0 | J86: 0 | K86: 0 | L86: 0 | M86: 0 | N86: 0 | O86: 0 | P86: 0 | Q86: 0 | R86: 0 | S86: 0 | T86: 0 | U86: 0 | V86: 0 | W86: 0 | X86: 0 | Y86: 0 | Z86: 0 | AA86: 0 | AB86: 0 | AC86: 0 | AD86: 0.05 | AF86: 25 | AG86: 25 | AH86: 1 | AI86: Operation | AJ86: Flat | AX86: none | BL86: 1 | BN86: =CJ86 -> 0.34216 | BO86: =BN86 -> 0.34216 | BP86: =BO86 -> 0.34216 | BQ86: =BP86 -> 0.34216 | BR86: =BQ86 -> 0.34216 | CB86: 10 | CC86: 10 | CD86: 10 | CE86: 10 | CF86: 10 | CG86: 10 | CH86: 10 | CI86: [D] | CJ86: =VLOOKUP($E86,[2]Activities!$A$9:$I$199,3,FALSE)/$AH86 -> 0.34216 | CK86: =VLOOKUP($E86,[2]Activities!$A$9:$I$199,4,FALSE)/$AH86 -> 0.34216 | CL86: =VLOOKUP($E86,[2]Activities!$A$9:$I$199,5,FALSE)/$AH86 -> 0.34216 | CM86: =VLOOKUP($E86,[2]Activities!$A$9:$I$199,6,FALSE)/$AH86 -> 0.34216 | CN86: =VLOOKUP($E86,[2]Activities!$A$9:$I$199,7,FALSE)/$AH86 -> 0.34216 | CO86: =VLOOKUP($E86,[2]Activities!$A$9:$I$199,8,FALSE)/$AH86 -> 0.34216 | CP86: =VLOOKUP($E86,[2]Activities!$A$9:$I$199,9,FALSE)/$AH86 -> 0.34216
A87: ICH01_25 | B87: Conversion | C87: Industry | D87: Chemicals | E87: PTA intermediate | F87: Paraxylene oxidation and crystallization | G87: [Mton_PTA/y] | H87: =H82 -> 655.467 | I87: =I82 -> 655.467 | J87: =J82 -> 655.467 | K87: =K82 -> 655.467 | L87: =L82 -> 655.467 | M87: =M82 -> 655.467 | N87: =N82 -> 655.467 | O87: 0.9 | P87: =H87*0.05 -> 32.77335 | Q87: =I87*0.05 -> 32.77335 | R87: =J87*0.05 -> 32.77335 | S87: =K87*0.05 -> 32.77335 | T87: =L87*0.05 -> 32.77335 | U87: =M87*0.05 -> 32.77335 | V87: =N87*0.05 -> 32.77335 | W87: =W82 -> 31.974 | X87: =X82 -> 31.974 | Y87: =Y82 -> 31.974 | Z87: =Z82 -> 31.974 | AA87: =AA82 -> 31.974 | AB87: =AB82 -> 31.974 | AC87: =AC82 -> 31.974 | AD87: 0.05 | AF87: 25 | AG87: 25 | AH87: 1 | AI87: Operation | AJ87: Flat | AX87: none | BL87: 1 | BN87: =BN86+0.84*[2]Activities!C34 -> 0.7 | BO87: =BN87 -> 0.7 | BP87: =BO87 -> 0.7 | BQ87: =BP87 -> 0.7 | BR87: =BQ87 -> 0.7 | CB87: 10 | CC87: 10 | CD87: 10 | CE87: 10 | CF87: 10 | CG87: 10 | CH87: 10 | CI87: [D] | CJ87: =VLOOKUP($E87,[2]Activities!$A$9:$I$199,3,FALSE)/$AH87 -> 0 | CK87: =VLOOKUP($E87,[2]Activities!$A$9:$I$199,4,FALSE)/$AH87 -> 0 | CL87: =VLOOKUP($E87,[2]Activities!$A$9:$I$199,5,FALSE)/$AH87 -> 0 | CM87: =VLOOKUP($E87,[2]Activities!$A$9:$I$199,6,FALSE)/$AH87 -> 0 | CN87: =VLOOKUP($E87,[2]Activities!$A$9:$I$199,7,FALSE)/$AH87 -> 0 | CO87: =VLOOKUP($E87,[2]Activities!$A$9:$I$199,8,FALSE)/$AH87 -> 0 | CP87: =VLOOKUP($E87,[2]Activities!$A$9:$I$199,9,FALSE)/$AH87 -> 0
A88: ICH01_26 | B88: Conversion | C88: Industry | D88: Chemicals | E88: Polyethylene terephthalate (PET) | F88: Polymerization to PET (PTA & MEG) | G88: [Mton_PET/y] | H88: =(141*1.0658)/0.3 -> 500.926 | I88: =(141*1.0658)/0.3 -> 500.926 | J88: =(141*1.0658)/0.3 -> 500.926 | K88: =(141*1.0658)/0.3 -> 500.926 | L88: =(141*1.0658)/0.3 -> 500.926 | M88: =(141*1.0658)/0.3 -> 500.926 | N88: =(141*1.0658)/0.3 -> 500.926 | O88: 0.9 | P88: =H88*0.05 -> 25.0463 | Q88: =I88*0.05 -> 25.0463 | R88: =J88*0.05 -> 25.0463 | S88: =K88*0.05 -> 25.0463 | T88: =L88*0.05 -> 25.0463 | U88: =M88*0.05 -> 25.0463 | V88: =N88*0.05 -> 25.0463 | W88: =(18*1.0658) -> 19.1844 | X88: =(18*1.0658) -> 19.1844 | Y88: =(18*1.0658) -> 19.1844 | Z88: =(18*1.0658) -> 19.1844 | AA88: =(18*1.0658) -> 19.1844 | AB88: =(18*1.0658) -> 19.1844 | AC88: =(18*1.0658) -> 19.1844 | AD88: 0.05 | AF88: 25 | AG88: 25 | AH88: 1 | AI88: Operation | AJ88: Flat | AX88: none | BL88: 1 | BN88: =[2]Activities!C34 -> 0.426 | BO88: =BN88 -> 0.426 | BP88: =BO88 -> 0.426 | BQ88: =BP88 -> 0.426 | BR88: =BQ88 -> 0.426 | CB88: 5 | CC88: 5 | CD88: 5 | CE88: 5 | CF88: 5 | CG88: 5 | CH88: 5 | CI88: [D]
A89: ICH01_27 | B89: Final | C89: Industry | D89: Chemicals | E89: PVC production - Chemical Industry | F89: VCM production and polymerisation to PVC | G89: [Mton_PVC/y] | H89: =(AVERAGE(108,138)*1.0658)/0.2 -> 655.467 | I89: =(AVERAGE(108,138)*1.0658)/0.2 -> 655.467 | J89: =(AVERAGE(108,138)*1.0658)/0.2 -> 655.467 | K89: =(AVERAGE(108,138)*1.0658)/0.2 -> 655.467 | L89: =(AVERAGE(108,138)*1.0658)/0.2 -> 655.467 | M89: =(AVERAGE(108,138)*1.0658)/0.2 -> 655.467 | N89: =(AVERAGE(108,138)*1.0658)/0.2 -> 655.467 | O89: 0.9 | P89: =H89*0.05 -> 32.77335 | Q89: =I89*0.05 -> 32.77335 | R89: =J89*0.05 -> 32.77335 | S89: =K89*0.05 -> 32.77335 | T89: =L89*0.05 -> 32.77335 | U89: =M89*0.05 -> 32.77335 | V89: =N89*0.05 -> 32.77335 | W89: =(AVERAGE(30,30)*1.0658) -> 31.974 | X89: =(AVERAGE(30,30)*1.0658) -> 31.974 | Y89: =(AVERAGE(30,30)*1.0658) -> 31.974 | Z89: =(AVERAGE(30,30)*1.0658) -> 31.974 | AA89: =(AVERAGE(30,30)*1.0658) -> 31.974 | AB89: =(AVERAGE(30,30)*1.0658) -> 31.974 | AC89: =(AVERAGE(30,30)*1.0658) -> 31.974 | AD89: 0.05 | AF89: 25 | AG89: 25 | AH89: 1 | AI89: Operation | AJ89: Flat | AX89: none | BL89: 1 | BN89: =CJ89 -> 0.75 | BO89: =BN89 -> 0.75 | BU89: =IF(BL89=1,BN89,0) -> 0.75 | CB89: 5 | CC89: 5 | CD89: 5 | CE89: 5 | CF89: 5 | CG89: 5 | CH89: 5 | CI89: [D] | CJ89: =VLOOKUP($E89,[2]Activities!$A$9:$I$199,3,FALSE)/$AH89 -> 0.75 | CK89: =VLOOKUP($E89,[2]Activities!$A$9:$I$199,4,FALSE)/$AH89 -> 0.75 | CL89: =VLOOKUP($E89,[2]Activities!$A$9:$I$199,5,FALSE)/$AH89 -> 0.75 | CM89: =VLOOKUP($E89,[2]Activities!$A$9:$I$199,6,FALSE)/$AH89 -> 0.75 | CN89: =VLOOKUP($E89,[2]Activities!$A$9:$I$199,7,FALSE)/$AH89 -> 0.75 | CO89: =VLOOKUP($E89,[2]Activities!$A$9:$I$199,8,FALSE)/$AH89 -> 0.75 | CP89: =VLOOKUP($E89,[2]Activities!$A$9:$I$199,9,FALSE)/$AH89 -> 0.75
